Workbook

Sheet Read Me
A1: Arab Bank – EWRA Platform: Inherent Risk Rating Calculator
A2: Companion to the EWRA Platform Scope Document v1.0 (§7 taxonomy, §8 inherent risk methodology, §12 risk appetite). Classification: Confidential – Internal Use Only.
A4: Purpose | B4: Calculates the inherent risk rating (before controls) for all 20 Level-1 risks across 30 group entities, using the two methods in Scope Document §8: a factor-based model for financial-crime risks (FC-01 to FC-07) and a likelihood × impact model for regulatory and enterprise risks (RC-01 to ER-09).
A5: Status of data | B5: All entity data, indicator values and likelihood/impact scores are ILLUSTRATIVE SAMPLE DATA for design and testing. Entity names, tiers and thresholds are proposed defaults to be confirmed by Group Compliance and Group Risk during Discovery.
A6: Calculation flow | B6: 1. Config sets scales, bands, aggregation method and LxI parameters. 2. Factor Weights sets the 5 factor weights per FC risk. 3. Indicators holds the indicator library, score thresholds and per-risk indicator weights. 4. Indicator Data holds raw values per entity. 5. Indicator Scores converts each value to a 1–5 score. 6. FC Calculation builds factor scores and the inherent score for 7 FC risks × 30 entities. 7. LxI Assessment scores 13 risks × 30 entities. 8. Inherent Summary, Dashboard and Checks consolidate and validate.
A7: Factor model | B7: Indicator score: 1 if below the 'Score 2 from' threshold, rising by one for each threshold met (max 5). Factor score = weighted average of indicator scores within the factor (indicator weights are relative, per risk; indicators with no data are excluded and the remainder reweighted, unless Config says otherwise). Inherent score = Σ factor weight × factor score, then the Config aggregation method is applied (weighted average, weighted with floor, or maximum).
A8: Floor rule | B8: With 'Weighted with floor', if any single factor scores at or above the trigger (default 5), the inherent score cannot be below the floor (default 4.00 = Medium-High). This stops one severe factor being averaged away.
A9: LxI model | B9: Impact = highest of the four impact dimensions (or weighted average, per Config). Inherent product = Likelihood × Impact (1–25), mapped to the 5-point scale using the L×I bands in Config. RC-04 Shariah applies only to entities flagged Islamic.
A10: Overrides | B10: A calculated rating may be moved by up to the Config maximum (default ±1 notch). The override applies only when 'HO approval' = Y, matching the maker-checker rule in Scope Document §8.4 and §13.4. Every override needs a justification.
A11: Colour legend | B11: Blue text on light-yellow fill = input you may edit. Black text = formula, do not edit. Green text = link to another sheet. Rating colours: green Low, light green Medium-Low, yellow Medium, orange Medium-High, red High.
A13: Sheet | B13: What it holds | C13: Edit?
A14: Config | B14: Rating scale, score bands, aggregation method, missing-data rule, LxI parameters, override limit | C14: Yes – yellow cells
A15: Entities | B15: 30 group entities with region, type, tier, Islamic flag and aggregation weight | C15: Yes – yellow cells
A16: Risk Taxonomy | B16: 20 Level-1 risks, domain, method, owner and appetite reference | C16: Reference
A17: Factor Weights | B17: Factor weights for the 7 financial-crime risks (each row must total 100%) | C17: Yes – yellow cells
A18: Indicators | B18: 31 indicators: factor, unit, source, direction, thresholds and relative weight per FC risk | C18: Yes – yellow cells
A19: Indicator Data | B19: Raw indicator values for each entity (one column per entity) | C19: Yes – yellow cells
A20: Indicator Scores | B20: 1–5 score for every indicator and entity | C20: No – formulas
A21: FC Calculation | B21: Factor scores, inherent score and rating for 7 FC risks × 30 entities, with overrides | C21: Override columns only
A22: LxI Assessment | B22: Likelihood, impact dimensions, product and rating for 13 risks × 30 entities, with overrides | C22: Yellow cells
A23: Inherent Summary | B23: Heat map of final inherent rating: 30 entities × 20 risks, with group averages | C23: No – formulas
A24: Dashboard | B24: Headline figures and charts of group inherent risk | C24: No – formulas
A25: Checks | B25: Validation of weights, thresholds, coverage, inputs and overrides | C25: No – formulas

Sheet Config
A1: Configuration
A2: Head Office Administrator settings. Changes here flow through every calculation. Yellow cells are editable.
A3: 1. Rating scale and score bands | H3: Lists (used by drop-downs)
A4: Score | B4: Rating | C4: Colour | D4: Factor model: inherent score from | E4: L×I model: product from
A5: 1 | B5: Low | C5: Green | D5: 1 | E5: 1 | H5: Weighted average
A6: 2 | B6: Medium-Low | C6: Light green | D6: 1.81 | E6: 5 | H6: Weighted with floor
A7: 3 | B7: Medium | C7: Amber | D7: 2.61 | E7: 9 | H7: Maximum (worst-of)
A8: 4 | B8: Medium-High | C8: Orange | D8: 3.41 | E8: 13
A9: 5 | B9: High | C9: Red | D9: 4.21 | E9: 20 | H9: Exclude and reweight
H10: Score as High (5)
A11: 2. Factor model (FC-01 to FC-07)
A12: Aggregation method | C12: Weighted with floor | D12: Weighted average | Weighted with floor | Maximum (worst-of). Scope Document §8.4. | H12: Highest dimension
A13: Floor trigger: any factor score at or above | C13: 5 | D13: Used only with 'Weighted with floor'. | H13: Weighted average
A14: Floor: minimum inherent score when triggered | C14: 4 | D14: Default 4.00 = Medium-High.
A15: Missing indicator data | C15: Exclude and reweight | D15: Exclude and reweight | Score as High (5). Conservative option scores missing data as 5. | H15: Y
H16: N
A18: 3. Likelihood × impact model (RC-01 to ER-09) | H18: Customer
A19: Impact aggregation | C19: Highest dimension | D19: Highest dimension | Weighted average. Scope Document §8.3 default is highest dimension. | H19: Geography
A20: Financial impact weight | C20: 0.35 | H20: Products & services
A21: Regulatory impact weight | C21: 0.3 | H21: Delivery channels
A22: Reputational impact weight | C22: 0.2 | H22: Transactions & volumes
A23: Customer / operational impact weight | C23: 0.15
A24: Total (must be 100%) | C24: =SUM(C20:C23) -> 1 | D24: Used only with 'Weighted average'. Proposed default weights. | H24: Higher = riskier
H25: Lower = riskier
A26: 4. Override governance
A27: Maximum override (notches) | C27: 1 | D27: Scope Document §8.4: up to one notch, with justification and HO approval.

Sheet Entities
A1: Entity register (illustrative – confirm in Discovery)
A2: Per Scope Document §5.3–5.5. Aggregation weight drives the group weighted average (default: Tier 1 = 3, Tier 2 = 2, Tier 3 = 1).
A4: Entity code | B4: Entity | C4: Country | D4: Region | E4: Entity type | F4: Tier | G4: Islamic (Y/N) | H4: Profile (sample data only) | I4: Aggregation weight
A5: JO-HO | B5: Arab Bank plc – Jordan (HO and domestic network) | C5: Jordan | D5: Jordan (home) | E5: Head Office / branches | F5: Tier 1 | G5: N | H5: Medium | I5: 3
A6: JO-IIAB | B6: Islamic International Arab Bank | C6: Jordan | D6: Jordan (home) | E6: Subsidiary – Islamic bank | F6: Tier 1 | G6: Y | H6: Medium | I6: 3
A7: JO-INV | B7: Al-Arabi Investment Group (AB Invest) | C7: Jordan | D7: Jordan (home) | E7: Subsidiary – investment | F7: Tier 3 | G7: N | H7: Medium | I7: 1
A8: JO-INS | B8: Insurance subsidiary – Jordan | C8: Jordan | D8: Jordan (home) | E8: Subsidiary – insurance | F8: Tier 3 | G8: N | H8: Medium | I8: 1
A9: JO-LSG | B9: Leasing subsidiary – Jordan | C9: Jordan | D9: Jordan (home) | E9: Subsidiary – leasing | F9: Tier 3 | G9: N | H9: Medium | I9: 1
A10: PS | B10: Arab Bank – Palestine | C10: Palestine | D10: Levant | E10: Foreign branch | F10: Tier 1 | G10: N | H10: Higher | I10: 3
A11: PS-INV | B11: Al-Arabi Investment Group – Palestine | C11: Palestine | D11: Levant | E11: Subsidiary – investment | F11: Tier 3 | G11: N | H11: Higher | I11: 1
A12: LB | B12: Arab Bank – Lebanon | C12: Lebanon | D12: Levant | E12: Foreign branch | F12: Tier 2 | G12: N | H12: Higher | I12: 2
A13: SY | B13: Arab Bank – Syria | C13: Syria | D13: Levant | E13: Subsidiary – bank | F13: Tier 2 | G13: N | H13: Higher | I13: 2
A14: AE | B14: Arab Bank – UAE | C14: UAE | D14: GCC | E14: Foreign branch | F14: Tier 1 | G14: N | H14: Medium | I14: 3
A15: BH | B15: Arab Bank – Bahrain | C15: Bahrain | D15: GCC | E15: Foreign branch | F15: Tier 2 | G15: N | H15: Medium | I15: 2
A16: QA | B16: Arab Bank – Qatar | C16: Qatar | D16: GCC | E16: Foreign branch | F16: Tier 2 | G16: N | H16: Medium | I16: 2
... A34: US | B34: Arab Bank – United States (if retained) | C34: United States | D34: Americas | E34: Foreign branch | F34: Tier 3 | G34: N | H34: Lower | I34: 1

Sheet Risk Taxonomy
A1: Level-1 risk taxonomy
A2: Scope Document §7 (taxonomy) and §12 (appetite). Appetite applies to residual risk and is shown here for reference.
A4: Code | B4: Level-1 risk | C4: Domain | D4: Inherent method | E4: Group owner | F4: Applies to | G4: Appetite level | H4: Max acceptable residual rating
A5: FC-01 | B5: Money laundering | C5: A – Financial crime | D5: Factor-based | E5: Group MLRO | F5: All entities | G5: Very low | H5: Medium-Low
A6: FC-02 | B6: Terrorist financing | C6: A – Financial crime | D6: Factor-based | E6: Group MLRO | F6: All entities | G6: Zero tolerance | H6: Low
A7: FC-03 | B7: Proliferation financing | C7: A – Financial crime | D7: Factor-based | E7: Group MLRO | F7: All entities | G7: Zero tolerance | H7: Low
A8: FC-04 | B8: Sanctions | C8: A – Financial crime | D8: Factor-based | E8: Head of Group Sanctions | F8: All entities | G8: Zero tolerance | H8: Low
A9: FC-05 | B9: Bribery and corruption | C9: A – Financial crime | D9: Factor-based | E9: Group CCO | F9: All entities | G9: Zero tolerance | H9: Low
A10: FC-06 | B10: Fraud | C10: A – Financial crime | D10: Factor-based | E10: Head of Fraud Risk | F10: All entities | G10: Low | H10: Medium
A11: FC-07 | B11: Tax evasion and tax transparency | C11: A – Financial crime | D11: Factor-based | E11: Group CCO | F11: All entities | G11: Zero tolerance (facilitation) | H11: Low
A12: RC-01 | B12: Regulatory compliance | C12: B – Regulatory and conduct | D12: Likelihood × impact | E12: Group CCO | F12: All entities | G12: Very low | H12: Medium-Low
A13: RC-02 | B13: Conduct and consumer protection | C13: B – Regulatory and conduct | D13: Likelihood × impact | E13: Group CCO | F13: All entities | G13: Low | H13: Medium
A14: RC-03 | B14: Data protection and privacy | C14: B – Regulatory and conduct | D14: Likelihood × impact | E14: Group DPO | F14: All entities | G14: Very low | H14: Medium-Low
A15: RC-04 | B15: Shariah non-compliance | C15: B – Regulatory and conduct | D15: Likelihood × impact | E15: Shariah Supervisory Board Secretary | F15: Islamic entities only | G15: Very low | H15: Medium-Low
... A24: ER-09 | B24: Strategic, business model and ESG | C24: C – Enterprise | D24: Likelihood × impact | E24: Group Head of Strategy / Sustainability | F24: All entities | G24: Moderate | H24: Medium-High

Sheet Factor Weights
A1: Factor weights – financial-crime risks
A2: Scope Document §8.2. Each row must total 100%; the ML row is the documented default, other rows are proposed defaults.
A4: Code | B4: Risk | C4: Customer | D4: Geography | E4: Products & services | F4: Delivery channels | G4: Transactions & volumes | H4: Total | I4: Check
A5: FC-01 | B5: Money laundering | C5: 0.3 | D5: 0.25 | E5: 0.2 | F5: 0.15 | G5: 0.1 | H5: =SUM(C5:G5) -> 1 | I5: =IF(ROUND(H5,4)=1,"OK","Must total 100%") -> OK
A6: FC-02 | B6: Terrorist financing | C6: 0.25 | D6: 0.3 | E6: 0.15 | F6: 0.1 | G6: 0.2 | H6: =SUM(C6:G6) -> 1 | I6: =IF(ROUND(H6,4)=1,"OK","Must total 100%") -> OK
A7: FC-03 | B7: Proliferation financing | C7: 0.15 | D7: 0.3 | E7: 0.3 | F7: 0.05 | G7: 0.2 | H7: =SUM(C7:G7) -> 1 | I7: =IF(ROUND(H7,4)=1,"OK","Must total 100%") -> OK
A8: FC-04 | B8: Sanctions | C8: 0.15 | D8: 0.4 | E8: 0.2 | F8: 0.05 | G8: 0.2 | H8: =SUM(C8:G8) -> 1 | I8: =IF(ROUND(H8,4)=1,"OK","Must total 100%") -> OK
A9: FC-05 | B9: Bribery and corruption | C9: 0.3 | D9: 0.25 | E9: 0.15 | F9: 0.2 | G9: 0.1 | H9: =SUM(C9:G9) -> 1 | I9: =IF(ROUND(H9,4)=1,"OK","Must total 100%") -> OK
A10: FC-06 | B10: Fraud | C10: 0.2 | D10: 0.1 | E10: 0.2 | F10: 0.3 | G10: 0.2 | H10: =SUM(C10:G10) -> 1 | I10: =IF(ROUND(H10,4)=1,"OK","Must total 100%") -> OK
A11: FC-07 | B11: Tax evasion and tax transparency | C11: 0.35 | D11: 0.25 | E11: 0.2 | F11: 0.1 | G11: 0.1 | H11: =SUM(C11:G11) -> 1 | I11: =IF(ROUND(H11,4)=1,"OK","Must total 100%") -> OK

Sheet Indicators
A1: Indicator library, scoring thresholds and per-risk weights
A2: Score = 1 below 'Score 2 from', +1 for each threshold met. For 'Lower = riskier' enter thresholds in descending order. Weights are relative within each factor (0 = not used for that risk).
A4: ID | B4: Risk factor | C4: Indicator | D4: Unit | E4: Data source | F4: Direction | G4: Score 2 from | H4: Score 3 from | I4: Score 4 from | J4: Score 5 from | K4: Weight FC-01 | L4: Weight FC-02 | M4: Weight FC-03 | N4: Weight FC-04 | O4: Weight FC-05 | P4: Weight FC-06 | Q4: Weight FC-07 | R4: Thresholds ordered?
A5: C01 | B5: Customer | C5: % of customers rated high risk (CRR) | D5: % | E5: KYC / CRR system | F5: Higher = riskier | G5: 2 | H5: 5 | I5: 10 | J5: 20 | K5: 3 | L5: 2 | M5: 1 | N5: 1 | O5: 1 | P5: 1 | Q5: 1 | R5: =IF(F5="Higher = riskier",IF(AND(G5<H5,H5<I5,I5<J5),"OK","Check order"),IF(AND(G5>H5,H5>I5,I5>J5),"OK","Check order")) -> OK
A6: C02 | B6: Customer | C6: PEP relationships per 10,000 customers | D6: count | E6: KYC / CRR system | F6: Higher = riskier | G6: 1 | H6: 3 | I6: 6 | J6: 10 | K6: 2 | L6: 1 | M6: 0 | N6: 1 | O6: 3 | P6: 0 | Q6: 1 | R6: =IF(F6="Higher = riskier",IF(AND(G6<H6,H6<I6,I6<J6),"OK","Check order"),IF(AND(G6>H6,H6>I6,I6>J6),"OK","Check order")) -> OK
A7: C03 | B7: Customer | C7: % of customers that are NPOs / charities | D7: % | E7: KYC / CRR system | F7: Higher = riskier | G7: 0.2 | H7: 0.5 | I7: 1 | J7: 2 | K7: 1 | L7: 3 | M7: 0 | N7: 0 | O7: 1 | P7: 0 | Q7: 0 | R7: =IF(F7="Higher = riskier",IF(AND(G7<H7,H7<I7,I7<J7),"OK","Check order"),IF(AND(G7>H7,H7>I7,I7>J7),"OK","Check order")) -> OK
A8: C04 | B8: Customer | C8: % non-resident customers | D8: % | E8: Core banking | F8: Higher = riskier | G8: 5 | H8: 10 | I8: 20 | J8: 35 | K8: 2 | L8: 2 | M8: 1 | N8: 2 | O8: 0 | P8: 1 | Q8: 3 | R8: =IF(F8="Higher = riskier",IF(AND(G8<H8,H8<I8,I8<J8),"OK","Check order"),IF(AND(G8>H8,H8>I8,I8>J8),"OK","Check order")) -> OK
A9: C05 | B9: Customer | C9: % corporate customers with complex or opaque ownership | D9: % | E9: KYC / CRR system | F9: Higher = riskier | G9: 2 | H9: 5 | I9: 10 | J9: 20 | K9: 2 | L9: 1 | M9: 2 | N9: 2 | O9: 1 | P9: 0 | Q9: 3 | R9: =IF(F9="Higher = riskier",IF(AND(G9<H9,H9<I9,I9<J9),"OK","Check order"),IF(AND(G9>H9,H9>I9,I9>J9),"OK","Check order")) -> OK
A10: C06 | B10: Customer | C10: % customers in cash-intensive businesses | D10: % | E10: KYC / CRR system | F10: Higher = riskier | G10: 3 | H10: 7 | I10: 12 | J10: 20 | K10: 2 | L10: 1 | M10: 0 | N10: 0 | O10: 0 | P10: 1 | Q10: 1 | R10: =IF(F10="Higher = riskier",IF(AND(G10<H10,H10<I10,I10<J10),"OK","Check order"),IF(AND(G10>H10,H10>I10,I10>J10),"OK","Check order")) -> OK
A11: C07 | B11: Customer | C11: % customers that are government bodies or SOEs | D11: % | E11: Core banking | F11: Higher = riskier | G11: 1 | H11: 3 | I11: 6 | J11: 10 | K11: 0 | L11: 0 | M11: 0 | N11: 1 | O11: 3 | P11: 0 | Q11: 0 | R11: =IF(F11="Higher = riskier",IF(AND(G11<H11,H11<I11,I11<J11),"OK","Check order"),IF(AND(G11>H11,H11>I11,I11>J11),"OK","Check order")) -> OK
A12: G01 | B12: Geography | C12: % cross-border value with FATF high-risk / increased-monitoring jurisdictions | D12: % | E12: Payments / TM system | F12: Higher = riskier | G12: 0.5 | H12: 2 | I12: 5 | J12: 10 | K12: 3 | L12: 3 | M12: 3 | N12: 2 | O12: 1 | P12: 1 | Q12: 1 | R12: =IF(F12="Higher = riskier",IF(AND(G12<H12,H12<I12,I12<J12),"OK","Check order"),IF(AND(G12>H12,H12>I12,I12>J12),"OK","Check order")) -> OK
A13: G02 | B13: Geography | C13: % payment value involving sanctioned or high sanctions-risk jurisdictions | D13: % | E13: Screening / payments | F13: Higher = riskier | G13: 0.01 | H13: 0.1 | I13: 0.5 | J13: 1 | K13: 1 | L13: 1 | M13: 3 | N13: 3 | O13: 0 | P13: 0 | Q13: 0 | R13: =IF(F13="Higher = riskier",IF(AND(G13<H13,H13<I13,I13<J13),"OK","Check order"),IF(AND(G13>H13,H13>I13,I13>J13),"OK","Check order")) -> OK
A14: G03 | B14: Geography | C14: Host-country national ML/TF risk (NRA-based, 1–5) | D14: score 1–5 | E14: Reference data (HO) | F14: Higher = riskier | G14: 2 | H14: 3 | I14: 4 | J14: 5 | K14: 2 | L14: 2 | M14: 1 | N14: 1 | O14: 1 | P14: 1 | Q14: 1 | R14: =IF(F14="Higher = riskier",IF(AND(G14<H14,H14<I14,I14<J14),"OK","Check order"),IF(AND(G14>H14,H14>I14,I14>J14),"OK","Check order")) -> OK
A15: G04 | B15: Geography | C15: Host-country corruption risk (CPI-based, 1–5) | D15: score 1–5 | E15: Reference data (HO) | F15: Higher = riskier | G15: 2 | H15: 3 | I15: 4 | J15: 5 | K15: 1 | L15: 0 | M15: 0 | N15: 0 | O15: 3 | P15: 1 | Q15: 1 | R15: =IF(F15="Higher = riskier",IF(AND(G15<H15,H15<I15,I15<J15),"OK","Check order"),IF(AND(G15>H15,H15>I15,I15>J15),"OK","Check order")) -> OK
A16: G05 | B16: Geography | C16: % branches in border, free-zone or conflict-affected areas | D16: % | E16: Branch register | F16: Higher = riskier | G16: 2 | H16: 5 | I16: 10 | J16: 20 | K16: 1 | L16: 3 | M16: 1 | N16: 1 | O16: 0 | P16: 1 | Q16: 0 | R16: =IF(F16="Higher = riskier",IF(AND(G16<H16,H16<I16,I16<J16),"OK","Check order"),IF(AND(G16>H16,H16>I16,I16>J16),"OK","Check order")) -> OK
... A35: T07 | B35: Transactions & volumes | C35: FATCA/CRS reportable accounts (% of accounts) | D35: % | E35: Tax reporting system | F35: Higher = riskier | G35: 1 | H35: 3 | I35: 6 | J35: 10 | K35: 0 | L35: 0 | M35: 0 | N35: 0 | O35: 0 | P35: 0 | Q35: 3 | R35: =IF(F35="Higher = riskier",IF(AND(G35<H35,H35<I35,I35<J35),"OK","Check order"),IF(AND(G35>H35,H35>I35,I35>J35),"OK","Check order")) -> OK

Sheet Indicator Data
A1: Raw indicator values by entity (ILLUSTRATIVE SAMPLE DATA)
A2: Replace with values from source systems or Country CO submissions for the assessment period. Leave a cell blank if data is unavailable; Config decides how blanks are treated.
A4: ID | B4: Indicator | C4: Unit | D4: =Entities!A5 -> JO-HO | E4: =Entities!A6 -> JO-IIAB | F4: =Entities!A7 -> JO-INV | G4: =Entities!A8 -> JO-INS | H4: =Entities!A9 -> JO-LSG | I4: =Entities!A10 -> PS | J4: =Entities!A11 -> PS-INV | K4: =Entities!A12 -> LB | L4: =Entities!A13 -> SY | M4: =Entities!A14 -> AE | N4: =Entities!A15 -> BH | O4: =Entities!A16 -> QA | P4: =Entities!A17 -> SA | Q4: =Entities!A18 -> OM | R4: =Entities!A19 -> IQ | S4: =Entities!A20 -> YE | T4: =Entities!A21 -> EG | U4: =Entities!A22 -> DZ | V4: =Entities!A23 -> MA | W4: =Entities!A24 -> TN | X4: =Entities!A25 -> SD | Y4: =Entities!A26 -> GB | Z4: =Entities!A27 -> FR | AA4: =Entities!A28 -> DE | AB4: =Entities!A29 -> IT | AC4: =Entities!A30 -> CH | AD4: =Entities!A31 -> SG | AE4: =Entities!A32 -> CN | AF4: =Entities!A33 -> AU | AG4: =Entities!A34 -> US
A5: =Indicators!A5 -> C01 | B5: =Indicators!C5 -> % of customers rated high risk (CRR) | C5: =Indicators!D5 -> % | D5: 14.91 | E5: 9.26 | F5: 0.16 | G5: 15.49 | H5: 12.22 | I5: 11.18 | J5: 5.71 | K5: 9.01 | L5: 19.46 | M5: 8.24 | N5: 3.76 | O5: 11.46 | P5: 4.75 | Q5: 5.64 | R5: 2.25 | S5: 18.28 | T5: 8.99 | U5: 6.87 | V5: 7.28 | W5: 6.81 | X5: 31.17 | Y5: 3.81 | Z5: 4.57 | AA5: 0.8 | AB5: 14.26 | AC5: 0.13 | AD5: 2.45 | AE5: 2.86 | AF5: 2.66 | AG5: 2.48
A6: =Indicators!A6 -> C02 | B6: =Indicators!C6 -> PEP relationships per 10,000 customers | C6: =Indicators!D6 -> count | D6: 9 | E6: 8 | F6: 2.54 | G6: 9 | H6: 0.93 | I6: 9 | J6: 13 | K6: 8 | L6: 8 | M6: 2.79 | N6: 3.74 | O6: 0.71 | P6: 2.18 | Q6: 4.54 | R6: 7 | S6: 13 | T6: 0.25 | U6: 4.24 | V6: 5 | W6: 5 | X6: 4.19 | Y6: 0.52 | Z6: 0.77 | AA6: 1.53 | AB6: 1.1 | AC6: 1.95 | AD6: 0.73 | AE6: 0.31 | AF6: 0.78 | AG6: 0.11
A7: =Indicators!A7 -> C03 | B7: =Indicators!C7 -> % of customers that are NPOs / charities | C7: =Indicators!D7 -> % | D7: 0.79 | E7: 1.46 | F7: 0 | G7: 0 | H7: 0 | I7: 0.3 | J7: 0 | K7: 0.54 | L7: 2.46 | M7: 1.87 | N7: 1.04 | O7: 0.24 | P7: 1.71 | Q7: 0.62 | R7: 3.01 | S7: 0.83 | T7: 0.64 | U7: 1.6 | V7: 1.41 | W7: 0.71 | X7: 3.18 | Y7: 1.95 | Z7: 0.01 | AA7: 0.19 | AB7: 0.34 | AC7: 0.16 | AD7: 0.26 | AE7: 0.22 | AF7: 0.03 | AG7: 0.12
A8: =Indicators!A8 -> C04 | B8: =Indicators!C8 -> % non-resident customers | C8: =Indicators!D8 -> % | D8: 15.34 | E8: 16.02 | F8: 17.22 | G8: 14.16 | H8: 25.83 | I8: 17.49 | J8: 23.77 | K8: 11.32 | L8: 15.92 | M8: 29.55 | N8: 7.35 | O8: 10.59 | P8: 21.66 | Q8: 21.02 | R8: 31.48 | S8: 27.08 | T8: 6.5 | U8: 31.44 | V8: 10.66 | W8: 7.73 | X8: 38.46 | Y8: 3.52 | Z8: 7.87 | AA8: 5.44 | AB8: 4.76 | AC8: 10.97 | AD8: 7.24 | AE8: 11.14 | AF8: 0.86 | AG8: 6.22
A9: =Indicators!A9 -> C05 | B9: =Indicators!C9 -> % corporate customers with complex or opaque ownership | C9: =Indicators!D9 -> % | D9: 8.51 | E9: 25.48 | F9: 19.18 | G9: 13.23 | H9: 4.27 | I9: 7.95 | J9: 7.85 | K9: 28.87 | L9: 18.73 | M9: 1.07 | N9: 12.44 | O9: 3.93 | P9: 15.97 | Q9: 7.89 | R9: 3.59 | S9: 5.55 | T9: 5.15 | U9: 3.62 | V9: 7.04 | W9: 3.04 | X9: 14.35 | Y9: 7.27 | Z9: 0.93 | AA9: 0.09 | AB9: 5.96 | AC9: 3.22 | AD9: 8.28 | AE9: 1.43 | AF9: 3.51 | AG9: 0.78
A10: =Indicators!A10 -> C06 | B10: =Indicators!C10 -> % customers in cash-intensive businesses | C10: =Indicators!D10 -> % | D10: 5.96 | E10: 2.9 | F10: 3.6 | G10: 3.27 | H10: 19.31 | I10: 11.4 | J10: 30.07 | K10: 13.65 | L10: 12.92 | M10: 8.57 | N10: 10.59 | O10: 19.15 | P10: 7.75 | Q10: 18.88 | R10: 7.17 | S10: 31.59 | T10: 13.62 | U10: 6.34 | V10: 4.35 | W10: 8.67 | X10: 16.36 | Y10: 7.72 | Z10: 3.46 | AA10: 4.3 | AB10: 4.2 | AC10: 0.4 | AD10: 1.75 | AE10: 3.75 | AF10: 10.16 | AG10: 0.13
A11: =Indicators!A11 -> C07 | B11: =Indicators!C11 -> % customers that are government bodies or SOEs | C11: =Indicators!D11 -> % | D11: 3.69 | E11: 4.57 | F11: 1.61 | G11: 1.77 | H11: 1.68 | I11: 7.76 | J11: 5.77 | K11: 9.23 | L11: 4.97 | M11: 9.51 | N11: 5.43 | O11: 3.52 | P11: 3.55 | Q11: 8.73 | R11: 14.16 | S11: 7.89 | T11: 2.47 | U11: 6.11 | V11: 8.29 | W11: 1.49 | X11: 13.82 | Y11: 0.45 | Z11: 5.76 | AA11: 0.79 | AB11: 5 | AC11: 4.68 | AD11: 1.12 | AE11: 2.71 | AF11: 0.88 | AG11: 0.24
A12: =Indicators!A12 -> G01 | B12: =Indicators!C12 -> % cross-border value with FATF high-risk / increased-monitoring jurisdictions | C12: =Indicators!D12 -> % | D12: 1.4 | E12: 0.95 | F12: 0.47 | G12: 2.13 | H12: 3.66 | I12: 15.87 | J12: 7.47 | K12: 4.77 | L12: 7.19 | M12: 3.62 | N12: 3.16 | O12: 3.03 | P12: 9.55 | Q12: 0.97 | R12: 9.04 | S12: 3.49 | T12: 0.2 | U12: 3.79 | V12: 8.8 | W12: 1.18 | X12: 4.27 | Y12: 4.07 | Z12: 0.13 | AA12: 1.25 | AB12: 1.51 | AC12: 1.84 | AD12: 0.49 | AE12: 0.35 | AF12: 1.65 | AG12: 1.29
A13: =Indicators!A13 -> G02 | B13: =Indicators!C13 -> % payment value involving sanctioned or high sanctions-risk jurisdictions | C13: =Indicators!D13 -> % | D13: 0.72 | E13: 0.08 | F13: 0.05 | G13: 1.33 | H13: 0.76 | I13: 1.52 | J13: 0.86 | K13: 0.68 | L13: 0.87 | M13: 0.2 | N13: 0.26 | O13: 0.72 | P13: 0.48 | Q13: 0.93 | R13: 0.09 | S13: 1.21 | T13: 0.58 | U13: 0.28 | V13: 0.41 | W13: 0.34 | X13: 0.88 | Y13: 0 | Z13: 0.03 | AA13: 0.01 | AB13: 0.07 | AC13: 0.01 | AD13: 0.78 | AE13: 0.09 | AF13: 0 | AG13: 0.08
A14: =Indicators!A14 -> G03 | B14: =Indicators!C14 -> Host-country national ML/TF risk (NRA-based, 1–5) | C14: =Indicators!D14 -> score 1–5 | D14: 4 | E14: 2 | F14: 3 | G14: 3 | H14: 4 | I14: 4 | J14: 5 | K14: 5 | L14: 4 | M14: 3 | N14: 3 | O14: 3 | P14: 3 | Q14: 3 | R14: 4 | S14: 5 | T14: 2 | U14: 3 | V14: 4 | W14: 3 | X14: 5 | Y14: 3 | Z14: 2 | AA14: 2 | AB14: 2 | AC14: 3 | AD14: 3 | AE14: 1 | AF14: 2 | AG14: 3
A15: =Indicators!A15 -> G04 | B15: =Indicators!C15 -> Host-country corruption risk (CPI-based, 1–5) | C15: =Indicators!D15 -> score 1–5 | D15: 3 | E15: 3 | F15: 3 | G15: 3 | H15: 4 | I15: 4 | J15: 4 | K15: 4 | L15: 5 | M15: 4 | N15: 4 | O15: 3 | P15: 2 | Q15: 3 | R15: 5 | S15: 4 | T15: 3 | U15: 3 | V15: 3 | W15: 3 | X15: 4 | Y15: 3 | Z15: 3 | AA15: 2 | AB15: 3 | AC15: 2 | AD15: 2 | AE15: 2 | AF15: 2 | AG15: 2
A16: =Indicators!A16 -> G05 | B16: =Indicators!C16 -> % branches in border, free-zone or conflict-affected areas | C16: =Indicators!D16 -> % | D16: 3.97 | E16: 12.83 | F16: 9.6 | G16: 8.41 | H16: 2.62 | I16: 3.13 | J16: 20.14 | K16: 14.88 | L16: 23.74 | M16: 0.93 | N16: 8.17 | O16: 8.08 | P16: 1.55 | Q16: 0.82 | R16: 8.12 | S16: 13.62 | T16: 7.89 | U16: 5.41 | V16: 4.18 | W16: 11.12 | X16: 28.88 | Y16: 2.92 | Z16: 3.99 | AA16: 0.11 | AB16: 0.6 | AC16: 0.51 | AD16: 2.35 | AE16: 9.13 | AF16: 2.5 | AG16: 0.01
... A25: =Indicators!A25 -> D02 | B25: =Indicators!C25 -> % customers introduced via agents or intermediaries | C25: =Indicators!D25 -> % | D25: 13.49 | E25: 4.41 | F25: 2.89 | G25: 9.05 | H25: 28.21 | I25: 5.54 | J25: 4.76 | K25: 27.27 | L25: 6.83 | M25: 5.05 | N25: 26.25 | O25: 8.38 | P25: 2.74 | Q25: 6.28 | R25: 13.38 | S25: 27.29 | T25: 3.29 | U25: 5.48 | V25: 4.52 | W25: 7.48 | X25: 10.89 | Y25: 6.21 | Z25: 3.07 | AA25: 4.08 | AB25: 1.78 | AC25: 6.28 | AD25: 3.15 | AE25: 4.71 | AF25: 0.08 | AG25: 3.54
A26: =Indicators!A26 -> D03 | B26: =Indicators!C26 -> Real-time / digital payments (% of payment value) | C26: =Indicators!D26 -> % | D26: 31 | E26: 11.43 | F26: 5.1 | G26: 16 | H26: 27.63 | I26: 51.64 | J26: 68.37 | K26: 36.53 | L26: 65.56 | M26: 28.12 | N26: 15.55 | O26: 35.75 | P26: 19.89 | Q26: 0.26 | R26: 50.09 | S26: 26.61 | T26: 30.33 | U26: 56.43 | V26: 43.91 | W26: 11.57 | X26: 79.41 | Y26: 34.7 | Z26: 13.12 | AA26: 11.87 | AB26: 12.59 | AC26: 6.7 | AD26: 0.32 | AE26: 12.27 | AF26: 8.13
A27: =Indicators!A27 -> D04 | B27: =Indicators!C27 -> Cash deposit machines and ATMs per branch | C27: =Indicators!D27 -> count | D27: 1.48 | E27: 7 | F27: 0 | G27: 0 | H27: 0 | I27: 6 | J27: 0 | K27: 4.71 | L27: 3.24 | M27: 2.44 | N27: 3.41 | O27: 1.16 | P27: 1.79 | Q27: 2.57 | R27: 3.03 | S27: 3.24 | T27: 1.29 | U27: 4.05 | V27: 3.84 | W27: 1.4 | X27: 7 | Y27: 0.53 | Z27: 0.75 | AA27: 0.79 | AB27: 0.08 | AC27: 1.65 | AD27: 0.84 | AE27: 1.34 | AF27: 1.21 | AG27: 1.88
A28: =Indicators!A28 -> D05 | B28: =Indicators!C28 -> Third parties with public-official contact acting for the bank | C28: =Indicators!D28 -> count | D28: 11 | E28: 7 | F28: 12 | G28: 5 | H28: 0.62 | I28: 28 | J28: 22 | K28: 22 | L28: 6 | M28: 2.21 | N28: 14 | O28: 7 | P28: 8 | Q28: 0.12 | R28: 14 | S28: 14 | T28: 5 | U28: 1.49 | V28: 2.4 | W28: 31 | X28: 26 | Y28: 0.83 | Z28: 0.94 | AA28: 0.94 | AB28: 0.98 | AC28: 4.18 | AD28: 2.57 | AE28: 3.8 | AF28: 0.22 | AG28: 0.11
A29: =Indicators!A29 -> T01 | B29: =Indicators!C29 -> Cash deposits (% of total deposit inflows) | C29: =Indicators!D29 -> % | D29: 2.94 | E29: 9.63 | F29: 18.52 | G29: 12.53 | H29: 9.02 | I29: 28.27 | J29: 13.45 | K29: 27.38 | L29: 52.66 | M29: 7.72 | N29: 15.06 | O29: 26.19 | P29: 6.33 | Q29: 13.54 | R29: 38.75 | S29: 23.6 | T29: 6.43 | U29: 13.33 | V29: 1.53 | W29: 51.68 | X29: 11.32 | Y29: 2.82 | Z29: 8.43 | AA29: 7.97 | AB29: 3.45 | AC29: 8.6 | AD29: 7.54 | AE29: 5.4 | AF29: 1.67 | AG29: 0.13
A30: =Indicators!A30 -> T02 | B30: =Indicators!C30 -> Cross-border wires per month ('000) | C30: =Indicators!D30 -> count ('000) | D30: 34 | E30: 73 | F30: 0 | G30: 0 | H30: 0 | I30: 67 | J30: 0 | K30: 110 | L30: 71 | M30: 13 | N30: 75 | O30: 27 | P30: 21 | Q30: 25 | R30: 114 | S30: 24 | T30: 11 | U30: 45 | V30: 45 | W30: 85 | X30: 109 | Y30: 3.38 | Z30: 16 | AA30: 0.04 | AB30: 16 | AC30: 2.53 | AD30: 10 | AE30: 3.19 | AF30: 1.39 | AG30: 2.45
A31: =Indicators!A31 -> T03 | B31: =Indicators!C31 -> Transactions above USD 1m per month | C31: =Indicators!D31 -> count | D31: 181 | E31: 25 | F31: 110 | G31: 443 | H31: 156 | I31: 421 | J31: 192 | K31: 919 | L31: 684 | M31: 2.12 | N31: 270 | O31: 95 | P31: 279 | Q31: 179 | R31: 165 | S31: 482 | T31: 454 | U31: 329 | V31: 217 | W31: 175 | X31: 176 | Y31: 25 | Z31: 46 | AA31: 64 | AB31: 55 | AC31: 133 | AD31: 33 | AE31: 84 | AF31: 0.21
A32: =Indicators!A32 -> T04 | B32: =Indicators!C32 -> TM alerts per 1,000 customers per month | C32: =Indicators!D32 -> count | D32: 4.69 | E32: 5 | F32: 4.23 | G32: 7 | H32: 5 | I32: 23 | J32: 9 | K32: 3.87 | L32: 32 | M32: 6 | N32: 3.42 | O32: 10 | P32: 8 | Q32: 10 | R32: 13 | S32: 21 | T32: 9 | U32: 14 | V32: 24 | W32: 15 | X32: 16 | Y32: 0.4 | Z32: 0.17 | AA32: 10 | AB32: 0.04 | AC32: 8 | AD32: 2.62 | AE32: 6 | AF32: 7 | AG32: 9
A33: =Indicators!A33 -> T05 | B33: =Indicators!C33 -> STRs filed per 10,000 customers per year | C33: =Indicators!D33 -> count | D33: 1.05 | E33: 9 | F33: 3.07 | G33: 1.63 | H33: 4.19 | I33: 14 | J33: 8 | K33: 6 | L33: 7 | M33: 9 | N33: 0.32 | O33: 4.22 | P33: 2.12 | Q33: 4.15 | R33: 6 | S33: 9 | T33: 4.91 | U33: 6 | V33: 2.24 | W33: 10 | X33: 9 | Y33: 0.92 | Z33: 1.15 | AA33: 1.08 | AB33: 0.71 | AC33: 2.9 | AD33: 0.57 | AE33: 0.56 | AF33: 0.22 | AG33: 1.32
A34: =Indicators!A34 -> T06 | B34: =Indicators!C34 -> Fraud cases per 10,000 customers per year | C34: =Indicators!D34 -> count | D34: 3.65 | E34: 1.03 | F34: 1.59 | G34: 2.55 | H34: 8 | I34: 16 | J34: 7 | K34: 7 | L34: 8 | M34: 15 | N34: 2.93 | O34: 0.69 | P34: 8 | Q34: 3.76 | R34: 7 | S34: 7 | T34: 6 | U34: 8 | V34: 14 | W34: 6 | X34: 10 | Y34: 0.78 | Z34: 1.34 | AA34: 0.02 | AB34: 2.13 | AC34: 5 | AD34: 2.17 | AE34: 1.42 | AF34: 1.39 | AG34: 6
A35: =Indicators!A35 -> T07 | B35: =Indicators!C35 -> FATCA/CRS reportable accounts (% of accounts) | C35: =Indicators!D35 -> % | D35: 5.03 | E35: 3 | F35: 3.94 | G35: 5.29 | H35: 1.03 | I35: 6.97 | J35: 14.88 | K35: 10.93 | L35: 8.72 | M35: 4.89 | N35: 2.05 | O35: 9.68 | P35: 5.59 | Q35: 5.31 | R35: 9.57 | S35: 7.04 | T35: 0.34 | U35: 9.77 | V35: 1.9 | W35: 2.08 | X35: 2.15 | Y35: 0.53 | Z35: 0.3 | AA35: 1.1 | AB35: 0.83 | AC35: 1.26 | AD35: 0.12 | AE35: 0.5 | AF35: 0.66 | AG35: 2.22

Sheet Indicator Scores
A1: Indicator scores (1–5) by entity
A2: Formula sheet – do not edit. A '-' means no data and the indicator is excluded (when Config = Exclude and reweight).
A4: ID | B4: Indicator | C4: Unit | D4: =Entities!A5 -> JO-HO | E4: =Entities!A6 -> JO-IIAB | F4: =Entities!A7 -> JO-INV | G4: =Entities!A8 -> JO-INS | H4: =Entities!A9 -> JO-LSG | I4: =Entities!A10 -> PS | J4: =Entities!A11 -> PS-INV | K4: =Entities!A12 -> LB | L4: =Entities!A13 -> SY | M4: =Entities!A14 -> AE | N4: =Entities!A15 -> BH | O4: =Entities!A16 -> QA | P4: =Entities!A17 -> SA | Q4: =Entities!A18 -> OM | R4: =Entities!A19 -> IQ | S4: =Entities!A20 -> YE | T4: =Entities!A21 -> EG | U4: =Entities!A22 -> DZ | V4: =Entities!A23 -> MA | W4: =Entities!A24 -> TN | X4: =Entities!A25 -> SD | Y4: =Entities!A26 -> GB | Z4: =Entities!A27 -> FR | AA4: =Entities!A28 -> DE | AB4: =Entities!A29 -> IT | AC4: =Entities!A30 -> CH | AD4: =Entities!A31 -> SG | AE4: =Entities!A32 -> CN | AF4: =Entities!A33 -> AU | AG4: =Entities!A34 -> US
A5: =Indicators!A5 -> C01 | B5: =Indicators!C5 -> % of customers rated high risk (CRR) | C5: =Indicators!D5 -> % | D5: =IF('Indicator Data'!D5="",IF(Config!$C$15="Score as High (5)",5,0),IF(Indicators!$F5="Higher = riskier",1+('Indicator Data'!D5>=Indicators!$G5)+('Indicator Data'!D5>=Indicators!$H5)+('Indicator Data'!D5>=Indicators!$I5)+('Indicator Data'!D5>=Indicators!$J5),1+('Indicator Data'!D5<=Indicators!$G5)+('Indicator Data'!D5<=Indicators!$H5)+('Indicator Data'!D5<=Indicators!$I5)+('Indicator Data'!D5<=Indicators!$J5))) -> 4 | E5: =IF('Indicator Data'!E5="",IF(Config!$C$15="Score as High (5)",5,0),IF(Indicators!$F5="Higher = riskier",1+('Indicator Data'!E5>=Indicators!$G5)+('Indicator Data'!E5>=Indicators!$H5)+('Indicator Data'!E5>=Indicators!$I5)+('Indicator Data'!E5>=Indicators!$J5),1+('Indicator Data'!E5<=Indicators!$G5)+('Indicator Data'!E5<=Indicators!$H5)+('Indicator Data'!E5<=Indicators!$I5)+('Indicator Data'!E5<=Indicators!$J5))) -> 3 | F5: =IF('Indicator Data'!F5="",IF(Config!$C$15="Score as High (5)",5,0),IF(Indicators!$F5="Higher = riskier",1+('Indicator Data'!F5>=Indicators!$G5)+('Indicator Data'!F5>=Indicators!$H5)+('Indicator Data'!F5>=Indicators!$I5)+('Indicator Data'!F5>=Indicators!$J5),1+('Indicator Data'!F5<=Indicators!$G5)+('Indicator Data'!F5<=Indicators!$H5)+('Indicator Data'!F5<=Indicators!$I5)+('Indicator Data'!F5<=Indicators!$J5))) -> 1 | G5: =IF('Indicator Data'!G5="",IF(Config!$C$15="Score as High (5)",5,0),IF(Indicators!$F5="Higher = riskier",1+('Indicator Data'!G5>=Indicators!$G5)+('Indicator Data'!G5>=Indicators!$H5)+('Indicator Data'!G5>=Indicators!$I5)+('Indicator Data'!G5>=Indicators!$J5),1+('Indicator Data'!G5<=Indicators!$G5)+('Indicator Data'!G5<=Indicators!$H5)+('Indicator Data'!G5<=Indicators!$I5)+('Indicator Data'!G5<=Indicators!$J5))) -> 4 | H5: =IF('Indicator Data'!H5="",IF(Config!$C$15="Score as High (5)",5,0),IF(Indicators!$F5="Higher = riskier",1+('Indicator Data'!H5>=Indicators!$G5)+('Indicator Data'!H5>=Indicators!$H5)+('Indicator Data'!H5>=Indicators!$I5)+('Indicator Data'!H5>=Indicators!$J5),1+('Indicator Data'!H5<=Indicators!$G5)+('Indicator Data'!H5<=Indicators!$H5)+('Indicator Data'!H5<=Indicators!$I5)+('Indicator Data'!H5<=Indicators!$J5))) -> 4 | I5: =IF('Indicator Data'!I5="",IF(Config!$C$15="Score as High (5)",5,0),IF(Indicators!$F5="Higher = riskier",1+('Indicator Data'!I5>=Indicators!$G5)+('Indicator Data'!I5>=Indicators!$H5)+('Indicator Data'!I5>=Indicators!$I5)+('Indicator Data'!I5>=Indicators!$J5),1+('Indicator Data'!I5<=Indicators!$G5)+('Indicator Data'!I5<=Indicators!$H5)+('Indicator Data'!I5<=Indicators!$I5)+('Indicator Data'!I5<=Indicators!$J5))) -> 4 | J5: =IF('Indicator Data'!J5="",IF(Config!$C$15="Score as High (5)",5,0),IF(Indicators!$F5="Higher = riskier",1+('Indicator Data'!J5>=Indicators!$G5)+('Indicator Data'!J5>=Indicators!$H5)+('Indicator Data'!J5>=Indicators!$I5)+('Indicator Data'!J5>=Indicators!$J5),1+('Indicator Data'!J5<=Indicators!$G5)+('Indicator Data'!J5<=Indicators!$H5)+('Indicator Data'!J5<=Indicators!$I5)+('Indicator Data'!J5<=Indicators!$J5))) -> 3 | K5: =IF('Indicator Data'!K5="",IF(Config!$C$15="Score as High (5)",5,0),IF(Indicators!$F5="Higher = riskier",1+('Indicator Data'!K5>=Indicators!$G5)+('Indicator Data'!K5>=Indicators!$H5)+('Indicator Data'!K5>=Indicators!$I5)+('Indicator Data'!K5>=Indicators!$J5),1+('Indicator Data'!K5<=Indicators!$G5)+('Indicator Data'!K5<=Indicators!$H5)+('Indicator Data'!K5<=Indicators!$I5)+('Indicator Data'!K5<=Indicators!$J5))) -> 3 | ... AG5: =IF('Indicator Data'!AG5="",IF(Config!$C$15="Score as High (5)",5,0),IF(Indicators!$F5="Higher = riskier",1+('Indicator Data'!AG5>=Indicators!$G5)+('Indicator Data'!AG5>=Indicators!$H5)+('Indicator Data'!AG5>=Indicators!$I5)+('Indicator Data'!AG5>=Indicators!$J5),1+('Indicator Data'!AG5<=Indicators!$G5)+('Indicator Data'!AG5<=Indicators!$H5)+('Indicator Data'!AG5<=Indicators!$I5)+('Indicator Data'!AG5<=Indicators!$J5))) -> 2
A6: =Indicators!A6 -> C02 | B6: =Indicators!C6 -> PEP relationships per 10,000 customers | C6: =Indicators!D6 -> count | D6: =IF('Indicator Data'!D6="",IF(Config!$C$15="Score as High (5)",5,0),IF(Indicators!$F6="Higher = riskier",1+('Indicator Data'!D6>=Indicators!$G6)+('Indicator Data'!D6>=Indicators!$H6)+('Indicator Data'!D6>=Indicators!$I6)+('Indicator Data'!D6>=Indicators!$J6),1+('Indicator Data'!D6<=Indicators!$G6)+('Indicator Data'!D6<=Indicators!$H6)+('Indicator Data'!D6<=Indicators!$I6)+('Indicator Data'!D6<=Indicators!$J6))) -> 4 | E6: =IF('Indicator Data'!E6="",IF(Config!$C$15="Score as High (5)",5,0),IF(Indicators!$F6="Higher = riskier",1+('Indicator Data'!E6>=Indicators!$G6)+('Indicator Data'!E6>=Indicators!$H6)+('Indicator Data'!E6>=Indicators!$I6)+('Indicator Data'!E6>=Indicators!$J6),1+('Indicator Data'!E6<=Indicators!$G6)+('Indicator Data'!E6<=Indicators!$H6)+('Indicator Data'!E6<=Indicators!$I6)+('Indicator Data'!E6<=Indicators!$J6))) -> 4 | F6: =IF('Indicator Data'!F6="",IF(Config!$C$15="Score as High (5)",5,0),IF(Indicators!$F6="Higher = riskier",1+('Indicator Data'!F6>=Indicators!$G6)+('Indicator Data'!F6>=Indicators!$H6)+('Indicator Data'!F6>=Indicators!$I6)+('Indicator Data'!F6>=Indicators!$J6),1+('Indicator Data'!F6<=Indicators!$G6)+('Indicator Data'!F6<=Indicators!$H6)+('Indicator Data'!F6<=Indicators!$I6)+('Indicator Data'!F6<=Indicators!$J6))) -> 2 | G6: =IF('Indicator Data'!G6="",IF(Config!$C$15="Score as High (5)",5,0),IF(Indicators!$F6="Higher = riskier",1+('Indicator Data'!G6>=Indicators!$G6)+('Indicator Data'!G6>=Indicators!$H6)+('Indicator Data'!G6>=Indicators!$I6)+('Indicator Data'!G6>=Indicators!$J6),1+('Indicator Data'!G6<=Indicators!$G6)+('Indicator Data'!G6<=Indicators!$H6)+('Indicator Data'!G6<=Indicators!$I6)+('Indicator Data'!G6<=Indicators!$J6))) -> 4 | H6: =IF('Indicator Data'!H6="",IF(Config!$C$15="Score as High (5)",5,0),IF(Indicators!$F6="Higher = riskier",1+('Indicator Data'!H6>=Indicators!$G6)+('Indicator Data'!H6>=Indicators!$H6)+('Indicator Data'!H6>=Indicators!$I6)+('Indicator Data'!H6>=Indicators!$J6),1+('Indicator Data'!H6<=Indicators!$G6)+('Indicator Data'!H6<=Indicators!$H6)+('Indicator Data'!H6<=Indicators!$I6)+('Indicator Data'!H6<=Indicators!$J6))) -> 1 | I6: =IF('Indicator Data'!I6="",IF(Config!$C$15="Score as High (5)",5,0),IF(Indicators!$F6="Higher = riskier",1+('Indicator Data'!I6>=Indicators!$G6)+('Indicator Data'!I6>=Indicators!$H6)+('Indicator Data'!I6>=Indicators!$I6)+('Indicator Data'!I6>=Indicators!$J6),1+('Indicator Data'!I6<=Indicators!$G6)+('Indicator Data'!I6<=Indicators!$H6)+('Indicator Data'!I6<=Indicators!$I6)+('Indicator Data'!I6<=Indicators!$J6))) -> 4 | J6: =IF('Indicator Data'!J6="",IF(Config!$C$15="Score as High (5)",5,0),IF(Indicators!$F6="Higher = riskier",1+('Indicator Data'!J6>=Indicators!$G6)+('Indicator Data'!J6>=Indicators!$H6)+('Indicator Data'!J6>=Indicators!$I6)+('Indicator Data'!J6>=Indicators!$J6),1+('Indicator Data'!J6<=Indicators!$G6)+('Indicator Data'!J6<=Indicators!$H6)+('Indicator Data'!J6<=Indicators!$I6)+('Indicator Data'!J6<=Indicators!$J6))) -> 5 | K6: =IF('Indicator Data'!K6="",IF(Config!$C$15="Score as High (5)",5,0),IF(Indicators!$F6="Higher = riskier",1+('Indicator Data'!K6>=Indicators!$G6)+('Indicator Data'!K6>=Indicators!$H6)+('Indicator Data'!K6>=Indicators!$I6)+('Indicator Data'!K6>=Indicators!$J6),1+('Indicator Data'!K6<=Indicators!$G6)+('Indicator Data'!K6<=Indicators!$H6)+('Indicator Data'!K6<=Indicators!$I6)+('Indicator Data'!K6<=Indicators!$J6))) -> 4 | ... AG6: =IF('Indicator Data'!AG6="",IF(Config!$C$15="Score as High (5)",5,0),IF(Indicators!$F6="Higher = riskier",1+('Indicator Data'!AG6>=Indicators!$G6)+('Indicator Data'!AG6>=Indicators!$H6)+('Indicator Data'!AG6>=Indicators!$I6)+('Indicator Data'!AG6>=Indicators!$J6),1+('Indicator Data'!AG6<=Indicators!$G6)+('Indicator Data'!AG6<=Indicators!$H6)+('Indicator Data'!AG6<=Indicators!$I6)+('Indicator Data'!AG6<=Indicators!$J6))) -> 1
A7: =Indicators!A7 -> C03 | B7: =Indicators!C7 -> % of customers that are NPOs / charities | C7: =Indicators!D7 -> % | D7: =IF('Indicator Data'!D7="",IF(Config!$C$15="Score as High (5)",5,0),IF(Indicators!$F7="Higher = riskier",1+('Indicator Data'!D7>=Indicators!$G7)+('Indicator Data'!D7>=Indicators!$H7)+('Indicator Data'!D7>=Indicators!$I7)+('Indicator Data'!D7>=Indicators!$J7),1+('Indicator Data'!D7<=Indicators!$G7)+('Indicator Data'!D7<=Indicators!$H7)+('Indicator Data'!D7<=Indicators!$I7)+('Indicator Data'!D7<=Indicators!$J7))) -> 3 | E7: =IF('Indicator Data'!E7="",IF(Config!$C$15="Score as High (5)",5,0),IF(Indicators!$F7="Higher = riskier",1+('Indicator Data'!E7>=Indicators!$G7)+('Indicator Data'!E7>=Indicators!$H7)+('Indicator Data'!E7>=Indicators!$I7)+('Indicator Data'!E7>=Indicators!$J7),1+('Indicator Data'!E7<=Indicators!$G7)+('Indicator Data'!E7<=Indicators!$H7)+('Indicator Data'!E7<=Indicators!$I7)+('Indicator Data'!E7<=Indicators!$J7))) -> 4 | F7: =IF('Indicator Data'!F7="",IF(Config!$C$15="Score as High (5)",5,0),IF(Indicators!$F7="Higher = riskier",1+('Indicator Data'!F7>=Indicators!$G7)+('Indicator Data'!F7>=Indicators!$H7)+('Indicator Data'!F7>=Indicators!$I7)+('Indicator Data'!F7>=Indicators!$J7),1+('Indicator Data'!F7<=Indicators!$G7)+('Indicator Data'!F7<=Indicators!$H7)+('Indicator Data'!F7<=Indicators!$I7)+('Indicator Data'!F7<=Indicators!$J7))) -> 1 | G7: =IF('Indicator Data'!G7="",IF(Config!$C$15="Score as High (5)",5,0),IF(Indicators!$F7="Higher = riskier",1+('Indicator Data'!G7>=Indicators!$G7)+('Indicator Data'!G7>=Indicators!$H7)+('Indicator Data'!G7>=Indicators!$I7)+('Indicator Data'!G7>=Indicators!$J7),1+('Indicator Data'!G7<=Indicators!$G7)+('Indicator Data'!G7<=Indicators!$H7)+('Indicator Data'!G7<=Indicators!$I7)+('Indicator Data'!G7<=Indicators!$J7))) -> 1 | H7: =IF('Indicator Data'!H7="",IF(Config!$C$15="Score as High (5)",5,0),IF(Indicators!$F7="Higher = riskier",1+('Indicator Data'!H7>=Indicators!$G7)+('Indicator Data'!H7>=Indicators!$H7)+('Indicator Data'!H7>=Indicators!$I7)+('Indicator Data'!H7>=Indicators!$J7),1+('Indicator Data'!H7<=Indicators!$G7)+('Indicator Data'!H7<=Indicators!$H7)+('Indicator Data'!H7<=Indicators!$I7)+('Indicator Data'!H7<=Indicators!$J7))) -> 1 | I7: =IF('Indicator Data'!I7="",IF(Config!$C$15="Score as High (5)",5,0),IF(Indicators!$F7="Higher = riskier",1+('Indicator Data'!I7>=Indicators!$G7)+('Indicator Data'!I7>=Indicators!$H7)+('Indicator Data'!I7>=Indicators!$I7)+('Indicator Data'!I7>=Indicators!$J7),1+('Indicator Data'!I7<=Indicators!$G7)+('Indicator Data'!I7<=Indicators!$H7)+('Indicator Data'!I7<=Indicators!$I7)+('Indicator Data'!I7<=Indicators!$J7))) -> 2 | J7: =IF('Indicator Data'!J7="",IF(Config!$C$15="Score as High (5)",5,0),IF(Indicators!$F7="Higher = riskier",1+('Indicator Data'!J7>=Indicators!$G7)+('Indicator Data'!J7>=Indicators!$H7)+('Indicator Data'!J7>=Indicators!$I7)+('Indicator Data'!J7>=Indicators!$J7),1+('Indicator Data'!J7<=Indicators!$G7)+('Indicator Data'!J7<=Indicators!$H7)+('Indicator Data'!J7<=Indicators!$I7)+('Indicator Data'!J7<=Indicators!$J7))) -> 1 | K7: =IF('Indicator Data'!K7="",IF(Config!$C$15="Score as High (5)",5,0),IF(Indicators!$F7="Higher = riskier",1+('Indicator Data'!K7>=Indicators!$G7)+('Indicator Data'!K7>=Indicators!$H7)+('Indicator Data'!K7>=Indicators!$I7)+('Indicator Data'!K7>=Indicators!$J7),1+('Indicator Data'!K7<=Indicators!$G7)+('Indicator Data'!K7<=Indicators!$H7)+('Indicator Data'!K7<=Indicators!$I7)+('Indicator Data'!K7<=Indicators!$J7))) -> 3 | ... AG7: =IF('Indicator Data'!AG7="",IF(Config!$C$15="Score as High (5)",5,0),IF(Indicators!$F7="Higher = riskier",1+('Indicator Data'!AG7>=Indicators!$G7)+('Indicator Data'!AG7>=Indicators!$H7)+('Indicator Data'!AG7>=Indicators!$I7)+('Indicator Data'!AG7>=Indicators!$J7),1+('Indicator Data'!AG7<=Indicators!$G7)+('Indicator Data'!AG7<=Indicators!$H7)+('Indicator Data'!AG7<=Indicators!$I7)+('Indicator Data'!AG7<=Indicators!$J7))) -> 1
A8: =Indicators!A8 -> C04 | B8: =Indicators!C8 -> % non-resident customers | C8: =Indicators!D8 -> % | D8: =IF('Indicator Data'!D8="",IF(Config!$C$15="Score as High (5)",5,0),IF(Indicators!$F8="Higher = riskier",1+('Indicator Data'!D8>=Indicators!$G8)+('Indicator Data'!D8>=Indicators!$H8)+('Indicator Data'!D8>=Indicators!$I8)+('Indicator Data'!D8>=Indicators!$J8),1+('Indicator Data'!D8<=Indicators!$G8)+('Indicator Data'!D8<=Indicators!$H8)+('Indicator Data'!D8<=Indicators!$I8)+('Indicator Data'!D8<=Indicators!$J8))) -> 3 | E8: =IF('Indicator Data'!E8="",IF(Config!$C$15="Score as High (5)",5,0),IF(Indicators!$F8="Higher = riskier",1+('Indicator Data'!E8>=Indicators!$G8)+('Indicator Data'!E8>=Indicators!$H8)+('Indicator Data'!E8>=Indicators!$I8)+('Indicator Data'!E8>=Indicators!$J8),1+('Indicator Data'!E8<=Indicators!$G8)+('Indicator Data'!E8<=Indicators!$H8)+('Indicator Data'!E8<=Indicators!$I8)+('Indicator Data'!E8<=Indicators!$J8))) -> 3 | F8: =IF('Indicator Data'!F8="",IF(Config!$C$15="Score as High (5)",5,0),IF(Indicators!$F8="Higher = riskier",1+('Indicator Data'!F8>=Indicators!$G8)+('Indicator Data'!F8>=Indicators!$H8)+('Indicator Data'!F8>=Indicators!$I8)+('Indicator Data'!F8>=Indicators!$J8),1+('Indicator Data'!F8<=Indicators!$G8)+('Indicator Data'!F8<=Indicators!$H8)+('Indicator Data'!F8<=Indicators!$I8)+('Indicator Data'!F8<=Indicators!$J8))) -> 3 | G8: =IF('Indicator Data'!G8="",IF(Config!$C$15="Score as High (5)",5,0),IF(Indicators!$F8="Higher = riskier",1+('Indicator Data'!G8>=Indicators!$G8)+('Indicator Data'!G8>=Indicators!$H8)+('Indicator Data'!G8>=Indicators!$I8)+('Indicator Data'!G8>=Indicators!$J8),1+('Indicator Data'!G8<=Indicators!$G8)+('Indicator Data'!G8<=Indicators!$H8)+('Indicator Data'!G8<=Indicators!$I8)+('Indicator Data'!G8<=Indicators!$J8))) -> 3 | H8: =IF('Indicator Data'!H8="",IF(Config!$C$15="Score as High (5)",5,0),IF(Indicators!$F8="Higher = riskier",1+('Indicator Data'!H8>=Indicators!$G8)+('Indicator Data'!H8>=Indicators!$H8)+('Indicator Data'!H8>=Indicators!$I8)+('Indicator Data'!H8>=Indicators!$J8),1+('Indicator Data'!H8<=Indicators!$G8)+('Indicator Data'!H8<=Indicators!$H8)+('Indicator Data'!H8<=Indicators!$I8)+('Indicator Data'!H8<=Indicators!$J8))) -> 4 | I8: =IF('Indicator Data'!I8="",IF(Config!$C$15="Score as High (5)",5,0),IF(Indicators!$F8="Higher = riskier",1+('Indicator Data'!I8>=Indicators!$G8)+('Indicator Data'!I8>=Indicators!$H8)+('Indicator Data'!I8>=Indicators!$I8)+('Indicator Data'!I8>=Indicators!$J8),1+('Indicator Data'!I8<=Indicators!$G8)+('Indicator Data'!I8<=Indicators!$H8)+('Indicator Data'!I8<=Indicators!$I8)+('Indicator Data'!I8<=Indicators!$J8))) -> 3 | J8: =IF('Indicator Data'!J8="",IF(Config!$C$15="Score as High (5)",5,0),IF(Indicators!$F8="Higher = riskier",1+('Indicator Data'!J8>=Indicators!$G8)+('Indicator Data'!J8>=Indicators!$H8)+('Indicator Data'!J8>=Indicators!$I8)+('Indicator Data'!J8>=Indicators!$J8),1+('Indicator Data'!J8<=Indicators!$G8)+('Indicator Data'!J8<=Indicators!$H8)+('Indicator Data'!J8<=Indicators!$I8)+('Indicator Data'!J8<=Indicators!$J8))) -> 4 | K8: =IF('Indicator Data'!K8="",IF(Config!$C$15="Score as High (5)",5,0),IF(Indicators!$F8="Higher = riskier",1+('Indicator Data'!K8>=Indicators!$G8)+('Indicator Data'!K8>=Indicators!$H8)+('Indicator Data'!K8>=Indicators!$I8)+('Indicator Data'!K8>=Indicators!$J8),1+('Indicator Data'!K8<=Indicators!$G8)+('Indicator Data'!K8<=Indicators!$H8)+('Indicator Data'!K8<=Indicators!$I8)+('Indicator Data'!K8<=Indicators!$J8))) -> 3 | ... AG8: =IF('Indicator Data'!AG8="",IF(Config!$C$15="Score as High (5)",5,0),IF(Indicators!$F8="Higher = riskier",1+('Indicator Data'!AG8>=Indicators!$G8)+('Indicator Data'!AG8>=Indicators!$H8)+('Indicator Data'!AG8>=Indicators!$I8)+('Indicator Data'!AG8>=Indicators!$J8),1+('Indicator Data'!AG8<=Indicators!$G8)+('Indicator Data'!AG8<=Indicators!$H8)+('Indicator Data'!AG8<=Indicators!$I8)+('Indicator Data'!AG8<=Indicators!$J8))) -> 2
A9: =Indicators!A9 -> C05 | B9: =Indicators!C9 -> % corporate customers with complex or opaque ownership | C9: =Indicators!D9 -> % | D9: =IF('Indicator Data'!D9="",IF(Config!$C$15="Score as High (5)",5,0),IF(Indicators!$F9="Higher = riskier",1+('Indicator Data'!D9>=Indicators!$G9)+('Indicator Data'!D9>=Indicators!$H9)+('Indicator Data'!D9>=Indicators!$I9)+('Indicator Data'!D9>=Indicators!$J9),1+('Indicator Data'!D9<=Indicators!$G9)+('Indicator Data'!D9<=Indicators!$H9)+('Indicator Data'!D9<=Indicators!$I9)+('Indicator Data'!D9<=Indicators!$J9))) -> 3 | E9: =IF('Indicator Data'!E9="",IF(Config!$C$15="Score as High (5)",5,0),IF(Indicators!$F9="Higher = riskier",1+('Indicator Data'!E9>=Indicators!$G9)+('Indicator Data'!E9>=Indicators!$H9)+('Indicator Data'!E9>=Indicators!$I9)+('Indicator Data'!E9>=Indicators!$J9),1+('Indicator Data'!E9<=Indicators!$G9)+('Indicator Data'!E9<=Indicators!$H9)+('Indicator Data'!E9<=Indicators!$I9)+('Indicator Data'!E9<=Indicators!$J9))) -> 5 | F9: =IF('Indicator Data'!F9="",IF(Config!$C$15="Score as High (5)",5,0),IF(Indicators!$F9="Higher = riskier",1+('Indicator Data'!F9>=Indicators!$G9)+('Indicator Data'!F9>=Indicators!$H9)+('Indicator Data'!F9>=Indicators!$I9)+('Indicator Data'!F9>=Indicators!$J9),1+('Indicator Data'!F9<=Indicators!$G9)+('Indicator Data'!F9<=Indicators!$H9)+('Indicator Data'!F9<=Indicators!$I9)+('Indicator Data'!F9<=Indicators!$J9))) -> 4 | G9: =IF('Indicator Data'!G9="",IF(Config!$C$15="Score as High (5)",5,0),IF(Indicators!$F9="Higher = riskier",1+('Indicator Data'!G9>=Indicators!$G9)+('Indicator Data'!G9>=Indicators!$H9)+('Indicator Data'!G9>=Indicators!$I9)+('Indicator Data'!G9>=Indicators!$J9),1+('Indicator Data'!G9<=Indicators!$G9)+('Indicator Data'!G9<=Indicators!$H9)+('Indicator Data'!G9<=Indicators!$I9)+('Indicator Data'!G9<=Indicators!$J9))) -> 4 | H9: =IF('Indicator Data'!H9="",IF(Config!$C$15="Score as High (5)",5,0),IF(Indicators!$F9="Higher = riskier",1+('Indicator Data'!H9>=Indicators!$G9)+('Indicator Data'!H9>=Indicators!$H9)+('Indicator Data'!H9>=Indicators!$I9)+('Indicator Data'!H9>=Indicators!$J9),1+('Indicator Data'!H9<=Indicators!$G9)+('Indicator Data'!H9<=Indicators!$H9)+('Indicator Data'!H9<=Indicators!$I9)+('Indicator Data'!H9<=Indicators!$J9))) -> 2 | I9: =IF('Indicator Data'!I9="",IF(Config!$C$15="Score as High (5)",5,0),IF(Indicators!$F9="Higher = riskier",1+('Indicator Data'!I9>=Indicators!$G9)+('Indicator Data'!I9>=Indicators!$H9)+('Indicator Data'!I9>=Indicators!$I9)+('Indicator Data'!I9>=Indicators!$J9),1+('Indicator Data'!I9<=Indicators!$G9)+('Indicator Data'!I9<=Indicators!$H9)+('Indicator Data'!I9<=Indicators!$I9)+('Indicator Data'!I9<=Indicators!$J9))) -> 3 | J9: =IF('Indicator Data'!J9="",IF(Config!$C$15="Score as High (5)",5,0),IF(Indicators!$F9="Higher = riskier",1+('Indicator Data'!J9>=Indicators!$G9)+('Indicator Data'!J9>=Indicators!$H9)+('Indicator Data'!J9>=Indicators!$I9)+('Indicator Data'!J9>=Indicators!$J9),1+('Indicator Data'!J9<=Indicators!$G9)+('Indicator Data'!J9<=Indicators!$H9)+('Indicator Data'!J9<=Indicators!$I9)+('Indicator Data'!J9<=Indicators!$J9))) -> 3 | K9: =IF('Indicator Data'!K9="",IF(Config!$C$15="Score as High (5)",5,0),IF(Indicators!$F9="Higher = riskier",1+('Indicator Data'!K9>=Indicators!$G9)+('Indicator Data'!K9>=Indicators!$H9)+('Indicator Data'!K9>=Indicators!$I9)+('Indicator Data'!K9>=Indicators!$J9),1+('Indicator Data'!K9<=Indicators!$G9)+('Indicator Data'!K9<=Indicators!$H9)+('Indicator Data'!K9<=Indicators!$I9)+('Indicator Data'!K9<=Indicators!$J9))) -> 5 | ... AG9: =IF('Indicator Data'!AG9="",IF(Config!$C$15="Score as High (5)",5,0),IF(Indicators!$F9="Higher = riskier",1+('Indicator Data'!AG9>=Indicators!$G9)+('Indicator Data'!AG9>=Indicators!$H9)+('Indicator Data'!AG9>=Indicators!$I9)+('Indicator Data'!AG9>=Indicators!$J9),1+('Indicator Data'!AG9<=Indicators!$G9)+('Indicator Data'!AG9<=Indicators!$H9)+('Indicator Data'!AG9<=Indicators!$I9)+('Indicator Data'!AG9<=Indicators!$J9))) -> 1
A10: =Indicators!A10 -> C06 | B10: =Indicators!C10 -> % customers in cash-intensive businesses | C10: =Indicators!D10 -> % | D10: =IF('Indicator Data'!D10="",IF(Config!$C$15="Score as High (5)",5,0),IF(Indicators!$F10="Higher = riskier",1+('Indicator Data'!D10>=Indicators!$G10)+('Indicator Data'!D10>=Indicators!$H10)+('Indicator Data'!D10>=Indicators!$I10)+('Indicator Data'!D10>=Indicators!$J10),1+('Indicator Data'!D10<=Indicators!$G10)+('Indicator Data'!D10<=Indicators!$H10)+('Indicator Data'!D10<=Indicators!$I10)+('Indicator Data'!D10<=Indicators!$J10))) -> 2 | E10: =IF('Indicator Data'!E10="",IF(Config!$C$15="Score as High (5)",5,0),IF(Indicators!$F10="Higher = riskier",1+('Indicator Data'!E10>=Indicators!$G10)+('Indicator Data'!E10>=Indicators!$H10)+('Indicator Data'!E10>=Indicators!$I10)+('Indicator Data'!E10>=Indicators!$J10),1+('Indicator Data'!E10<=Indicators!$G10)+('Indicator Data'!E10<=Indicators!$H10)+('Indicator Data'!E10<=Indicators!$I10)+('Indicator Data'!E10<=Indicators!$J10))) -> 1 | F10: =IF('Indicator Data'!F10="",IF(Config!$C$15="Score as High (5)",5,0),IF(Indicators!$F10="Higher = riskier",1+('Indicator Data'!F10>=Indicators!$G10)+('Indicator Data'!F10>=Indicators!$H10)+('Indicator Data'!F10>=Indicators!$I10)+('Indicator Data'!F10>=Indicators!$J10),1+('Indicator Data'!F10<=Indicators!$G10)+('Indicator Data'!F10<=Indicators!$H10)+('Indicator Data'!F10<=Indicators!$I10)+('Indicator Data'!F10<=Indicators!$J10))) -> 2 | G10: =IF('Indicator Data'!G10="",IF(Config!$C$15="Score as High (5)",5,0),IF(Indicators!$F10="Higher = riskier",1+('Indicator Data'!G10>=Indicators!$G10)+('Indicator Data'!G10>=Indicators!$H10)+('Indicator Data'!G10>=Indicators!$I10)+('Indicator Data'!G10>=Indicators!$J10),1+('Indicator Data'!G10<=Indicators!$G10)+('Indicator Data'!G10<=Indicators!$H10)+('Indicator Data'!G10<=Indicators!$I10)+('Indicator Data'!G10<=Indicators!$J10))) -> 2 | H10: =IF('Indicator Data'!H10="",IF(Config!$C$15="Score as High (5)",5,0),IF(Indicators!$F10="Higher = riskier",1+('Indicator Data'!H10>=Indicators!$G10)+('Indicator Data'!H10>=Indicators!$H10)+('Indicator Data'!H10>=Indicators!$I10)+('Indicator Data'!H10>=Indicators!$J10),1+('Indicator Data'!H10<=Indicators!$G10)+('Indicator Data'!H10<=Indicators!$H10)+('Indicator Data'!H10<=Indicators!$I10)+('Indicator Data'!H10<=Indicators!$J10))) -> 4 | I10: =IF('Indicator Data'!I10="",IF(Config!$C$15="Score as High (5)",5,0),IF(Indicators!$F10="Higher = riskier",1+('Indicator Data'!I10>=Indicators!$G10)+('Indicator Data'!I10>=Indicators!$H10)+('Indicator Data'!I10>=Indicators!$I10)+('Indicator Data'!I10>=Indicators!$J10),1+('Indicator Data'!I10<=Indicators!$G10)+('Indicator Data'!I10<=Indicators!$H10)+('Indicator Data'!I10<=Indicators!$I10)+('Indicator Data'!I10<=Indicators!$J10))) -> 3 | J10: =IF('Indicator Data'!J10="",IF(Config!$C$15="Score as High (5)",5,0),IF(Indicators!$F10="Higher = riskier",1+('Indicator Data'!J10>=Indicators!$G10)+('Indicator Data'!J10>=Indicators!$H10)+('Indicator Data'!J10>=Indicators!$I10)+('Indicator Data'!J10>=Indicators!$J10),1+('Indicator Data'!J10<=Indicators!$G10)+('Indicator Data'!J10<=Indicators!$H10)+('Indicator Data'!J10<=Indicators!$I10)+('Indicator Data'!J10<=Indicators!$J10))) -> 5 | K10: =IF('Indicator Data'!K10="",IF(Config!$C$15="Score as High (5)",5,0),IF(Indicators!$F10="Higher = riskier",1+('Indicator Data'!K10>=Indicators!$G10)+('Indicator Data'!K10>=Indicators!$H10)+('Indicator Data'!K10>=Indicators!$I10)+('Indicator Data'!K10>=Indicators!$J10),1+('Indicator Data'!K10<=Indicators!$G10)+('Indicator Data'!K10<=Indicators!$H10)+('Indicator Data'!K10<=Indicators!$I10)+('Indicator Data'!K10<=Indicators!$J10))) -> 4 | ... AG10: =IF('Indicator Data'!AG10="",IF(Config!$C$15="Score as High (5)",5,0),IF(Indicators!$F10="Higher = riskier",1+('Indicator Data'!AG10>=Indicators!$G10)+('Indicator Data'!AG10>=Indicators!$H10)+('Indicator Data'!AG10>=Indicators!$I10)+('Indicator Data'!AG10>=Indicators!$J10),1+('Indicator Data'!AG10<=Indicators!$G10)+('Indicator Data'!AG10<=Indicators!$H10)+('Indicator Data'!AG10<=Indicators!$I10)+('Indicator Data'!AG10<=Indicators!$J10))) -> 1
A11: =Indicators!A11 -> C07 | B11: =Indicators!C11 -> % customers that are government bodies or SOEs | C11: =Indicators!D11 -> % | D11: =IF('Indicator Data'!D11="",IF(Config!$C$15="Score as High (5)",5,0),IF(Indicators!$F11="Higher = riskier",1+('Indicator Data'!D11>=Indicators!$G11)+('Indicator Data'!D11>=Indicators!$H11)+('Indicator Data'!D11>=Indicators!$I11)+('Indicator Data'!D11>=Indicators!$J11),1+('Indicator Data'!D11<=Indicators!$G11)+('Indicator Data'!D11<=Indicators!$H11)+('Indicator Data'!D11<=Indicators!$I11)+('Indicator Data'!D11<=Indicators!$J11))) -> 3 | E11: =IF('Indicator Data'!E11="",IF(Config!$C$15="Score as High (5)",5,0),IF(Indicators!$F11="Higher = riskier",1+('Indicator Data'!E11>=Indicators!$G11)+('Indicator Data'!E11>=Indicators!$H11)+('Indicator Data'!E11>=Indicators!$I11)+('Indicator Data'!E11>=Indicators!$J11),1+('Indicator Data'!E11<=Indicators!$G11)+('Indicator Data'!E11<=Indicators!$H11)+('Indicator Data'!E11<=Indicators!$I11)+('Indicator Data'!E11<=Indicators!$J11))) -> 3 | F11: =IF('Indicator Data'!F11="",IF(Config!$C$15="Score as High (5)",5,0),IF(Indicators!$F11="Higher = riskier",1+('Indicator Data'!F11>=Indicators!$G11)+('Indicator Data'!F11>=Indicators!$H11)+('Indicator Data'!F11>=Indicators!$I11)+('Indicator Data'!F11>=Indicators!$J11),1+('Indicator Data'!F11<=Indicators!$G11)+('Indicator Data'!F11<=Indicators!$H11)+('Indicator Data'!F11<=Indicators!$I11)+('Indicator Data'!F11<=Indicators!$J11))) -> 2 | G11: =IF('Indicator Data'!G11="",IF(Config!$C$15="Score as High (5)",5,0),IF(Indicators!$F11="Higher = riskier",1+('Indicator Data'!G11>=Indicators!$G11)+('Indicator Data'!G11>=Indicators!$H11)+('Indicator Data'!G11>=Indicators!$I11)+('Indicator Data'!G11>=Indicators!$J11),1+('Indicator Data'!G11<=Indicators!$G11)+('Indicator Data'!G11<=Indicators!$H11)+('Indicator Data'!G11<=Indicators!$I11)+('Indicator Data'!G11<=Indicators!$J11))) -> 2 | H11: =IF('Indicator Data'!H11="",IF(Config!$C$15="Score as High (5)",5,0),IF(Indicators!$F11="Higher = riskier",1+('Indicator Data'!H11>=Indicators!$G11)+('Indicator Data'!H11>=Indicators!$H11)+('Indicator Data'!H11>=Indicators!$I11)+('Indicator Data'!H11>=Indicators!$J11),1+('Indicator Data'!H11<=Indicators!$G11)+('Indicator Data'!H11<=Indicators!$H11)+('Indicator Data'!H11<=Indicators!$I11)+('Indicator Data'!H11<=Indicators!$J11))) -> 2 | I11: =IF('Indicator Data'!I11="",IF(Config!$C$15="Score as High (5)",5,0),IF(Indicators!$F11="Higher = riskier",1+('Indicator Data'!I11>=Indicators!$G11)+('Indicator Data'!I11>=Indicators!$H11)+('Indicator Data'!I11>=Indicators!$I11)+('Indicator Data'!I11>=Indicators!$J11),1+('Indicator Data'!I11<=Indicators!$G11)+('Indicator Data'!I11<=Indicators!$H11)+('Indicator Data'!I11<=Indicators!$I11)+('Indicator Data'!I11<=Indicators!$J11))) -> 4 | J11: =IF('Indicator Data'!J11="",IF(Config!$C$15="Score as High (5)",5,0),IF(Indicators!$F11="Higher = riskier",1+('Indicator Data'!J11>=Indicators!$G11)+('Indicator Data'!J11>=Indicators!$H11)+('Indicator Data'!J11>=Indicators!$I11)+('Indicator Data'!J11>=Indicators!$J11),1+('Indicator Data'!J11<=Indicators!$G11)+('Indicator Data'!J11<=Indicators!$H11)+('Indicator Data'!J11<=Indicators!$I11)+('Indicator Data'!J11<=Indicators!$J11))) -> 3 | K11: =IF('Indicator Data'!K11="",IF(Config!$C$15="Score as High (5)",5,0),IF(Indicators!$F11="Higher = riskier",1+('Indicator Data'!K11>=Indicators!$G11)+('Indicator Data'!K11>=Indicators!$H11)+('Indicator Data'!K11>=Indicators!$I11)+('Indicator Data'!K11>=Indicators!$J11),1+('Indicator Data'!K11<=Indicators!$G11)+('Indicator Data'!K11<=Indicators!$H11)+('Indicator Data'!K11<=Indicators!$I11)+('Indicator Data'!K11<=Indicators!$J11))) -> 4 | ... AG11: =IF('Indicator Data'!AG11="",IF(Config!$C$15="Score as High (5)",5,0),IF(Indicators!$F11="Higher = riskier",1+('Indicator Data'!AG11>=Indicators!$G11)+('Indicator Data'!AG11>=Indicators!$H11)+('Indicator Data'!AG11>=Indicators!$I11)+('Indicator Data'!AG11>=Indicators!$J11),1+('Indicator Data'!AG11<=Indicators!$G11)+('Indicator Data'!AG11<=Indicators!$H11)+('Indicator Data'!AG11<=Indicators!$I11)+('Indicator Data'!AG11<=Indicators!$J11))) -> 1
A12: =Indicators!A12 -> G01 | B12: =Indicators!C12 -> % cross-border value with FATF high-risk / increased-monitoring jurisdictions | C12: =Indicators!D12 -> % | D12: =IF('Indicator Data'!D12="",IF(Config!$C$15="Score as High (5)",5,0),IF(Indicators!$F12="Higher = riskier",1+('Indicator Data'!D12>=Indicators!$G12)+('Indicator Data'!D12>=Indicators!$H12)+('Indicator Data'!D12>=Indicators!$I12)+('Indicator Data'!D12>=Indicators!$J12),1+('Indicator Data'!D12<=Indicators!$G12)+('Indicator Data'!D12<=Indicators!$H12)+('Indicator Data'!D12<=Indicators!$I12)+('Indicator Data'!D12<=Indicators!$J12))) -> 2 | E12: =IF('Indicator Data'!E12="",IF(Config!$C$15="Score as High (5)",5,0),IF(Indicators!$F12="Higher = riskier",1+('Indicator Data'!E12>=Indicators!$G12)+('Indicator Data'!E12>=Indicators!$H12)+('Indicator Data'!E12>=Indicators!$I12)+('Indicator Data'!E12>=Indicators!$J12),1+('Indicator Data'!E12<=Indicators!$G12)+('Indicator Data'!E12<=Indicators!$H12)+('Indicator Data'!E12<=Indicators!$I12)+('Indicator Data'!E12<=Indicators!$J12))) -> 2 | F12: =IF('Indicator Data'!F12="",IF(Config!$C$15="Score as High (5)",5,0),IF(Indicators!$F12="Higher = riskier",1+('Indicator Data'!F12>=Indicators!$G12)+('Indicator Data'!F12>=Indicators!$H12)+('Indicator Data'!F12>=Indicators!$I12)+('Indicator Data'!F12>=Indicators!$J12),1+('Indicator Data'!F12<=Indicators!$G12)+('Indicator Data'!F12<=Indicators!$H12)+('Indicator Data'!F12<=Indicators!$I12)+('Indicator Data'!F12<=Indicators!$J12))) -> 1 | G12: =IF('Indicator Data'!G12="",IF(Config!$C$15="Score as High (5)",5,0),IF(Indicators!$F12="Higher = riskier",1+('Indicator Data'!G12>=Indicators!$G12)+('Indicator Data'!G12>=Indicators!$H12)+('Indicator Data'!G12>=Indicators!$I12)+('Indicator Data'!G12>=Indicators!$J12),1+('Indicator Data'!G12<=Indicators!$G12)+('Indicator Data'!G12<=Indicators!$H12)+('Indicator Data'!G12<=Indicators!$I12)+('Indicator Data'!G12<=Indicators!$J12))) -> 3 | H12: =IF('Indicator Data'!H12="",IF(Config!$C$15="Score as High (5)",5,0),IF(Indicators!$F12="Higher = riskier",1+('Indicator Data'!H12>=Indicators!$G12)+('Indicator Data'!H12>=Indicators!$H12)+('Indicator Data'!H12>=Indicators!$I12)+('Indicator Data'!H12>=Indicators!$J12),1+('Indicator Data'!H12<=Indicators!$G12)+('Indicator Data'!H12<=Indicators!$H12)+('Indicator Data'!H12<=Indicators!$I12)+('Indicator Data'!H12<=Indicators!$J12))) -> 3 | I12: =IF('Indicator Data'!I12="",IF(Config!$C$15="Score as High (5)",5,0),IF(Indicators!$F12="Higher = riskier",1+('Indicator Data'!I12>=Indicators!$G12)+('Indicator Data'!I12>=Indicators!$H12)+('Indicator Data'!I12>=Indicators!$I12)+('Indicator Data'!I12>=Indicators!$J12),1+('Indicator Data'!I12<=Indicators!$G12)+('Indicator Data'!I12<=Indicators!$H12)+('Indicator Data'!I12<=Indicators!$I12)+('Indicator Data'!I12<=Indicators!$J12))) -> 5 | J12: =IF('Indicator Data'!J12="",IF(Config!$C$15="Score as High (5)",5,0),IF(Indicators!$F12="Higher = riskier",1+('Indicator Data'!J12>=Indicators!$G12)+('Indicator Data'!J12>=Indicators!$H12)+('Indicator Data'!J12>=Indicators!$I12)+('Indicator Data'!J12>=Indicators!$J12),1+('Indicator Data'!J12<=Indicators!$G12)+('Indicator Data'!J12<=Indicators!$H12)+('Indicator Data'!J12<=Indicators!$I12)+('Indicator Data'!J12<=Indicators!$J12))) -> 4 | K12: =IF('Indicator Data'!K12="",IF(Config!$C$15="Score as High (5)",5,0),IF(Indicators!$F12="Higher = riskier",1+('Indicator Data'!K12>=Indicators!$G12)+('Indicator Data'!K12>=Indicators!$H12)+('Indicator Data'!K12>=Indicators!$I12)+('Indicator Data'!K12>=Indicators!$J12),1+('Indicator Data'!K12<=Indicators!$G12)+('Indicator Data'!K12<=Indicators!$H12)+('Indicator Data'!K12<=Indicators!$I12)+('Indicator Data'!K12<=Indicators!$J12))) -> 3 | ... AG12: =IF('Indicator Data'!AG12="",IF(Config!$C$15="Score as High (5)",5,0),IF(Indicators!$F12="Higher = riskier",1+('Indicator Data'!AG12>=Indicators!$G12)+('Indicator Data'!AG12>=Indicators!$H12)+('Indicator Data'!AG12>=Indicators!$I12)+('Indicator Data'!AG12>=Indicators!$J12),1+('Indicator Data'!AG12<=Indicators!$G12)+('Indicator Data'!AG12<=Indicators!$H12)+('Indicator Data'!AG12<=Indicators!$I12)+('Indicator Data'!AG12<=Indicators!$J12))) -> 2
A13: =Indicators!A13 -> G02 | B13: =Indicators!C13 -> % payment value involving sanctioned or high sanctions-risk jurisdictions | C13: =Indicators!D13 -> % | D13: =IF('Indicator Data'!D13="",IF(Config!$C$15="Score as High (5)",5,0),IF(Indicators!$F13="Higher = riskier",1+('Indicator Data'!D13>=Indicators!$G13)+('Indicator Data'!D13>=Indicators!$H13)+('Indicator Data'!D13>=Indicators!$I13)+('Indicator Data'!D13>=Indicators!$J13),1+('Indicator Data'!D13<=Indicators!$G13)+('Indicator Data'!D13<=Indicators!$H13)+('Indicator Data'!D13<=Indicators!$I13)+('Indicator Data'!D13<=Indicators!$J13))) -> 4 | E13: =IF('Indicator Data'!E13="",IF(Config!$C$15="Score as High (5)",5,0),IF(Indicators!$F13="Higher = riskier",1+('Indicator Data'!E13>=Indicators!$G13)+('Indicator Data'!E13>=Indicators!$H13)+('Indicator Data'!E13>=Indicators!$I13)+('Indicator Data'!E13>=Indicators!$J13),1+('Indicator Data'!E13<=Indicators!$G13)+('Indicator Data'!E13<=Indicators!$H13)+('Indicator Data'!E13<=Indicators!$I13)+('Indicator Data'!E13<=Indicators!$J13))) -> 2 | F13: =IF('Indicator Data'!F13="",IF(Config!$C$15="Score as High (5)",5,0),IF(Indicators!$F13="Higher = riskier",1+('Indicator Data'!F13>=Indicators!$G13)+('Indicator Data'!F13>=Indicators!$H13)+('Indicator Data'!F13>=Indicators!$I13)+('Indicator Data'!F13>=Indicators!$J13),1+('Indicator Data'!F13<=Indicators!$G13)+('Indicator Data'!F13<=Indicators!$H13)+('Indicator Data'!F13<=Indicators!$I13)+('Indicator Data'!F13<=Indicators!$J13))) -> 2 | G13: =IF('Indicator Data'!G13="",IF(Config!$C$15="Score as High (5)",5,0),IF(Indicators!$F13="Higher = riskier",1+('Indicator Data'!G13>=Indicators!$G13)+('Indicator Data'!G13>=Indicators!$H13)+('Indicator Data'!G13>=Indicators!$I13)+('Indicator Data'!G13>=Indicators!$J13),1+('Indicator Data'!G13<=Indicators!$G13)+('Indicator Data'!G13<=Indicators!$H13)+('Indicator Data'!G13<=Indicators!$I13)+('Indicator Data'!G13<=Indicators!$J13))) -> 5 | H13: =IF('Indicator Data'!H13="",IF(Config!$C$15="Score as High (5)",5,0),IF(Indicators!$F13="Higher = riskier",1+('Indicator Data'!H13>=Indicators!$G13)+('Indicator Data'!H13>=Indicators!$H13)+('Indicator Data'!H13>=Indicators!$I13)+('Indicator Data'!H13>=Indicators!$J13),1+('Indicator Data'!H13<=Indicators!$G13)+('Indicator Data'!H13<=Indicators!$H13)+('Indicator Data'!H13<=Indicators!$I13)+('Indicator Data'!H13<=Indicators!$J13))) -> 4 | I13: =IF('Indicator Data'!I13="",IF(Config!$C$15="Score as High (5)",5,0),IF(Indicators!$F13="Higher = riskier",1+('Indicator Data'!I13>=Indicators!$G13)+('Indicator Data'!I13>=Indicators!$H13)+('Indicator Data'!I13>=Indicators!$I13)+('Indicator Data'!I13>=Indicators!$J13),1+('Indicator Data'!I13<=Indicators!$G13)+('Indicator Data'!I13<=Indicators!$H13)+('Indicator Data'!I13<=Indicators!$I13)+('Indicator Data'!I13<=Indicators!$J13))) -> 5 | J13: =IF('Indicator Data'!J13="",IF(Config!$C$15="Score as High (5)",5,0),IF(Indicators!$F13="Higher = riskier",1+('Indicator Data'!J13>=Indicators!$G13)+('Indicator Data'!J13>=Indicators!$H13)+('Indicator Data'!J13>=Indicators!$I13)+('Indicator Data'!J13>=Indicators!$J13),1+('Indicator Data'!J13<=Indicators!$G13)+('Indicator Data'!J13<=Indicators!$H13)+('Indicator Data'!J13<=Indicators!$I13)+('Indicator Data'!J13<=Indicators!$J13))) -> 4 | K13: =IF('Indicator Data'!K13="",IF(Config!$C$15="Score as High (5)",5,0),IF(Indicators!$F13="Higher = riskier",1+('Indicator Data'!K13>=Indicators!$G13)+('Indicator Data'!K13>=Indicators!$H13)+('Indicator Data'!K13>=Indicators!$I13)+('Indicator Data'!K13>=Indicators!$J13),1+('Indicator Data'!K13<=Indicators!$G13)+('Indicator Data'!K13<=Indicators!$H13)+('Indicator Data'!K13<=Indicators!$I13)+('Indicator Data'!K13<=Indicators!$J13))) -> 4 | ... AG13: =IF('Indicator Data'!AG13="",IF(Config!$C$15="Score as High (5)",5,0),IF(Indicators!$F13="Higher = riskier",1+('Indicator Data'!AG13>=Indicators!$G13)+('Indicator Data'!AG13>=Indicators!$H13)+('Indicator Data'!AG13>=Indicators!$I13)+('Indicator Data'!AG13>=Indicators!$J13),1+('Indicator Data'!AG13<=Indicators!$G13)+('Indicator Data'!AG13<=Indicators!$H13)+('Indicator Data'!AG13<=Indicators!$I13)+('Indicator Data'!AG13<=Indicators!$J13))) -> 2
A14: =Indicators!A14 -> G03 | B14: =Indicators!C14 -> Host-country national ML/TF risk (NRA-based, 1–5) | C14: =Indicators!D14 -> score 1–5 | D14: =IF('Indicator Data'!D14="",IF(Config!$C$15="Score as High (5)",5,0),IF(Indicators!$F14="Higher = riskier",1+('Indicator Data'!D14>=Indicators!$G14)+('Indicator Data'!D14>=Indicators!$H14)+('Indicator Data'!D14>=Indicators!$I14)+('Indicator Data'!D14>=Indicators!$J14),1+('Indicator Data'!D14<=Indicators!$G14)+('Indicator Data'!D14<=Indicators!$H14)+('Indicator Data'!D14<=Indicators!$I14)+('Indicator Data'!D14<=Indicators!$J14))) -> 4 | E14: =IF('Indicator Data'!E14="",IF(Config!$C$15="Score as High (5)",5,0),IF(Indicators!$F14="Higher = riskier",1+('Indicator Data'!E14>=Indicators!$G14)+('Indicator Data'!E14>=Indicators!$H14)+('Indicator Data'!E14>=Indicators!$I14)+('Indicator Data'!E14>=Indicators!$J14),1+('Indicator Data'!E14<=Indicators!$G14)+('Indicator Data'!E14<=Indicators!$H14)+('Indicator Data'!E14<=Indicators!$I14)+('Indicator Data'!E14<=Indicators!$J14))) -> 2 | F14: =IF('Indicator Data'!F14="",IF(Config!$C$15="Score as High (5)",5,0),IF(Indicators!$F14="Higher = riskier",1+('Indicator Data'!F14>=Indicators!$G14)+('Indicator Data'!F14>=Indicators!$H14)+('Indicator Data'!F14>=Indicators!$I14)+('Indicator Data'!F14>=Indicators!$J14),1+('Indicator Data'!F14<=Indicators!$G14)+('Indicator Data'!F14<=Indicators!$H14)+('Indicator Data'!F14<=Indicators!$I14)+('Indicator Data'!F14<=Indicators!$J14))) -> 3 | G14: =IF('Indicator Data'!G14="",IF(Config!$C$15="Score as High (5)",5,0),IF(Indicators!$F14="Higher = riskier",1+('Indicator Data'!G14>=Indicators!$G14)+('Indicator Data'!G14>=Indicators!$H14)+('Indicator Data'!G14>=Indicators!$I14)+('Indicator Data'!G14>=Indicators!$J14),1+('Indicator Data'!G14<=Indicators!$G14)+('Indicator Data'!G14<=Indicators!$H14)+('Indicator Data'!G14<=Indicators!$I14)+('Indicator Data'!G14<=Indicators!$J14))) -> 3 | H14: =IF('Indicator Data'!H14="",IF(Config!$C$15="Score as High (5)",5,0),IF(Indicators!$F14="Higher = riskier",1+('Indicator Data'!H14>=Indicators!$G14)+('Indicator Data'!H14>=Indicators!$H14)+('Indicator Data'!H14>=Indicators!$I14)+('Indicator Data'!H14>=Indicators!$J14),1+('Indicator Data'!H14<=Indicators!$G14)+('Indicator Data'!H14<=Indicators!$H14)+('Indicator Data'!H14<=Indicators!$I14)+('Indicator Data'!H14<=Indicators!$J14))) -> 4 | I14: =IF('Indicator Data'!I14="",IF(Config!$C$15="Score as High (5)",5,0),IF(Indicators!$F14="Higher = riskier",1+('Indicator Data'!I14>=Indicators!$G14)+('Indicator Data'!I14>=Indicators!$H14)+('Indicator Data'!I14>=Indicators!$I14)+('Indicator Data'!I14>=Indicators!$J14),1+('Indicator Data'!I14<=Indicators!$G14)+('Indicator Data'!I14<=Indicators!$H14)+('Indicator Data'!I14<=Indicators!$I14)+('Indicator Data'!I14<=Indicators!$J14))) -> 4 | J14: =IF('Indicator Data'!J14="",IF(Config!$C$15="Score as High (5)",5,0),IF(Indicators!$F14="Higher = riskier",1+('Indicator Data'!J14>=Indicators!$G14)+('Indicator Data'!J14>=Indicators!$H14)+('Indicator Data'!J14>=Indicators!$I14)+('Indicator Data'!J14>=Indicators!$J14),1+('Indicator Data'!J14<=Indicators!$G14)+('Indicator Data'!J14<=Indicators!$H14)+('Indicator Data'!J14<=Indicators!$I14)+('Indicator Data'!J14<=Indicators!$J14))) -> 5 | K14: =IF('Indicator Data'!K14="",IF(Config!$C$15="Score as High (5)",5,0),IF(Indicators!$F14="Higher = riskier",1+('Indicator Data'!K14>=Indicators!$G14)+('Indicator Data'!K14>=Indicators!$H14)+('Indicator Data'!K14>=Indicators!$I14)+('Indicator Data'!K14>=Indicators!$J14),1+('Indicator Data'!K14<=Indicators!$G14)+('Indicator Data'!K14<=Indicators!$H14)+('Indicator Data'!K14<=Indicators!$I14)+('Indicator Data'!K14<=Indicators!$J14))) -> 5 | ... AG14: =IF('Indicator Data'!AG14="",IF(Config!$C$15="Score as High (5)",5,0),IF(Indicators!$F14="Higher = riskier",1+('Indicator Data'!AG14>=Indicators!$G14)+('Indicator Data'!AG14>=Indicators!$H14)+('Indicator Data'!AG14>=Indicators!$I14)+('Indicator Data'!AG14>=Indicators!$J14),1+('Indicator Data'!AG14<=Indicators!$G14)+('Indicator Data'!AG14<=Indicators!$H14)+('Indicator Data'!AG14<=Indicators!$I14)+('Indicator Data'!AG14<=Indicators!$J14))) -> 3
A15: =Indicators!A15 -> G04 | B15: =Indicators!C15 -> Host-country corruption risk (CPI-based, 1–5) | C15: =Indicators!D15 -> score 1–5 | D15: =IF('Indicator Data'!D15="",IF(Config!$C$15="Score as High (5)",5,0),IF(Indicators!$F15="Higher = riskier",1+('Indicator Data'!D15>=Indicators!$G15)+('Indicator Data'!D15>=Indicators!$H15)+('Indicator Data'!D15>=Indicators!$I15)+('Indicator Data'!D15>=Indicators!$J15),1+('Indicator Data'!D15<=Indicators!$G15)+('Indicator Data'!D15<=Indicators!$H15)+('Indicator Data'!D15<=Indicators!$I15)+('Indicator Data'!D15<=Indicators!$J15))) -> 3 | E15: =IF('Indicator Data'!E15="",IF(Config!$C$15="Score as High (5)",5,0),IF(Indicators!$F15="Higher = riskier",1+('Indicator Data'!E15>=Indicators!$G15)+('Indicator Data'!E15>=Indicators!$H15)+('Indicator Data'!E15>=Indicators!$I15)+('Indicator Data'!E15>=Indicators!$J15),1+('Indicator Data'!E15<=Indicators!$G15)+('Indicator Data'!E15<=Indicators!$H15)+('Indicator Data'!E15<=Indicators!$I15)+('Indicator Data'!E15<=Indicators!$J15))) -> 3 | F15: =IF('Indicator Data'!F15="",IF(Config!$C$15="Score as High (5)",5,0),IF(Indicators!$F15="Higher = riskier",1+('Indicator Data'!F15>=Indicators!$G15)+('Indicator Data'!F15>=Indicators!$H15)+('Indicator Data'!F15>=Indicators!$I15)+('Indicator Data'!F15>=Indicators!$J15),1+('Indicator Data'!F15<=Indicators!$G15)+('Indicator Data'!F15<=Indicators!$H15)+('Indicator Data'!F15<=Indicators!$I15)+('Indicator Data'!F15<=Indicators!$J15))) -> 3 | G15: =IF('Indicator Data'!G15="",IF(Config!$C$15="Score as High (5)",5,0),IF(Indicators!$F15="Higher = riskier",1+('Indicator Data'!G15>=Indicators!$G15)+('Indicator Data'!G15>=Indicators!$H15)+('Indicator Data'!G15>=Indicators!$I15)+('Indicator Data'!G15>=Indicators!$J15),1+('Indicator Data'!G15<=Indicators!$G15)+('Indicator Data'!G15<=Indicators!$H15)+('Indicator Data'!G15<=Indicators!$I15)+('Indicator Data'!G15<=Indicators!$J15))) -> 3 | H15: =IF('Indicator Data'!H15="",IF(Config!$C$15="Score as High (5)",5,0),IF(Indicators!$F15="Higher = riskier",1+('Indicator Data'!H15>=Indicators!$G15)+('Indicator Data'!H15>=Indicators!$H15)+('Indicator Data'!H15>=Indicators!$I15)+('Indicator Data'!H15>=Indicators!$J15),1+('Indicator Data'!H15<=Indicators!$G15)+('Indicator Data'!H15<=Indicators!$H15)+('Indicator Data'!H15<=Indicators!$I15)+('Indicator Data'!H15<=Indicators!$J15))) -> 4 | I15: =IF('Indicator Data'!I15="",IF(Config!$C$15="Score as High (5)",5,0),IF(Indicators!$F15="Higher = riskier",1+('Indicator Data'!I15>=Indicators!$G15)+('Indicator Data'!I15>=Indicators!$H15)+('Indicator Data'!I15>=Indicators!$I15)+('Indicator Data'!I15>=Indicators!$J15),1+('Indicator Data'!I15<=Indicators!$G15)+('Indicator Data'!I15<=Indicators!$H15)+('Indicator Data'!I15<=Indicators!$I15)+('Indicator Data'!I15<=Indicators!$J15))) -> 4 | J15: =IF('Indicator Data'!J15="",IF(Config!$C$15="Score as High (5)",5,0),IF(Indicators!$F15="Higher = riskier",1+('Indicator Data'!J15>=Indicators!$G15)+('Indicator Data'!J15>=Indicators!$H15)+('Indicator Data'!J15>=Indicators!$I15)+('Indicator Data'!J15>=Indicators!$J15),1+('Indicator Data'!J15<=Indicators!$G15)+('Indicator Data'!J15<=Indicators!$H15)+('Indicator Data'!J15<=Indicators!$I15)+('Indicator Data'!J15<=Indicators!$J15))) -> 4 | K15: =IF('Indicator Data'!K15="",IF(Config!$C$15="Score as High (5)",5,0),IF(Indicators!$F15="Higher = riskier",1+('Indicator Data'!K15>=Indicators!$G15)+('Indicator Data'!K15>=Indicators!$H15)+('Indicator Data'!K15>=Indicators!$I15)+('Indicator Data'!K15>=Indicators!$J15),1+('Indicator Data'!K15<=Indicators!$G15)+('Indicator Data'!K15<=Indicators!$H15)+('Indicator Data'!K15<=Indicators!$I15)+('Indicator Data'!K15<=Indicators!$J15))) -> 4 | ... AG15: =IF('Indicator Data'!AG15="",IF(Config!$C$15="Score as High (5)",5,0),IF(Indicators!$F15="Higher = riskier",1+('Indicator Data'!AG15>=Indicators!$G15)+('Indicator Data'!AG15>=Indicators!$H15)+('Indicator Data'!AG15>=Indicators!$I15)+('Indicator Data'!AG15>=Indicators!$J15),1+('Indicator Data'!AG15<=Indicators!$G15)+('Indicator Data'!AG15<=Indicators!$H15)+('Indicator Data'!AG15<=Indicators!$I15)+('Indicator Data'!AG15<=Indicators!$J15))) -> 2
A16: =Indicators!A16 -> G05 | B16: =Indicators!C16 -> % branches in border, free-zone or conflict-affected areas | C16: =Indicators!D16 -> % | D16: =IF('Indicator Data'!D16="",IF(Config!$C$15="Score as High (5)",5,0),IF(Indicators!$F16="Higher = riskier",1+('Indicator Data'!D16>=Indicators!$G16)+('Indicator Data'!D16>=Indicators!$H16)+('Indicator Data'!D16>=Indicators!$I16)+('Indicator Data'!D16>=Indicators!$J16),1+('Indicator Data'!D16<=Indicators!$G16)+('Indicator Data'!D16<=Indicators!$H16)+('Indicator Data'!D16<=Indicators!$I16)+('Indicator Data'!D16<=Indicators!$J16))) -> 2 | E16: =IF('Indicator Data'!E16="",IF(Config!$C$15="Score as High (5)",5,0),IF(Indicators!$F16="Higher = riskier",1+('Indicator Data'!E16>=Indicators!$G16)+('Indicator Data'!E16>=Indicators!$H16)+('Indicator Data'!E16>=Indicators!$I16)+('Indicator Data'!E16>=Indicators!$J16),1+('Indicator Data'!E16<=Indicators!$G16)+('Indicator Data'!E16<=Indicators!$H16)+('Indicator Data'!E16<=Indicators!$I16)+('Indicator Data'!E16<=Indicators!$J16))) -> 4 | F16: =IF('Indicator Data'!F16="",IF(Config!$C$15="Score as High (5)",5,0),IF(Indicators!$F16="Higher = riskier",1+('Indicator Data'!F16>=Indicators!$G16)+('Indicator Data'!F16>=Indicators!$H16)+('Indicator Data'!F16>=Indicators!$I16)+('Indicator Data'!F16>=Indicators!$J16),1+('Indicator Data'!F16<=Indicators!$G16)+('Indicator Data'!F16<=Indicators!$H16)+('Indicator Data'!F16<=Indicators!$I16)+('Indicator Data'!F16<=Indicators!$J16))) -> 3 | G16: =IF('Indicator Data'!G16="",IF(Config!$C$15="Score as High (5)",5,0),IF(Indicators!$F16="Higher = riskier",1+('Indicator Data'!G16>=Indicators!$G16)+('Indicator Data'!G16>=Indicators!$H16)+('Indicator Data'!G16>=Indicators!$I16)+('Indicator Data'!G16>=Indicators!$J16),1+('Indicator Data'!G16<=Indicators!$G16)+('Indicator Data'!G16<=Indicators!$H16)+('Indicator Data'!G16<=Indicators!$I16)+('Indicator Data'!G16<=Indicators!$J16))) -> 3 | H16: =IF('Indicator Data'!H16="",IF(Config!$C$15="Score as High (5)",5,0),IF(Indicators!$F16="Higher = riskier",1+('Indicator Data'!H16>=Indicators!$G16)+('Indicator Data'!H16>=Indicators!$H16)+('Indicator Data'!H16>=Indicators!$I16)+('Indicator Data'!H16>=Indicators!$J16),1+('Indicator Data'!H16<=Indicators!$G16)+('Indicator Data'!H16<=Indicators!$H16)+('Indicator Data'!H16<=Indicators!$I16)+('Indicator Data'!H16<=Indicators!$J16))) -> 2 | I16: =IF('Indicator Data'!I16="",IF(Config!$C$15="Score as High (5)",5,0),IF(Indicators!$F16="Higher = riskier",1+('Indicator Data'!I16>=Indicators!$G16)+('Indicator Data'!I16>=Indicators!$H16)+('Indicator Data'!I16>=Indicators!$I16)+('Indicator Data'!I16>=Indicators!$J16),1+('Indicator Data'!I16<=Indicators!$G16)+('Indicator Data'!I16<=Indicators!$H16)+('Indicator Data'!I16<=Indicators!$I16)+('Indicator Data'!I16<=Indicators!$J16))) -> 2 | J16: =IF('Indicator Data'!J16="",IF(Config!$C$15="Score as High (5)",5,0),IF(Indicators!$F16="Higher = riskier",1+('Indicator Data'!J16>=Indicators!$G16)+('Indicator Data'!J16>=Indicators!$H16)+('Indicator Data'!J16>=Indicators!$I16)+('Indicator Data'!J16>=Indicators!$J16),1+('Indicator Data'!J16<=Indicators!$G16)+('Indicator Data'!J16<=Indicators!$H16)+('Indicator Data'!J16<=Indicators!$I16)+('Indicator Data'!J16<=Indicators!$J16))) -> 5 | K16: =IF('Indicator Data'!K16="",IF(Config!$C$15="Score as High (5)",5,0),IF(Indicators!$F16="Higher = riskier",1+('Indicator Data'!K16>=Indicators!$G16)+('Indicator Data'!K16>=Indicators!$H16)+('Indicator Data'!K16>=Indicators!$I16)+('Indicator Data'!K16>=Indicators!$J16),1+('Indicator Data'!K16<=Indicators!$G16)+('Indicator Data'!K16<=Indicators!$H16)+('Indicator Data'!K16<=Indicators!$I16)+('Indicator Data'!K16<=Indicators!$J16))) -> 4 | ... AG16: =IF('Indicator Data'!AG16="",IF(Config!$C$15="Score as High (5)",5,0),IF(Indicators!$F16="Higher = riskier",1+('Indicator Data'!AG16>=Indicators!$G16)+('Indicator Data'!AG16>=Indicators!$H16)+('Indicator Data'!AG16>=Indicators!$I16)+('Indicator Data'!AG16>=Indicators!$J16),1+('Indicator Data'!AG16<=Indicators!$G16)+('Indicator Data'!AG16<=Indicators!$H16)+('Indicator Data'!AG16<=Indicators!$I16)+('Indicator Data'!AG16<=Indicators!$J16))) -> 1
... A35: =Indicators!A35 -> T07 | B35: =Indicators!C35 -> FATCA/CRS reportable accounts (% of accounts) | C35: =Indicators!D35 -> % | D35: =IF('Indicator Data'!D35="",IF(Config!$C$15="Score as High (5)",5,0),IF(Indicators!$F35="Higher = riskier",1+('Indicator Data'!D35>=Indicators!$G35)+('Indicator Data'!D35>=Indicators!$H35)+('Indicator Data'!D35>=Indicators!$I35)+('Indicator Data'!D35>=Indicators!$J35),1+('Indicator Data'!D35<=Indicators!$G35)+('Indicator Data'!D35<=Indicators!$H35)+('Indicator Data'!D35<=Indicators!$I35)+('Indicator Data'!D35<=Indicators!$J35))) -> 3 | E35: =IF('Indicator Data'!E35="",IF(Config!$C$15="Score as High (5)",5,0),IF(Indicators!$F35="Higher = riskier",1+('Indicator Data'!E35>=Indicators!$G35)+('Indicator Data'!E35>=Indicators!$H35)+('Indicator Data'!E35>=Indicators!$I35)+('Indicator Data'!E35>=Indicators!$J35),1+('Indicator Data'!E35<=Indicators!$G35)+('Indicator Data'!E35<=Indicators!$H35)+('Indicator Data'!E35<=Indicators!$I35)+('Indicator Data'!E35<=Indicators!$J35))) -> 3 | F35: =IF('Indicator Data'!F35="",IF(Config!$C$15="Score as High (5)",5,0),IF(Indicators!$F35="Higher = riskier",1+('Indicator Data'!F35>=Indicators!$G35)+('Indicator Data'!F35>=Indicators!$H35)+('Indicator Data'!F35>=Indicators!$I35)+('Indicator Data'!F35>=Indicators!$J35),1+('Indicator Data'!F35<=Indicators!$G35)+('Indicator Data'!F35<=Indicators!$H35)+('Indicator Data'!F35<=Indicators!$I35)+('Indicator Data'!F35<=Indicators!$J35))) -> 3 | G35: =IF('Indicator Data'!G35="",IF(Config!$C$15="Score as High (5)",5,0),IF(Indicators!$F35="Higher = riskier",1+('Indicator Data'!G35>=Indicators!$G35)+('Indicator Data'!G35>=Indicators!$H35)+('Indicator Data'!G35>=Indicators!$I35)+('Indicator Data'!G35>=Indicators!$J35),1+('Indicator Data'!G35<=Indicators!$G35)+('Indicator Data'!G35<=Indicators!$H35)+('Indicator Data'!G35<=Indicators!$I35)+('Indicator Data'!G35<=Indicators!$J35))) -> 3 | H35: =IF('Indicator Data'!H35="",IF(Config!$C$15="Score as High (5)",5,0),IF(Indicators!$F35="Higher = riskier",1+('Indicator Data'!H35>=Indicators!$G35)+('Indicator Data'!H35>=Indicators!$H35)+('Indicator Data'!H35>=Indicators!$I35)+('Indicator Data'!H35>=Indicators!$J35),1+('Indicator Data'!H35<=Indicators!$G35)+('Indicator Data'!H35<=Indicators!$H35)+('Indicator Data'!H35<=Indicators!$I35)+('Indicator Data'!H35<=Indicators!$J35))) -> 2 | I35: =IF('Indicator Data'!I35="",IF(Config!$C$15="Score as High (5)",5,0),IF(Indicators!$F35="Higher = riskier",1+('Indicator Data'!I35>=Indicators!$G35)+('Indicator Data'!I35>=Indicators!$H35)+('Indicator Data'!I35>=Indicators!$I35)+('Indicator Data'!I35>=Indicators!$J35),1+('Indicator Data'!I35<=Indicators!$G35)+('Indicator Data'!I35<=Indicators!$H35)+('Indicator Data'!I35<=Indicators!$I35)+('Indicator Data'!I35<=Indicators!$J35))) -> 4 | J35: =IF('Indicator Data'!J35="",IF(Config!$C$15="Score as High (5)",5,0),IF(Indicators!$F35="Higher = riskier",1+('Indicator Data'!J35>=Indicators!$G35)+('Indicator Data'!J35>=Indicators!$H35)+('Indicator Data'!J35>=Indicators!$I35)+('Indicator Data'!J35>=Indicators!$J35),1+('Indicator Data'!J35<=Indicators!$G35)+('Indicator Data'!J35<=Indicators!$H35)+('Indicator Data'!J35<=Indicators!$I35)+('Indicator Data'!J35<=Indicators!$J35))) -> 5 | K35: =IF('Indicator Data'!K35="",IF(Config!$C$15="Score as High (5)",5,0),IF(Indicators!$F35="Higher = riskier",1+('Indicator Data'!K35>=Indicators!$G35)+('Indicator Data'!K35>=Indicators!$H35)+('Indicator Data'!K35>=Indicators!$I35)+('Indicator Data'!K35>=Indicators!$J35),1+('Indicator Data'!K35<=Indicators!$G35)+('Indicator Data'!K35<=Indicators!$H35)+('Indicator Data'!K35<=Indicators!$I35)+('Indicator Data'!K35<=Indicators!$J35))) -> 5 | ... AG35: =IF('Indicator Data'!AG35="",IF(Config!$C$15="Score as High (5)",5,0),IF(Indicators!$F35="Higher = riskier",1+('Indicator Data'!AG35>=Indicators!$G35)+('Indicator Data'!AG35>=Indicators!$H35)+('Indicator Data'!AG35>=Indicators!$I35)+('Indicator Data'!AG35>=Indicators!$J35),1+('Indicator Data'!AG35<=Indicators!$G35)+('Indicator Data'!AG35<=Indicators!$H35)+('Indicator Data'!AG35<=Indicators!$I35)+('Indicator Data'!AG35<=Indicators!$J35))) -> 2

Sheet FC Calculation
A1: Inherent risk – factor-based model (FC-01 to FC-07)
A2: One row per entity and risk. Factor score = weighted average of that factor's indicator scores using the risk's indicator weights. Edit only the yellow override columns.
A4: Entity code | B4: Entity | C4: Region | D4: Risk code | E4: Risk | F4: Customer | G4: Geography | H4: Products & services | I4: Delivery channels | J4: Transactions & volumes | K4: Weighted score | L4: Highest factor | M4: Floor-adjusted score | N4: Calculated inherent score | O4: Calculated rating (1–5) | P4: Calculated rating | Q4: Override (notches) | R4: Override justification | S4: HO approval (Y/N) | T4: Final score (1–5) | U4: Final rating | V4: Override status | W4: Data completeness
A5: =Entities!$A$5 -> JO-HO | B5: =INDEX(Entities!$B$5:$B$34,MATCH(A5,Entities!$A$5:$A$34,0)) -> Arab Bank plc – Jordan (HO and domestic network) | C5: =INDEX(Entities!$D$5:$D$34,MATCH(A5,Entities!$A$5:$A$34,0)) -> Jordan (home) | D5: FC-01 | E5: =INDEX('Risk Taxonomy'!$B$5:$B$24,MATCH(D5,'Risk Taxonomy'!$A$5:$A$24,0)) -> Money laundering | F5: =IFERROR(SUMPRODUCT((Indicators!$B$5:$B$35=F$4)*Indicators!$K$5:$K$35*'Indicator Scores'!$D$5:$D$35)/SUMPRODUCT((Indicators!$B$5:$B$35=F$4)*Indicators!$K$5:$K$35*('Indicator Scores'!$D$5:$D$35>0)),0) -> 3.25 | G5: =IFERROR(SUMPRODUCT((Indicators!$B$5:$B$35=G$4)*Indicators!$K$5:$K$35*'Indicator Scores'!$D$5:$D$35)/SUMPRODUCT((Indicators!$B$5:$B$35=G$4)*Indicators!$K$5:$K$35*('Indicator Scores'!$D$5:$D$35>0)),0) -> 2.8888889 | H5: =IFERROR(SUMPRODUCT((Indicators!$B$5:$B$35=H$4)*Indicators!$K$5:$K$35*'Indicator Scores'!$D$5:$D$35)/SUMPRODUCT((Indicators!$B$5:$B$35=H$4)*Indicators!$K$5:$K$35*('Indicator Scores'!$D$5:$D$35>0)),0) -> 3 | I5: =IFERROR(SUMPRODUCT((Indicators!$B$5:$B$35=I$4)*Indicators!$K$5:$K$35*'Indicator Scores'!$D$5:$D$35)/SUMPRODUCT((Indicators!$B$5:$B$35=I$4)*Indicators!$K$5:$K$35*('Indicator Scores'!$D$5:$D$35>0)),0) -> 2.8571429 | J5: =IFERROR(SUMPRODUCT((Indicators!$B$5:$B$35=J$4)*Indicators!$K$5:$K$35*'Indicator Scores'!$D$5:$D$35)/SUMPRODUCT((Indicators!$B$5:$B$35=J$4)*Indicators!$K$5:$K$35*('Indicator Scores'!$D$5:$D$35>0)),0) -> 2 | K5: =IFERROR(SUMPRODUCT(F5:J5,INDEX('Factor Weights'!$C$5:$G$11,MATCH(D5,'Factor Weights'!$A$5:$A$11,0),0))/SUMPRODUCT((F5:J5>0)*INDEX('Factor Weights'!$C$5:$G$11,MATCH(D5,'Factor Weights'!$A$5:$A$11,0),0)),0) -> 2.9257937 | L5: =MAX(F5:J5) -> 3.25 | M5: =IF(L5>=Config!$C$13,MAX(K5,Config!$C$14),K5) -> 2.9257937 | N5: =IF(Config!$C$12="Weighted average",K5,IF(Config!$C$12="Weighted with floor",M5,L5)) -> 2.9257937 | O5: =IF(N5<Config!$D$5,"",MATCH(N5,Config!$D$5:$D$9,1)) -> 3 | P5: =IF(O5="","No data",INDEX(Config!$B$5:$B$9,O5)) -> Medium | Q5: 0 | T5: =IF(O5="","",IF(AND(S5="Y",Q5<>0),MAX(1,MIN(5,O5+MAX(-Config!$C$27,MIN(Config!$C$27,Q5)))),O5)) -> 3 | U5: =IF(T5="","No data",INDEX(Config!$B$5:$B$9,T5)) -> Medium | V5: =IF(Q5=0,"None",IF(S5="Y","Applied","Pending HO approval")) -> None | W5: =SUMPRODUCT((Indicators!$K$5:$K$35>0)*('Indicator Data'!$D$5:$D$35<>""))/SUMPRODUCT(--(Indicators!$K$5:$K$35>0)) -> 1
A6: =Entities!$A$5 -> JO-HO | B6: =INDEX(Entities!$B$5:$B$34,MATCH(A6,Entities!$A$5:$A$34,0)) -> Arab Bank plc – Jordan (HO and domestic network) | C6: =INDEX(Entities!$D$5:$D$34,MATCH(A6,Entities!$A$5:$A$34,0)) -> Jordan (home) | D6: FC-02 | E6: =INDEX('Risk Taxonomy'!$B$5:$B$24,MATCH(D6,'Risk Taxonomy'!$A$5:$A$24,0)) -> Terrorist financing | F6: =IFERROR(SUMPRODUCT((Indicators!$B$5:$B$35=F$4)*Indicators!$L$5:$L$35*'Indicator Scores'!$D$5:$D$35)/SUMPRODUCT((Indicators!$B$5:$B$35=F$4)*Indicators!$L$5:$L$35*('Indicator Scores'!$D$5:$D$35>0)),0) -> 3.2 | G6: =IFERROR(SUMPRODUCT((Indicators!$B$5:$B$35=G$4)*Indicators!$L$5:$L$35*'Indicator Scores'!$D$5:$D$35)/SUMPRODUCT((Indicators!$B$5:$B$35=G$4)*Indicators!$L$5:$L$35*('Indicator Scores'!$D$5:$D$35>0)),0) -> 2.6666667 | H6: =IFERROR(SUMPRODUCT((Indicators!$B$5:$B$35=H$4)*Indicators!$L$5:$L$35*'Indicator Scores'!$D$5:$D$35)/SUMPRODUCT((Indicators!$B$5:$B$35=H$4)*Indicators!$L$5:$L$35*('Indicator Scores'!$D$5:$D$35>0)),0) -> 3.1666667 | I6: =IFERROR(SUMPRODUCT((Indicators!$B$5:$B$35=I$4)*Indicators!$L$5:$L$35*'Indicator Scores'!$D$5:$D$35)/SUMPRODUCT((Indicators!$B$5:$B$35=I$4)*Indicators!$L$5:$L$35*('Indicator Scores'!$D$5:$D$35>0)),0) -> 3 | J6: =IFERROR(SUMPRODUCT((Indicators!$B$5:$B$35=J$4)*Indicators!$L$5:$L$35*'Indicator Scores'!$D$5:$D$35)/SUMPRODUCT((Indicators!$B$5:$B$35=J$4)*Indicators!$L$5:$L$35*('Indicator Scores'!$D$5:$D$35>0)),0) -> 2 | K6: =IFERROR(SUMPRODUCT(F6:J6,INDEX('Factor Weights'!$C$5:$G$11,MATCH(D6,'Factor Weights'!$A$5:$A$11,0),0))/SUMPRODUCT((F6:J6>0)*INDEX('Factor Weights'!$C$5:$G$11,MATCH(D6,'Factor Weights'!$A$5:$A$11,0),0)),0) -> 2.775 | L6: =MAX(F6:J6) -> 3.2 | M6: =IF(L6>=Config!$C$13,MAX(K6,Config!$C$14),K6) -> 2.775 | N6: =IF(Config!$C$12="Weighted average",K6,IF(Config!$C$12="Weighted with floor",M6,L6)) -> 2.775 | O6: =IF(N6<Config!$D$5,"",MATCH(N6,Config!$D$5:$D$9,1)) -> 3 | P6: =IF(O6="","No data",INDEX(Config!$B$5:$B$9,O6)) -> Medium | Q6: 0 | T6: =IF(O6="","",IF(AND(S6="Y",Q6<>0),MAX(1,MIN(5,O6+MAX(-Config!$C$27,MIN(Config!$C$27,Q6)))),O6)) -> 3 | U6: =IF(T6="","No data",INDEX(Config!$B$5:$B$9,T6)) -> Medium | V6: =IF(Q6=0,"None",IF(S6="Y","Applied","Pending HO approval")) -> None | W6: =SUMPRODUCT((Indicators!$L$5:$L$35>0)*('Indicator Data'!$D$5:$D$35<>""))/SUMPRODUCT(--(Indicators!$L$5:$L$35>0)) -> 1
A7: =Entities!$A$5 -> JO-HO | B7: =INDEX(Entities!$B$5:$B$34,MATCH(A7,Entities!$A$5:$A$34,0)) -> Arab Bank plc – Jordan (HO and domestic network) | C7: =INDEX(Entities!$D$5:$D$34,MATCH(A7,Entities!$A$5:$A$34,0)) -> Jordan (home) | D7: FC-03 | E7: =INDEX('Risk Taxonomy'!$B$5:$B$24,MATCH(D7,'Risk Taxonomy'!$A$5:$A$24,0)) -> Proliferation financing | F7: =IFERROR(SUMPRODUCT((Indicators!$B$5:$B$35=F$4)*Indicators!$M$5:$M$35*'Indicator Scores'!$D$5:$D$35)/SUMPRODUCT((Indicators!$B$5:$B$35=F$4)*Indicators!$M$5:$M$35*('Indicator Scores'!$D$5:$D$35>0)),0) -> 3.25 | G7: =IFERROR(SUMPRODUCT((Indicators!$B$5:$B$35=G$4)*Indicators!$M$5:$M$35*'Indicator Scores'!$D$5:$D$35)/SUMPRODUCT((Indicators!$B$5:$B$35=G$4)*Indicators!$M$5:$M$35*('Indicator Scores'!$D$5:$D$35>0)),0) -> 3 | H7: =IFERROR(SUMPRODUCT((Indicators!$B$5:$B$35=H$4)*Indicators!$M$5:$M$35*'Indicator Scores'!$D$5:$D$35)/SUMPRODUCT((Indicators!$B$5:$B$35=H$4)*Indicators!$M$5:$M$35*('Indicator Scores'!$D$5:$D$35>0)),0) -> 3.6666667 | I7: =IFERROR(SUMPRODUCT((Indicators!$B$5:$B$35=I$4)*Indicators!$M$5:$M$35*'Indicator Scores'!$D$5:$D$35)/SUMPRODUCT((Indicators!$B$5:$B$35=I$4)*Indicators!$M$5:$M$35*('Indicator Scores'!$D$5:$D$35>0)),0) -> 3.6666667 | J7: =IFERROR(SUMPRODUCT((Indicators!$B$5:$B$35=J$4)*Indicators!$M$5:$M$35*'Indicator Scores'!$D$5:$D$35)/SUMPRODUCT((Indicators!$B$5:$B$35=J$4)*Indicators!$M$5:$M$35*('Indicator Scores'!$D$5:$D$35>0)),0) -> 3 | K7: =IFERROR(SUMPRODUCT(F7:J7,INDEX('Factor Weights'!$C$5:$G$11,MATCH(D7,'Factor Weights'!$A$5:$A$11,0),0))/SUMPRODUCT((F7:J7>0)*INDEX('Factor Weights'!$C$5:$G$11,MATCH(D7,'Factor Weights'!$A$5:$A$11,0),0)),0) -> 3.2708333 | L7: =MAX(F7:J7) -> 3.6666667 | M7: =IF(L7>=Config!$C$13,MAX(K7,Config!$C$14),K7) -> 3.2708333 | N7: =IF(Config!$C$12="Weighted average",K7,IF(Config!$C$12="Weighted with floor",M7,L7)) -> 3.2708333 | O7: =IF(N7<Config!$D$5,"",MATCH(N7,Config!$D$5:$D$9,1)) -> 3 | P7: =IF(O7="","No data",INDEX(Config!$B$5:$B$9,O7)) -> Medium | Q7: 0 | T7: =IF(O7="","",IF(AND(S7="Y",Q7<>0),MAX(1,MIN(5,O7+MAX(-Config!$C$27,MIN(Config!$C$27,Q7)))),O7)) -> 3 | U7: =IF(T7="","No data",INDEX(Config!$B$5:$B$9,T7)) -> Medium | V7: =IF(Q7=0,"None",IF(S7="Y","Applied","Pending HO approval")) -> None | W7: =SUMPRODUCT((Indicators!$M$5:$M$35>0)*('Indicator Data'!$D$5:$D$35<>""))/SUMPRODUCT(--(Indicators!$M$5:$M$35>0)) -> 1
A8: =Entities!$A$5 -> JO-HO | B8: =INDEX(Entities!$B$5:$B$34,MATCH(A8,Entities!$A$5:$A$34,0)) -> Arab Bank plc – Jordan (HO and domestic network) | C8: =INDEX(Entities!$D$5:$D$34,MATCH(A8,Entities!$A$5:$A$34,0)) -> Jordan (home) | D8: FC-04 | E8: =INDEX('Risk Taxonomy'!$B$5:$B$24,MATCH(D8,'Risk Taxonomy'!$A$5:$A$24,0)) -> Sanctions | F8: =IFERROR(SUMPRODUCT((Indicators!$B$5:$B$35=F$4)*Indicators!$N$5:$N$35*'Indicator Scores'!$D$5:$D$35)/SUMPRODUCT((Indicators!$B$5:$B$35=F$4)*Indicators!$N$5:$N$35*('Indicator Scores'!$D$5:$D$35>0)),0) -> 3.2857143 | G8: =IFERROR(SUMPRODUCT((Indicators!$B$5:$B$35=G$4)*Indicators!$N$5:$N$35*'Indicator Scores'!$D$5:$D$35)/SUMPRODUCT((Indicators!$B$5:$B$35=G$4)*Indicators!$N$5:$N$35*('Indicator Scores'!$D$5:$D$35>0)),0) -> 3.1428571 | H8: =IFERROR(SUMPRODUCT((Indicators!$B$5:$B$35=H$4)*Indicators!$N$5:$N$35*'Indicator Scores'!$D$5:$D$35)/SUMPRODUCT((Indicators!$B$5:$B$35=H$4)*Indicators!$N$5:$N$35*('Indicator Scores'!$D$5:$D$35>0)),0) -> 3.375 | I8: =IFERROR(SUMPRODUCT((Indicators!$B$5:$B$35=I$4)*Indicators!$N$5:$N$35*'Indicator Scores'!$D$5:$D$35)/SUMPRODUCT((Indicators!$B$5:$B$35=I$4)*Indicators!$N$5:$N$35*('Indicator Scores'!$D$5:$D$35>0)),0) -> 3.3333333 | J8: =IFERROR(SUMPRODUCT((Indicators!$B$5:$B$35=J$4)*Indicators!$N$5:$N$35*'Indicator Scores'!$D$5:$D$35)/SUMPRODUCT((Indicators!$B$5:$B$35=J$4)*Indicators!$N$5:$N$35*('Indicator Scores'!$D$5:$D$35>0)),0) -> 3 | K8: =IFERROR(SUMPRODUCT(F8:J8,INDEX('Factor Weights'!$C$5:$G$11,MATCH(D8,'Factor Weights'!$A$5:$A$11,0),0))/SUMPRODUCT((F8:J8>0)*INDEX('Factor Weights'!$C$5:$G$11,MATCH(D8,'Factor Weights'!$A$5:$A$11,0),0)),0) -> 3.1916667 | L8: =MAX(F8:J8) -> 3.375 | M8: =IF(L8>=Config!$C$13,MAX(K8,Config!$C$14),K8) -> 3.1916667 | N8: =IF(Config!$C$12="Weighted average",K8,IF(Config!$C$12="Weighted with floor",M8,L8)) -> 3.1916667 | O8: =IF(N8<Config!$D$5,"",MATCH(N8,Config!$D$5:$D$9,1)) -> 3 | P8: =IF(O8="","No data",INDEX(Config!$B$5:$B$9,O8)) -> Medium | Q8: 0 | T8: =IF(O8="","",IF(AND(S8="Y",Q8<>0),MAX(1,MIN(5,O8+MAX(-Config!$C$27,MIN(Config!$C$27,Q8)))),O8)) -> 3 | U8: =IF(T8="","No data",INDEX(Config!$B$5:$B$9,T8)) -> Medium | V8: =IF(Q8=0,"None",IF(S8="Y","Applied","Pending HO approval")) -> None | W8: =SUMPRODUCT((Indicators!$N$5:$N$35>0)*('Indicator Data'!$D$5:$D$35<>""))/SUMPRODUCT(--(Indicators!$N$5:$N$35>0)) -> 1
A9: =Entities!$A$5 -> JO-HO | B9: =INDEX(Entities!$B$5:$B$34,MATCH(A9,Entities!$A$5:$A$34,0)) -> Arab Bank plc – Jordan (HO and domestic network) | C9: =INDEX(Entities!$D$5:$D$34,MATCH(A9,Entities!$A$5:$A$34,0)) -> Jordan (home) | D9: FC-05 | E9: =INDEX('Risk Taxonomy'!$B$5:$B$24,MATCH(D9,'Risk Taxonomy'!$A$5:$A$24,0)) -> Bribery and corruption | F9: =IFERROR(SUMPRODUCT((Indicators!$B$5:$B$35=F$4)*Indicators!$O$5:$O$35*'Indicator Scores'!$D$5:$D$35)/SUMPRODUCT((Indicators!$B$5:$B$35=F$4)*Indicators!$O$5:$O$35*('Indicator Scores'!$D$5:$D$35>0)),0) -> 3.4444444 | G9: =IFERROR(SUMPRODUCT((Indicators!$B$5:$B$35=G$4)*Indicators!$O$5:$O$35*'Indicator Scores'!$D$5:$D$35)/SUMPRODUCT((Indicators!$B$5:$B$35=G$4)*Indicators!$O$5:$O$35*('Indicator Scores'!$D$5:$D$35>0)),0) -> 3 | H9: =IFERROR(SUMPRODUCT((Indicators!$B$5:$B$35=H$4)*Indicators!$O$5:$O$35*'Indicator Scores'!$D$5:$D$35)/SUMPRODUCT((Indicators!$B$5:$B$35=H$4)*Indicators!$O$5:$O$35*('Indicator Scores'!$D$5:$D$35>0)),0) -> 2 | I9: =IFERROR(SUMPRODUCT((Indicators!$B$5:$B$35=I$4)*Indicators!$O$5:$O$35*'Indicator Scores'!$D$5:$D$35)/SUMPRODUCT((Indicators!$B$5:$B$35=I$4)*Indicators!$O$5:$O$35*('Indicator Scores'!$D$5:$D$35>0)),0) -> 4 | J9: =IFERROR(SUMPRODUCT((Indicators!$B$5:$B$35=J$4)*Indicators!$O$5:$O$35*'Indicator Scores'!$D$5:$D$35)/SUMPRODUCT((Indicators!$B$5:$B$35=J$4)*Indicators!$O$5:$O$35*('Indicator Scores'!$D$5:$D$35>0)),0) -> 3 | K9: =IFERROR(SUMPRODUCT(F9:J9,INDEX('Factor Weights'!$C$5:$G$11,MATCH(D9,'Factor Weights'!$A$5:$A$11,0),0))/SUMPRODUCT((F9:J9>0)*INDEX('Factor Weights'!$C$5:$G$11,MATCH(D9,'Factor Weights'!$A$5:$A$11,0),0)),0) -> 3.1833333 | L9: =MAX(F9:J9) -> 4 | M9: =IF(L9>=Config!$C$13,MAX(K9,Config!$C$14),K9) -> 3.1833333 | N9: =IF(Config!$C$12="Weighted average",K9,IF(Config!$C$12="Weighted with floor",M9,L9)) -> 3.1833333 | O9: =IF(N9<Config!$D$5,"",MATCH(N9,Config!$D$5:$D$9,1)) -> 3 | P9: =IF(O9="","No data",INDEX(Config!$B$5:$B$9,O9)) -> Medium | Q9: 0 | T9: =IF(O9="","",IF(AND(S9="Y",Q9<>0),MAX(1,MIN(5,O9+MAX(-Config!$C$27,MIN(Config!$C$27,Q9)))),O9)) -> 3 | U9: =IF(T9="","No data",INDEX(Config!$B$5:$B$9,T9)) -> Medium | V9: =IF(Q9=0,"None",IF(S9="Y","Applied","Pending HO approval")) -> None | W9: =SUMPRODUCT((Indicators!$O$5:$O$35>0)*('Indicator Data'!$D$5:$D$35<>""))/SUMPRODUCT(--(Indicators!$O$5:$O$35>0)) -> 1
A10: =Entities!$A$5 -> JO-HO | B10: =INDEX(Entities!$B$5:$B$34,MATCH(A10,Entities!$A$5:$A$34,0)) -> Arab Bank plc – Jordan (HO and domestic network) | C10: =INDEX(Entities!$D$5:$D$34,MATCH(A10,Entities!$A$5:$A$34,0)) -> Jordan (home) | D10: FC-06 | E10: =INDEX('Risk Taxonomy'!$B$5:$B$24,MATCH(D10,'Risk Taxonomy'!$A$5:$A$24,0)) -> Fraud | F10: =IFERROR(SUMPRODUCT((Indicators!$B$5:$B$35=F$4)*Indicators!$P$5:$P$35*'Indicator Scores'!$D$5:$D$35)/SUMPRODUCT((Indicators!$B$5:$B$35=F$4)*Indicators!$P$5:$P$35*('Indicator Scores'!$D$5:$D$35>0)),0) -> 3 | G10: =IFERROR(SUMPRODUCT((Indicators!$B$5:$B$35=G$4)*Indicators!$P$5:$P$35*'Indicator Scores'!$D$5:$D$35)/SUMPRODUCT((Indicators!$B$5:$B$35=G$4)*Indicators!$P$5:$P$35*('Indicator Scores'!$D$5:$D$35>0)),0) -> 2.75 | H10: =IFERROR(SUMPRODUCT((Indicators!$B$5:$B$35=H$4)*Indicators!$P$5:$P$35*'Indicator Scores'!$D$5:$D$35)/SUMPRODUCT((Indicators!$B$5:$B$35=H$4)*Indicators!$P$5:$P$35*('Indicator Scores'!$D$5:$D$35>0)),0) -> 3 | I10: =IFERROR(SUMPRODUCT((Indicators!$B$5:$B$35=I$4)*Indicators!$P$5:$P$35*'Indicator Scores'!$D$5:$D$35)/SUMPRODUCT((Indicators!$B$5:$B$35=I$4)*Indicators!$P$5:$P$35*('Indicator Scores'!$D$5:$D$35>0)),0) -> 2.5555556 | J10: =IFERROR(SUMPRODUCT((Indicators!$B$5:$B$35=J$4)*Indicators!$P$5:$P$35*'Indicator Scores'!$D$5:$D$35)/SUMPRODUCT((Indicators!$B$5:$B$35=J$4)*Indicators!$P$5:$P$35*('Indicator Scores'!$D$5:$D$35>0)),0) -> 2.6 | K10: =IFERROR(SUMPRODUCT(F10:J10,INDEX('Factor Weights'!$C$5:$G$11,MATCH(D10,'Factor Weights'!$A$5:$A$11,0),0))/SUMPRODUCT((F10:J10>0)*INDEX('Factor Weights'!$C$5:$G$11,MATCH(D10,'Factor Weights'!$A$5:$A$11,0),0)),0) -> 2.7616667 | L10: =MAX(F10:J10) -> 3 | M10: =IF(L10>=Config!$C$13,MAX(K10,Config!$C$14),K10) -> 2.7616667 | N10: =IF(Config!$C$12="Weighted average",K10,IF(Config!$C$12="Weighted with floor",M10,L10)) -> 2.7616667 | O10: =IF(N10<Config!$D$5,"",MATCH(N10,Config!$D$5:$D$9,1)) -> 3 | P10: =IF(O10="","No data",INDEX(Config!$B$5:$B$9,O10)) -> Medium | Q10: 0 | T10: =IF(O10="","",IF(AND(S10="Y",Q10<>0),MAX(1,MIN(5,O10+MAX(-Config!$C$27,MIN(Config!$C$27,Q10)))),O10)) -> 3 | U10: =IF(T10="","No data",INDEX(Config!$B$5:$B$9,T10)) -> Medium | V10: =IF(Q10=0,"None",IF(S10="Y","Applied","Pending HO approval")) -> None | W10: =SUMPRODUCT((Indicators!$P$5:$P$35>0)*('Indicator Data'!$D$5:$D$35<>""))/SUMPRODUCT(--(Indicators!$P$5:$P$35>0)) -> 1
A11: =Entities!$A$5 -> JO-HO | B11: =INDEX(Entities!$B$5:$B$34,MATCH(A11,Entities!$A$5:$A$34,0)) -> Arab Bank plc – Jordan (HO and domestic network) | C11: =INDEX(Entities!$D$5:$D$34,MATCH(A11,Entities!$A$5:$A$34,0)) -> Jordan (home) | D11: FC-07 | E11: =INDEX('Risk Taxonomy'!$B$5:$B$24,MATCH(D11,'Risk Taxonomy'!$A$5:$A$24,0)) -> Tax evasion and tax transparency | F11: =IFERROR(SUMPRODUCT((Indicators!$B$5:$B$35=F$4)*Indicators!$Q$5:$Q$35*'Indicator Scores'!$D$5:$D$35)/SUMPRODUCT((Indicators!$B$5:$B$35=F$4)*Indicators!$Q$5:$Q$35*('Indicator Scores'!$D$5:$D$35>0)),0) -> 3.1111111 | G11: =IFERROR(SUMPRODUCT((Indicators!$B$5:$B$35=G$4)*Indicators!$Q$5:$Q$35*'Indicator Scores'!$D$5:$D$35)/SUMPRODUCT((Indicators!$B$5:$B$35=G$4)*Indicators!$Q$5:$Q$35*('Indicator Scores'!$D$5:$D$35>0)),0) -> 3 | H11: =IFERROR(SUMPRODUCT((Indicators!$B$5:$B$35=H$4)*Indicators!$Q$5:$Q$35*'Indicator Scores'!$D$5:$D$35)/SUMPRODUCT((Indicators!$B$5:$B$35=H$4)*Indicators!$Q$5:$Q$35*('Indicator Scores'!$D$5:$D$35>0)),0) -> 2.5 | I11: =IFERROR(SUMPRODUCT((Indicators!$B$5:$B$35=I$4)*Indicators!$Q$5:$Q$35*'Indicator Scores'!$D$5:$D$35)/SUMPRODUCT((Indicators!$B$5:$B$35=I$4)*Indicators!$Q$5:$Q$35*('Indicator Scores'!$D$5:$D$35>0)),0) -> 3 | J11: =IFERROR(SUMPRODUCT((Indicators!$B$5:$B$35=J$4)*Indicators!$Q$5:$Q$35*'Indicator Scores'!$D$5:$D$35)/SUMPRODUCT((Indicators!$B$5:$B$35=J$4)*Indicators!$Q$5:$Q$35*('Indicator Scores'!$D$5:$D$35>0)),0) -> 2.6 | K11: =IFERROR(SUMPRODUCT(F11:J11,INDEX('Factor Weights'!$C$5:$G$11,MATCH(D11,'Factor Weights'!$A$5:$A$11,0),0))/SUMPRODUCT((F11:J11>0)*INDEX('Factor Weights'!$C$5:$G$11,MATCH(D11,'Factor Weights'!$A$5:$A$11,0),0)),0) -> 2.8988889 | L11: =MAX(F11:J11) -> 3.1111111 | M11: =IF(L11>=Config!$C$13,MAX(K11,Config!$C$14),K11) -> 2.8988889 | N11: =IF(Config!$C$12="Weighted average",K11,IF(Config!$C$12="Weighted with floor",M11,L11)) -> 2.8988889 | O11: =IF(N11<Config!$D$5,"",MATCH(N11,Config!$D$5:$D$9,1)) -> 3 | P11: =IF(O11="","No data",INDEX(Config!$B$5:$B$9,O11)) -> Medium | Q11: 0 | T11: =IF(O11="","",IF(AND(S11="Y",Q11<>0),MAX(1,MIN(5,O11+MAX(-Config!$C$27,MIN(Config!$C$27,Q11)))),O11)) -> 3 | U11: =IF(T11="","No data",INDEX(Config!$B$5:$B$9,T11)) -> Medium | V11: =IF(Q11=0,"None",IF(S11="Y","Applied","Pending HO approval")) -> None | W11: =SUMPRODUCT((Indicators!$Q$5:$Q$35>0)*('Indicator Data'!$D$5:$D$35<>""))/SUMPRODUCT(--(Indicators!$Q$5:$Q$35>0)) -> 1
A12: =Entities!$A$6 -> JO-IIAB | B12: =INDEX(Entities!$B$5:$B$34,MATCH(A12,Entities!$A$5:$A$34,0)) -> Islamic International Arab Bank | C12: =INDEX(Entities!$D$5:$D$34,MATCH(A12,Entities!$A$5:$A$34,0)) -> Jordan (home) | D12: FC-01 | E12: =INDEX('Risk Taxonomy'!$B$5:$B$24,MATCH(D12,'Risk Taxonomy'!$A$5:$A$24,0)) -> Money laundering | F12: =IFERROR(SUMPRODUCT((Indicators!$B$5:$B$35=F$4)*Indicators!$K$5:$K$35*'Indicator Scores'!$E$5:$E$35)/SUMPRODUCT((Indicators!$B$5:$B$35=F$4)*Indicators!$K$5:$K$35*('Indicator Scores'!$E$5:$E$35>0)),0) -> 3.25 | G12: =IFERROR(SUMPRODUCT((Indicators!$B$5:$B$35=G$4)*Indicators!$K$5:$K$35*'Indicator Scores'!$E$5:$E$35)/SUMPRODUCT((Indicators!$B$5:$B$35=G$4)*Indicators!$K$5:$K$35*('Indicator Scores'!$E$5:$E$35>0)),0) -> 2.3333333 | H12: =IFERROR(SUMPRODUCT((Indicators!$B$5:$B$35=H$4)*Indicators!$K$5:$K$35*'Indicator Scores'!$E$5:$E$35)/SUMPRODUCT((Indicators!$B$5:$B$35=H$4)*Indicators!$K$5:$K$35*('Indicator Scores'!$E$5:$E$35>0)),0) -> 2.9 | I12: =IFERROR(SUMPRODUCT((Indicators!$B$5:$B$35=I$4)*Indicators!$K$5:$K$35*'Indicator Scores'!$E$5:$E$35)/SUMPRODUCT((Indicators!$B$5:$B$35=I$4)*Indicators!$K$5:$K$35*('Indicator Scores'!$E$5:$E$35>0)),0) -> 2.7142857 | J12: =IFERROR(SUMPRODUCT((Indicators!$B$5:$B$35=J$4)*Indicators!$K$5:$K$35*'Indicator Scores'!$E$5:$E$35)/SUMPRODUCT((Indicators!$B$5:$B$35=J$4)*Indicators!$K$5:$K$35*('Indicator Scores'!$E$5:$E$35>0)),0) -> 3 | K12: =IFERROR(SUMPRODUCT(F12:J12,INDEX('Factor Weights'!$C$5:$G$11,MATCH(D12,'Factor Weights'!$A$5:$A$11,0),0))/SUMPRODUCT((F12:J12>0)*INDEX('Factor Weights'!$C$5:$G$11,MATCH(D12,'Factor Weights'!$A$5:$A$11,0),0)),0) -> 2.8454762 | L12: =MAX(F12:J12) -> 3.25 | M12: =IF(L12>=Config!$C$13,MAX(K12,Config!$C$14),K12) -> 2.8454762 | N12: =IF(Config!$C$12="Weighted average",K12,IF(Config!$C$12="Weighted with floor",M12,L12)) -> 2.8454762 | O12: =IF(N12<Config!$D$5,"",MATCH(N12,Config!$D$5:$D$9,1)) -> 3 | P12: =IF(O12="","No data",INDEX(Config!$B$5:$B$9,O12)) -> Medium | Q12: 0 | T12: =IF(O12="","",IF(AND(S12="Y",Q12<>0),MAX(1,MIN(5,O12+MAX(-Config!$C$27,MIN(Config!$C$27,Q12)))),O12)) -> 3 | U12: =IF(T12="","No data",INDEX(Config!$B$5:$B$9,T12)) -> Medium | V12: =IF(Q12=0,"None",IF(S12="Y","Applied","Pending HO approval")) -> None | W12: =SUMPRODUCT((Indicators!$K$5:$K$35>0)*('Indicator Data'!$E$5:$E$35<>""))/SUMPRODUCT(--(Indicators!$K$5:$K$35>0)) -> 1
A13: =Entities!$A$6 -> JO-IIAB | B13: =INDEX(Entities!$B$5:$B$34,MATCH(A13,Entities!$A$5:$A$34,0)) -> Islamic International Arab Bank | C13: =INDEX(Entities!$D$5:$D$34,MATCH(A13,Entities!$A$5:$A$34,0)) -> Jordan (home) | D13: FC-02 | E13: =INDEX('Risk Taxonomy'!$B$5:$B$24,MATCH(D13,'Risk Taxonomy'!$A$5:$A$24,0)) -> Terrorist financing | F13: =IFERROR(SUMPRODUCT((Indicators!$B$5:$B$35=F$4)*Indicators!$L$5:$L$35*'Indicator Scores'!$E$5:$E$35)/SUMPRODUCT((Indicators!$B$5:$B$35=F$4)*Indicators!$L$5:$L$35*('Indicator Scores'!$E$5:$E$35>0)),0) -> 3.4 | G13: =IFERROR(SUMPRODUCT((Indicators!$B$5:$B$35=G$4)*Indicators!$L$5:$L$35*'Indicator Scores'!$E$5:$E$35)/SUMPRODUCT((Indicators!$B$5:$B$35=G$4)*Indicators!$L$5:$L$35*('Indicator Scores'!$E$5:$E$35>0)),0) -> 2.6666667 | H13: =IFERROR(SUMPRODUCT((Indicators!$B$5:$B$35=H$4)*Indicators!$L$5:$L$35*'Indicator Scores'!$E$5:$E$35)/SUMPRODUCT((Indicators!$B$5:$B$35=H$4)*Indicators!$L$5:$L$35*('Indicator Scores'!$E$5:$E$35>0)),0) -> 3.1666667 | I13: =IFERROR(SUMPRODUCT((Indicators!$B$5:$B$35=I$4)*Indicators!$L$5:$L$35*'Indicator Scores'!$E$5:$E$35)/SUMPRODUCT((Indicators!$B$5:$B$35=I$4)*Indicators!$L$5:$L$35*('Indicator Scores'!$E$5:$E$35>0)),0) -> 2.6666667 | J13: =IFERROR(SUMPRODUCT((Indicators!$B$5:$B$35=J$4)*Indicators!$L$5:$L$35*'Indicator Scores'!$E$5:$E$35)/SUMPRODUCT((Indicators!$B$5:$B$35=J$4)*Indicators!$L$5:$L$35*('Indicator Scores'!$E$5:$E$35>0)),0) -> 3.2857143 | K13: =IFERROR(SUMPRODUCT(F13:J13,INDEX('Factor Weights'!$C$5:$G$11,MATCH(D13,'Factor Weights'!$A$5:$A$11,0),0))/SUMPRODUCT((F13:J13>0)*INDEX('Factor Weights'!$C$5:$G$11,MATCH(D13,'Factor Weights'!$A$5:$A$11,0),0)),0) -> 3.0488095 | L13: =MAX(F13:J13) -> 3.4 | M13: =IF(L13>=Config!$C$13,MAX(K13,Config!$C$14),K13) -> 3.0488095 | N13: =IF(Config!$C$12="Weighted average",K13,IF(Config!$C$12="Weighted with floor",M13,L13)) -> 3.0488095 | O13: =IF(N13<Config!$D$5,"",MATCH(N13,Config!$D$5:$D$9,1)) -> 3 | P13: =IF(O13="","No data",INDEX(Config!$B$5:$B$9,O13)) -> Medium | Q13: 0 | T13: =IF(O13="","",IF(AND(S13="Y",Q13<>0),MAX(1,MIN(5,O13+MAX(-Config!$C$27,MIN(Config!$C$27,Q13)))),O13)) -> 3 | U13: =IF(T13="","No data",INDEX(Config!$B$5:$B$9,T13)) -> Medium | V13: =IF(Q13=0,"None",IF(S13="Y","Applied","Pending HO approval")) -> None | W13: =SUMPRODUCT((Indicators!$L$5:$L$35>0)*('Indicator Data'!$E$5:$E$35<>""))/SUMPRODUCT(--(Indicators!$L$5:$L$35>0)) -> 1
A14: =Entities!$A$6 -> JO-IIAB | B14: =INDEX(Entities!$B$5:$B$34,MATCH(A14,Entities!$A$5:$A$34,0)) -> Islamic International Arab Bank | C14: =INDEX(Entities!$D$5:$D$34,MATCH(A14,Entities!$A$5:$A$34,0)) -> Jordan (home) | D14: FC-03 | E14: =INDEX('Risk Taxonomy'!$B$5:$B$24,MATCH(D14,'Risk Taxonomy'!$A$5:$A$24,0)) -> Proliferation financing | F14: =IFERROR(SUMPRODUCT((Indicators!$B$5:$B$35=F$4)*Indicators!$M$5:$M$35*'Indicator Scores'!$E$5:$E$35)/SUMPRODUCT((Indicators!$B$5:$B$35=F$4)*Indicators!$M$5:$M$35*('Indicator Scores'!$E$5:$E$35>0)),0) -> 4 | G14: =IFERROR(SUMPRODUCT((Indicators!$B$5:$B$35=G$4)*Indicators!$M$5:$M$35*'Indicator Scores'!$E$5:$E$35)/SUMPRODUCT((Indicators!$B$5:$B$35=G$4)*Indicators!$M$5:$M$35*('Indicator Scores'!$E$5:$E$35>0)),0) -> 2.25 | H14: =IFERROR(SUMPRODUCT((Indicators!$B$5:$B$35=H$4)*Indicators!$M$5:$M$35*'Indicator Scores'!$E$5:$E$35)/SUMPRODUCT((Indicators!$B$5:$B$35=H$4)*Indicators!$M$5:$M$35*('Indicator Scores'!$E$5:$E$35>0)),0) -> 3 | I14: =IFERROR(SUMPRODUCT((Indicators!$B$5:$B$35=I$4)*Indicators!$M$5:$M$35*'Indicator Scores'!$E$5:$E$35)/SUMPRODUCT((Indicators!$B$5:$B$35=I$4)*Indicators!$M$5:$M$35*('Indicator Scores'!$E$5:$E$35>0)),0) -> 2 | J14: =IFERROR(SUMPRODUCT((Indicators!$B$5:$B$35=J$4)*Indicators!$M$5:$M$35*'Indicator Scores'!$E$5:$E$35)/SUMPRODUCT((Indicators!$B$5:$B$35=J$4)*Indicators!$M$5:$M$35*('Indicator Scores'!$E$5:$E$35>0)),0) -> 3 | K14: =IFERROR(SUMPRODUCT(F14:J14,INDEX('Factor Weights'!$C$5:$G$11,MATCH(D14,'Factor Weights'!$A$5:$A$11,0),0))/SUMPRODUCT((F14:J14>0)*INDEX('Factor Weights'!$C$5:$G$11,MATCH(D14,'Factor Weights'!$A$5:$A$11,0),0)),0) -> 2.875 | L14: =MAX(F14:J14) -> 4 | M14: =IF(L14>=Config!$C$13,MAX(K14,Config!$C$14),K14) -> 2.875 | N14: =IF(Config!$C$12="Weighted average",K14,IF(Config!$C$12="Weighted with floor",M14,L14)) -> 2.875 | O14: =IF(N14<Config!$D$5,"",MATCH(N14,Config!$D$5:$D$9,1)) -> 3 | P14: =IF(O14="","No data",INDEX(Config!$B$5:$B$9,O14)) -> Medium | Q14: 0 | T14: =IF(O14="","",IF(AND(S14="Y",Q14<>0),MAX(1,MIN(5,O14+MAX(-Config!$C$27,MIN(Config!$C$27,Q14)))),O14)) -> 3 | U14: =IF(T14="","No data",INDEX(Config!$B$5:$B$9,T14)) -> Medium | V14: =IF(Q14=0,"None",IF(S14="Y","Applied","Pending HO approval")) -> None | W14: =SUMPRODUCT((Indicators!$M$5:$M$35>0)*('Indicator Data'!$E$5:$E$35<>""))/SUMPRODUCT(--(Indicators!$M$5:$M$35>0)) -> 1
A15: =Entities!$A$6 -> JO-IIAB | B15: =INDEX(Entities!$B$5:$B$34,MATCH(A15,Entities!$A$5:$A$34,0)) -> Islamic International Arab Bank | C15: =INDEX(Entities!$D$5:$D$34,MATCH(A15,Entities!$A$5:$A$34,0)) -> Jordan (home) | D15: FC-04 | E15: =INDEX('Risk Taxonomy'!$B$5:$B$24,MATCH(D15,'Risk Taxonomy'!$A$5:$A$24,0)) -> Sanctions | F15: =IFERROR(SUMPRODUCT((Indicators!$B$5:$B$35=F$4)*Indicators!$N$5:$N$35*'Indicator Scores'!$E$5:$E$35)/SUMPRODUCT((Indicators!$B$5:$B$35=F$4)*Indicators!$N$5:$N$35*('Indicator Scores'!$E$5:$E$35>0)),0) -> 3.7142857 | G15: =IFERROR(SUMPRODUCT((Indicators!$B$5:$B$35=G$4)*Indicators!$N$5:$N$35*'Indicator Scores'!$E$5:$E$35)/SUMPRODUCT((Indicators!$B$5:$B$35=G$4)*Indicators!$N$5:$N$35*('Indicator Scores'!$E$5:$E$35>0)),0) -> 2.2857143 | H15: =IFERROR(SUMPRODUCT((Indicators!$B$5:$B$35=H$4)*Indicators!$N$5:$N$35*'Indicator Scores'!$E$5:$E$35)/SUMPRODUCT((Indicators!$B$5:$B$35=H$4)*Indicators!$N$5:$N$35*('Indicator Scores'!$E$5:$E$35>0)),0) -> 2.875 | I15: =IFERROR(SUMPRODUCT((Indicators!$B$5:$B$35=I$4)*Indicators!$N$5:$N$35*'Indicator Scores'!$E$5:$E$35)/SUMPRODUCT((Indicators!$B$5:$B$35=I$4)*Indicators!$N$5:$N$35*('Indicator Scores'!$E$5:$E$35>0)),0) -> 2 | J15: =IFERROR(SUMPRODUCT((Indicators!$B$5:$B$35=J$4)*Indicators!$N$5:$N$35*'Indicator Scores'!$E$5:$E$35)/SUMPRODUCT((Indicators!$B$5:$B$35=J$4)*Indicators!$N$5:$N$35*('Indicator Scores'!$E$5:$E$35>0)),0) -> 3.2 | K15: =IFERROR(SUMPRODUCT(F15:J15,INDEX('Factor Weights'!$C$5:$G$11,MATCH(D15,'Factor Weights'!$A$5:$A$11,0),0))/SUMPRODUCT((F15:J15>0)*INDEX('Factor Weights'!$C$5:$G$11,MATCH(D15,'Factor Weights'!$A$5:$A$11,0),0)),0) -> 2.7864286 | L15: =MAX(F15:J15) -> 3.7142857 | M15: =IF(L15>=Config!$C$13,MAX(K15,Config!$C$14),K15) -> 2.7864286 | N15: =IF(Config!$C$12="Weighted average",K15,IF(Config!$C$12="Weighted with floor",M15,L15)) -> 2.7864286 | O15: =IF(N15<Config!$D$5,"",MATCH(N15,Config!$D$5:$D$9,1)) -> 3 | P15: =IF(O15="","No data",INDEX(Config!$B$5:$B$9,O15)) -> Medium | Q15: 0 | T15: =IF(O15="","",IF(AND(S15="Y",Q15<>0),MAX(1,MIN(5,O15+MAX(-Config!$C$27,MIN(Config!$C$27,Q15)))),O15)) -> 3 | U15: =IF(T15="","No data",INDEX(Config!$B$5:$B$9,T15)) -> Medium | V15: =IF(Q15=0,"None",IF(S15="Y","Applied","Pending HO approval")) -> None | W15: =SUMPRODUCT((Indicators!$N$5:$N$35>0)*('Indicator Data'!$E$5:$E$35<>""))/SUMPRODUCT(--(Indicators!$N$5:$N$35>0)) -> 1
A16: =Entities!$A$6 -> JO-IIAB | B16: =INDEX(Entities!$B$5:$B$34,MATCH(A16,Entities!$A$5:$A$34,0)) -> Islamic International Arab Bank | C16: =INDEX(Entities!$D$5:$D$34,MATCH(A16,Entities!$A$5:$A$34,0)) -> Jordan (home) | D16: FC-05 | E16: =INDEX('Risk Taxonomy'!$B$5:$B$24,MATCH(D16,'Risk Taxonomy'!$A$5:$A$24,0)) -> Bribery and corruption | F16: =IFERROR(SUMPRODUCT((Indicators!$B$5:$B$35=F$4)*Indicators!$O$5:$O$35*'Indicator Scores'!$E$5:$E$35)/SUMPRODUCT((Indicators!$B$5:$B$35=F$4)*Indicators!$O$5:$O$35*('Indicator Scores'!$E$5:$E$35>0)),0) -> 3.6666667 | G16: =IFERROR(SUMPRODUCT((Indicators!$B$5:$B$35=G$4)*Indicators!$O$5:$O$35*'Indicator Scores'!$E$5:$E$35)/SUMPRODUCT((Indicators!$B$5:$B$35=G$4)*Indicators!$O$5:$O$35*('Indicator Scores'!$E$5:$E$35>0)),0) -> 2.6 | H16: =IFERROR(SUMPRODUCT((Indicators!$B$5:$B$35=H$4)*Indicators!$O$5:$O$35*'Indicator Scores'!$E$5:$E$35)/SUMPRODUCT((Indicators!$B$5:$B$35=H$4)*Indicators!$O$5:$O$35*('Indicator Scores'!$E$5:$E$35>0)),0) -> 3 | I16: =IFERROR(SUMPRODUCT((Indicators!$B$5:$B$35=I$4)*Indicators!$O$5:$O$35*'Indicator Scores'!$E$5:$E$35)/SUMPRODUCT((Indicators!$B$5:$B$35=I$4)*Indicators!$O$5:$O$35*('Indicator Scores'!$E$5:$E$35>0)),0) -> 2.6 | J16: =IFERROR(SUMPRODUCT((Indicators!$B$5:$B$35=J$4)*Indicators!$O$5:$O$35*'Indicator Scores'!$E$5:$E$35)/SUMPRODUCT((Indicators!$B$5:$B$35=J$4)*Indicators!$O$5:$O$35*('Indicator Scores'!$E$5:$E$35>0)),0) -> 2 | K16: =IFERROR(SUMPRODUCT(F16:J16,INDEX('Factor Weights'!$C$5:$G$11,MATCH(D16,'Factor Weights'!$A$5:$A$11,0),0))/SUMPRODUCT((F16:J16>0)*INDEX('Factor Weights'!$C$5:$G$11,MATCH(D16,'Factor Weights'!$A$5:$A$11,0),0)),0) -> 2.92 | L16: =MAX(F16:J16) -> 3.6666667 | M16: =IF(L16>=Config!$C$13,MAX(K16,Config!$C$14),K16) -> 2.92 | N16: =IF(Config!$C$12="Weighted average",K16,IF(Config!$C$12="Weighted with floor",M16,L16)) -> 2.92 | O16: =IF(N16<Config!$D$5,"",MATCH(N16,Config!$D$5:$D$9,1)) -> 3 | P16: =IF(O16="","No data",INDEX(Config!$B$5:$B$9,O16)) -> Medium | Q16: 0 | T16: =IF(O16="","",IF(AND(S16="Y",Q16<>0),MAX(1,MIN(5,O16+MAX(-Config!$C$27,MIN(Config!$C$27,Q16)))),O16)) -> 3 | U16: =IF(T16="","No data",INDEX(Config!$B$5:$B$9,T16)) -> Medium | V16: =IF(Q16=0,"None",IF(S16="Y","Applied","Pending HO approval")) -> None | W16: =SUMPRODUCT((Indicators!$O$5:$O$35>0)*('Indicator Data'!$E$5:$E$35<>""))/SUMPRODUCT(--(Indicators!$O$5:$O$35>0)) -> 1
A17: =Entities!$A$6 -> JO-IIAB | B17: =INDEX(Entities!$B$5:$B$34,MATCH(A17,Entities!$A$5:$A$34,0)) -> Islamic International Arab Bank | C17: =INDEX(Entities!$D$5:$D$34,MATCH(A17,Entities!$A$5:$A$34,0)) -> Jordan (home) | D17: FC-06 | E17: =INDEX('Risk Taxonomy'!$B$5:$B$24,MATCH(D17,'Risk Taxonomy'!$A$5:$A$24,0)) -> Fraud | F17: =IFERROR(SUMPRODUCT((Indicators!$B$5:$B$35=F$4)*Indicators!$P$5:$P$35*'Indicator Scores'!$E$5:$E$35)/SUMPRODUCT((Indicators!$B$5:$B$35=F$4)*Indicators!$P$5:$P$35*('Indicator Scores'!$E$5:$E$35>0)),0) -> 2.3333333 | G17: =IFERROR(SUMPRODUCT((Indicators!$B$5:$B$35=G$4)*Indicators!$P$5:$P$35*'Indicator Scores'!$E$5:$E$35)/SUMPRODUCT((Indicators!$B$5:$B$35=G$4)*Indicators!$P$5:$P$35*('Indicator Scores'!$E$5:$E$35>0)),0) -> 2.75 | H17: =IFERROR(SUMPRODUCT((Indicators!$B$5:$B$35=H$4)*Indicators!$P$5:$P$35*'Indicator Scores'!$E$5:$E$35)/SUMPRODUCT((Indicators!$B$5:$B$35=H$4)*Indicators!$P$5:$P$35*('Indicator Scores'!$E$5:$E$35>0)),0) -> 3.2 | I17: =IFERROR(SUMPRODUCT((Indicators!$B$5:$B$35=I$4)*Indicators!$P$5:$P$35*'Indicator Scores'!$E$5:$E$35)/SUMPRODUCT((Indicators!$B$5:$B$35=I$4)*Indicators!$P$5:$P$35*('Indicator Scores'!$E$5:$E$35>0)),0) -> 3 | J17: =IFERROR(SUMPRODUCT((Indicators!$B$5:$B$35=J$4)*Indicators!$P$5:$P$35*'Indicator Scores'!$E$5:$E$35)/SUMPRODUCT((Indicators!$B$5:$B$35=J$4)*Indicators!$P$5:$P$35*('Indicator Scores'!$E$5:$E$35>0)),0) -> 2.4 | K17: =IFERROR(SUMPRODUCT(F17:J17,INDEX('Factor Weights'!$C$5:$G$11,MATCH(D17,'Factor Weights'!$A$5:$A$11,0),0))/SUMPRODUCT((F17:J17>0)*INDEX('Factor Weights'!$C$5:$G$11,MATCH(D17,'Factor Weights'!$A$5:$A$11,0),0)),0) -> 2.7616667 | L17: =MAX(F17:J17) -> 3.2 | M17: =IF(L17>=Config!$C$13,MAX(K17,Config!$C$14),K17) -> 2.7616667 | N17: =IF(Config!$C$12="Weighted average",K17,IF(Config!$C$12="Weighted with floor",M17,L17)) -> 2.7616667 | O17: =IF(N17<Config!$D$5,"",MATCH(N17,Config!$D$5:$D$9,1)) -> 3 | P17: =IF(O17="","No data",INDEX(Config!$B$5:$B$9,O17)) -> Medium | Q17: 0 | T17: =IF(O17="","",IF(AND(S17="Y",Q17<>0),MAX(1,MIN(5,O17+MAX(-Config!$C$27,MIN(Config!$C$27,Q17)))),O17)) -> 3 | U17: =IF(T17="","No data",INDEX(Config!$B$5:$B$9,T17)) -> Medium | V17: =IF(Q17=0,"None",IF(S17="Y","Applied","Pending HO approval")) -> None | W17: =SUMPRODUCT((Indicators!$P$5:$P$35>0)*('Indicator Data'!$E$5:$E$35<>""))/SUMPRODUCT(--(Indicators!$P$5:$P$35>0)) -> 1
A18: =Entities!$A$6 -> JO-IIAB | B18: =INDEX(Entities!$B$5:$B$34,MATCH(A18,Entities!$A$5:$A$34,0)) -> Islamic International Arab Bank | C18: =INDEX(Entities!$D$5:$D$34,MATCH(A18,Entities!$A$5:$A$34,0)) -> Jordan (home) | D18: FC-07 | E18: =INDEX('Risk Taxonomy'!$B$5:$B$24,MATCH(D18,'Risk Taxonomy'!$A$5:$A$24,0)) -> Tax evasion and tax transparency | F18: =IFERROR(SUMPRODUCT((Indicators!$B$5:$B$35=F$4)*Indicators!$Q$5:$Q$35*'Indicator Scores'!$E$5:$E$35)/SUMPRODUCT((Indicators!$B$5:$B$35=F$4)*Indicators!$Q$5:$Q$35*('Indicator Scores'!$E$5:$E$35>0)),0) -> 3.5555556 | G18: =IFERROR(SUMPRODUCT((Indicators!$B$5:$B$35=G$4)*Indicators!$Q$5:$Q$35*'Indicator Scores'!$E$5:$E$35)/SUMPRODUCT((Indicators!$B$5:$B$35=G$4)*Indicators!$Q$5:$Q$35*('Indicator Scores'!$E$5:$E$35>0)),0) -> 2.1666667 | H18: =IFERROR(SUMPRODUCT((Indicators!$B$5:$B$35=H$4)*Indicators!$Q$5:$Q$35*'Indicator Scores'!$E$5:$E$35)/SUMPRODUCT((Indicators!$B$5:$B$35=H$4)*Indicators!$Q$5:$Q$35*('Indicator Scores'!$E$5:$E$35>0)),0) -> 2.5 | I18: =IFERROR(SUMPRODUCT((Indicators!$B$5:$B$35=I$4)*Indicators!$Q$5:$Q$35*'Indicator Scores'!$E$5:$E$35)/SUMPRODUCT((Indicators!$B$5:$B$35=I$4)*Indicators!$Q$5:$Q$35*('Indicator Scores'!$E$5:$E$35>0)),0) -> 2.5 | J18: =IFERROR(SUMPRODUCT((Indicators!$B$5:$B$35=J$4)*Indicators!$Q$5:$Q$35*'Indicator Scores'!$E$5:$E$35)/SUMPRODUCT((Indicators!$B$5:$B$35=J$4)*Indicators!$Q$5:$Q$35*('Indicator Scores'!$E$5:$E$35>0)),0) -> 3 | K18: =IFERROR(SUMPRODUCT(F18:J18,INDEX('Factor Weights'!$C$5:$G$11,MATCH(D18,'Factor Weights'!$A$5:$A$11,0),0))/SUMPRODUCT((F18:J18>0)*INDEX('Factor Weights'!$C$5:$G$11,MATCH(D18,'Factor Weights'!$A$5:$A$11,0),0)),0) -> 2.8361111 | L18: =MAX(F18:J18) -> 3.5555556 | M18: =IF(L18>=Config!$C$13,MAX(K18,Config!$C$14),K18) -> 2.8361111 | N18: =IF(Config!$C$12="Weighted average",K18,IF(Config!$C$12="Weighted with floor",M18,L18)) -> 2.8361111 | O18: =IF(N18<Config!$D$5,"",MATCH(N18,Config!$D$5:$D$9,1)) -> 3 | P18: =IF(O18="","No data",INDEX(Config!$B$5:$B$9,O18)) -> Medium | Q18: 0 | T18: =IF(O18="","",IF(AND(S18="Y",Q18<>0),MAX(1,MIN(5,O18+MAX(-Config!$C$27,MIN(Config!$C$27,Q18)))),O18)) -> 3 | U18: =IF(T18="","No data",INDEX(Config!$B$5:$B$9,T18)) -> Medium | V18: =IF(Q18=0,"None",IF(S18="Y","Applied","Pending HO approval")) -> None | W18: =SUMPRODUCT((Indicators!$Q$5:$Q$35>0)*('Indicator Data'!$E$5:$E$35<>""))/SUMPRODUCT(--(Indicators!$Q$5:$Q$35>0)) -> 1
A19: =Entities!$A$7 -> JO-INV | B19: =INDEX(Entities!$B$5:$B$34,MATCH(A19,Entities!$A$5:$A$34,0)) -> Al-Arabi Investment Group (AB Invest) | C19: =INDEX(Entities!$D$5:$D$34,MATCH(A19,Entities!$A$5:$A$34,0)) -> Jordan (home) | D19: FC-01 | E19: =INDEX('Risk Taxonomy'!$B$5:$B$24,MATCH(D19,'Risk Taxonomy'!$A$5:$A$24,0)) -> Money laundering | F19: =IFERROR(SUMPRODUCT((Indicators!$B$5:$B$35=F$4)*Indicators!$K$5:$K$35*'Indicator Scores'!$F$5:$F$35)/SUMPRODUCT((Indicators!$B$5:$B$35=F$4)*Indicators!$K$5:$K$35*('Indicator Scores'!$F$5:$F$35>0)),0) -> 2.1666667 | G19: =IFERROR(SUMPRODUCT((Indicators!$B$5:$B$35=G$4)*Indicators!$K$5:$K$35*'Indicator Scores'!$F$5:$F$35)/SUMPRODUCT((Indicators!$B$5:$B$35=G$4)*Indicators!$K$5:$K$35*('Indicator Scores'!$F$5:$F$35>0)),0) -> 2.3333333 | H19: =IFERROR(SUMPRODUCT((Indicators!$B$5:$B$35=H$4)*Indicators!$K$5:$K$35*'Indicator Scores'!$F$5:$F$35)/SUMPRODUCT((Indicators!$B$5:$B$35=H$4)*Indicators!$K$5:$K$35*('Indicator Scores'!$F$5:$F$35>0)),0) -> 1.6 | I19: =IFERROR(SUMPRODUCT((Indicators!$B$5:$B$35=I$4)*Indicators!$K$5:$K$35*'Indicator Scores'!$F$5:$F$35)/SUMPRODUCT((Indicators!$B$5:$B$35=I$4)*Indicators!$K$5:$K$35*('Indicator Scores'!$F$5:$F$35>0)),0) -> 2.1428571 | J19: =IFERROR(SUMPRODUCT((Indicators!$B$5:$B$35=J$4)*Indicators!$K$5:$K$35*'Indicator Scores'!$F$5:$F$35)/SUMPRODUCT((Indicators!$B$5:$B$35=J$4)*Indicators!$K$5:$K$35*('Indicator Scores'!$F$5:$F$35>0)),0) -> 2.4 | K19: =IFERROR(SUMPRODUCT(F19:J19,INDEX('Factor Weights'!$C$5:$G$11,MATCH(D19,'Factor Weights'!$A$5:$A$11,0),0))/SUMPRODUCT((F19:J19>0)*INDEX('Factor Weights'!$C$5:$G$11,MATCH(D19,'Factor Weights'!$A$5:$A$11,0),0)),0) -> 2.1147619 | L19: =MAX(F19:J19) -> 2.4 | M19: =IF(L19>=Config!$C$13,MAX(K19,Config!$C$14),K19) -> 2.1147619 | N19: =IF(Config!$C$12="Weighted average",K19,IF(Config!$C$12="Weighted with floor",M19,L19)) -> 2.1147619 | O19: =IF(N19<Config!$D$5,"",MATCH(N19,Config!$D$5:$D$9,1)) -> 2 | P19: =IF(O19="","No data",INDEX(Config!$B$5:$B$9,O19)) -> Medium-Low | Q19: 0 | T19: =IF(O19="","",IF(AND(S19="Y",Q19<>0),MAX(1,MIN(5,O19+MAX(-Config!$C$27,MIN(Config!$C$27,Q19)))),O19)) -> 2 | U19: =IF(T19="","No data",INDEX(Config!$B$5:$B$9,T19)) -> Medium-Low | V19: =IF(Q19=0,"None",IF(S19="Y","Applied","Pending HO approval")) -> None | W19: =SUMPRODUCT((Indicators!$K$5:$K$35>0)*('Indicator Data'!$F$5:$F$35<>""))/SUMPRODUCT(--(Indicators!$K$5:$K$35>0)) -> 1
A20: =Entities!$A$7 -> JO-INV | B20: =INDEX(Entities!$B$5:$B$34,MATCH(A20,Entities!$A$5:$A$34,0)) -> Al-Arabi Investment Group (AB Invest) | C20: =INDEX(Entities!$D$5:$D$34,MATCH(A20,Entities!$A$5:$A$34,0)) -> Jordan (home) | D20: FC-02 | E20: =INDEX('Risk Taxonomy'!$B$5:$B$24,MATCH(D20,'Risk Taxonomy'!$A$5:$A$24,0)) -> Terrorist financing | F20: =IFERROR(SUMPRODUCT((Indicators!$B$5:$B$35=F$4)*Indicators!$L$5:$L$35*'Indicator Scores'!$F$5:$F$35)/SUMPRODUCT((Indicators!$B$5:$B$35=F$4)*Indicators!$L$5:$L$35*('Indicator Scores'!$F$5:$F$35>0)),0) -> 1.9 | G20: =IFERROR(SUMPRODUCT((Indicators!$B$5:$B$35=G$4)*Indicators!$L$5:$L$35*'Indicator Scores'!$F$5:$F$35)/SUMPRODUCT((Indicators!$B$5:$B$35=G$4)*Indicators!$L$5:$L$35*('Indicator Scores'!$F$5:$F$35>0)),0) -> 2.2222222 | H20: =IFERROR(SUMPRODUCT((Indicators!$B$5:$B$35=H$4)*Indicators!$L$5:$L$35*'Indicator Scores'!$F$5:$F$35)/SUMPRODUCT((Indicators!$B$5:$B$35=H$4)*Indicators!$L$5:$L$35*('Indicator Scores'!$F$5:$F$35>0)),0) -> 1.3333333 | I20: =IFERROR(SUMPRODUCT((Indicators!$B$5:$B$35=I$4)*Indicators!$L$5:$L$35*'Indicator Scores'!$F$5:$F$35)/SUMPRODUCT((Indicators!$B$5:$B$35=I$4)*Indicators!$L$5:$L$35*('Indicator Scores'!$F$5:$F$35>0)),0) -> 1.8333333 | J20: =IFERROR(SUMPRODUCT((Indicators!$B$5:$B$35=J$4)*Indicators!$L$5:$L$35*'Indicator Scores'!$F$5:$F$35)/SUMPRODUCT((Indicators!$B$5:$B$35=J$4)*Indicators!$L$5:$L$35*('Indicator Scores'!$F$5:$F$35>0)),0) -> 2.2857143 | K20: =IFERROR(SUMPRODUCT(F20:J20,INDEX('Factor Weights'!$C$5:$G$11,MATCH(D20,'Factor Weights'!$A$5:$A$11,0),0))/SUMPRODUCT((F20:J20>0)*INDEX('Factor Weights'!$C$5:$G$11,MATCH(D20,'Factor Weights'!$A$5:$A$11,0),0)),0) -> 1.9821429 | L20: =MAX(F20:J20) -> 2.2857143 | M20: =IF(L20>=Config!$C$13,MAX(K20,Config!$C$14),K20) -> 1.9821429 | N20: =IF(Config!$C$12="Weighted average",K20,IF(Config!$C$12="Weighted with floor",M20,L20)) -> 1.9821429 | O20: =IF(N20<Config!$D$5,"",MATCH(N20,Config!$D$5:$D$9,1)) -> 2 | P20: =IF(O20="","No data",INDEX(Config!$B$5:$B$9,O20)) -> Medium-Low | Q20: 0 | T20: =IF(O20="","",IF(AND(S20="Y",Q20<>0),MAX(1,MIN(5,O20+MAX(-Config!$C$27,MIN(Config!$C$27,Q20)))),O20)) -> 2 | U20: =IF(T20="","No data",INDEX(Config!$B$5:$B$9,T20)) -> Medium-Low | V20: =IF(Q20=0,"None",IF(S20="Y","Applied","Pending HO approval")) -> None | W20: =SUMPRODUCT((Indicators!$L$5:$L$35>0)*('Indicator Data'!$F$5:$F$35<>""))/SUMPRODUCT(--(Indicators!$L$5:$L$35>0)) -> 1
A21: =Entities!$A$7 -> JO-INV | B21: =INDEX(Entities!$B$5:$B$34,MATCH(A21,Entities!$A$5:$A$34,0)) -> Al-Arabi Investment Group (AB Invest) | C21: =INDEX(Entities!$D$5:$D$34,MATCH(A21,Entities!$A$5:$A$34,0)) -> Jordan (home) | D21: FC-03 | E21: =INDEX('Risk Taxonomy'!$B$5:$B$24,MATCH(D21,'Risk Taxonomy'!$A$5:$A$24,0)) -> Proliferation financing | F21: =IFERROR(SUMPRODUCT((Indicators!$B$5:$B$35=F$4)*Indicators!$M$5:$M$35*'Indicator Scores'!$F$5:$F$35)/SUMPRODUCT((Indicators!$B$5:$B$35=F$4)*Indicators!$M$5:$M$35*('Indicator Scores'!$F$5:$F$35>0)),0) -> 3 | G21: =IFERROR(SUMPRODUCT((Indicators!$B$5:$B$35=G$4)*Indicators!$M$5:$M$35*'Indicator Scores'!$F$5:$F$35)/SUMPRODUCT((Indicators!$B$5:$B$35=G$4)*Indicators!$M$5:$M$35*('Indicator Scores'!$F$5:$F$35>0)),0) -> 1.875 | H21: =IFERROR(SUMPRODUCT((Indicators!$B$5:$B$35=H$4)*Indicators!$M$5:$M$35*'Indicator Scores'!$F$5:$F$35)/SUMPRODUCT((Indicators!$B$5:$B$35=H$4)*Indicators!$M$5:$M$35*('Indicator Scores'!$F$5:$F$35>0)),0) -> 1.2222222 | I21: =IFERROR(SUMPRODUCT((Indicators!$B$5:$B$35=I$4)*Indicators!$M$5:$M$35*'Indicator Scores'!$F$5:$F$35)/SUMPRODUCT((Indicators!$B$5:$B$35=I$4)*Indicators!$M$5:$M$35*('Indicator Scores'!$F$5:$F$35>0)),0) -> 1.6666667 | J21: =IFERROR(SUMPRODUCT((Indicators!$B$5:$B$35=J$4)*Indicators!$M$5:$M$35*'Indicator Scores'!$F$5:$F$35)/SUMPRODUCT((Indicators!$B$5:$B$35=J$4)*Indicators!$M$5:$M$35*('Indicator Scores'!$F$5:$F$35>0)),0) -> 2 | K21: =IFERROR(SUMPRODUCT(F21:J21,INDEX('Factor Weights'!$C$5:$G$11,MATCH(D21,'Factor Weights'!$A$5:$A$11,0),0))/SUMPRODUCT((F21:J21>0)*INDEX('Factor Weights'!$C$5:$G$11,MATCH(D21,'Factor Weights'!$A$5:$A$11,0),0)),0) -> 1.8625 | L21: =MAX(F21:J21) -> 3 | M21: =IF(L21>=Config!$C$13,MAX(K21,Config!$C$14),K21) -> 1.8625 | N21: =IF(Config!$C$12="Weighted average",K21,IF(Config!$C$12="Weighted with floor",M21,L21)) -> 1.8625 | O21: =IF(N21<Config!$D$5,"",MATCH(N21,Config!$D$5:$D$9,1)) -> 2 | P21: =IF(O21="","No data",INDEX(Config!$B$5:$B$9,O21)) -> Medium-Low | Q21: 0 | T21: =IF(O21="","",IF(AND(S21="Y",Q21<>0),MAX(1,MIN(5,O21+MAX(-Config!$C$27,MIN(Config!$C$27,Q21)))),O21)) -> 2 | U21: =IF(T21="","No data",INDEX(Config!$B$5:$B$9,T21)) -> Medium-Low | V21: =IF(Q21=0,"None",IF(S21="Y","Applied","Pending HO approval")) -> None | W21: =SUMPRODUCT((Indicators!$M$5:$M$35>0)*('Indicator Data'!$F$5:$F$35<>""))/SUMPRODUCT(--(Indicators!$M$5:$M$35>0)) -> 1
A22: =Entities!$A$7 -> JO-INV | B22: =INDEX(Entities!$B$5:$B$34,MATCH(A22,Entities!$A$5:$A$34,0)) -> Al-Arabi Investment Group (AB Invest) | C22: =INDEX(Entities!$D$5:$D$34,MATCH(A22,Entities!$A$5:$A$34,0)) -> Jordan (home) | D22: FC-04 | E22: =INDEX('Risk Taxonomy'!$B$5:$B$24,MATCH(D22,'Risk Taxonomy'!$A$5:$A$24,0)) -> Sanctions | F22: =IFERROR(SUMPRODUCT((Indicators!$B$5:$B$35=F$4)*Indicators!$N$5:$N$35*'Indicator Scores'!$F$5:$F$35)/SUMPRODUCT((Indicators!$B$5:$B$35=F$4)*Indicators!$N$5:$N$35*('Indicator Scores'!$F$5:$F$35>0)),0) -> 2.7142857 | G22: =IFERROR(SUMPRODUCT((Indicators!$B$5:$B$35=G$4)*Indicators!$N$5:$N$35*'Indicator Scores'!$F$5:$F$35)/SUMPRODUCT((Indicators!$B$5:$B$35=G$4)*Indicators!$N$5:$N$35*('Indicator Scores'!$F$5:$F$35>0)),0) -> 2 | H22: =IFERROR(SUMPRODUCT((Indicators!$B$5:$B$35=H$4)*Indicators!$N$5:$N$35*'Indicator Scores'!$F$5:$F$35)/SUMPRODUCT((Indicators!$B$5:$B$35=H$4)*Indicators!$N$5:$N$35*('Indicator Scores'!$F$5:$F$35>0)),0) -> 1.375 | I22: =IFERROR(SUMPRODUCT((Indicators!$B$5:$B$35=I$4)*Indicators!$N$5:$N$35*'Indicator Scores'!$F$5:$F$35)/SUMPRODUCT((Indicators!$B$5:$B$35=I$4)*Indicators!$N$5:$N$35*('Indicator Scores'!$F$5:$F$35>0)),0) -> 1.3333333 | J22: =IFERROR(SUMPRODUCT((Indicators!$B$5:$B$35=J$4)*Indicators!$N$5:$N$35*'Indicator Scores'!$F$5:$F$35)/SUMPRODUCT((Indicators!$B$5:$B$35=J$4)*Indicators!$N$5:$N$35*('Indicator Scores'!$F$5:$F$35>0)),0) -> 1.8 | K22: =IFERROR(SUMPRODUCT(F22:J22,INDEX('Factor Weights'!$C$5:$G$11,MATCH(D22,'Factor Weights'!$A$5:$A$11,0),0))/SUMPRODUCT((F22:J22>0)*INDEX('Factor Weights'!$C$5:$G$11,MATCH(D22,'Factor Weights'!$A$5:$A$11,0),0)),0) -> 1.9088095 | L22: =MAX(F22:J22) -> 2.7142857 | M22: =IF(L22>=Config!$C$13,MAX(K22,Config!$C$14),K22) -> 1.9088095 | N22: =IF(Config!$C$12="Weighted average",K22,IF(Config!$C$12="Weighted with floor",M22,L22)) -> 1.9088095 | O22: =IF(N22<Config!$D$5,"",MATCH(N22,Config!$D$5:$D$9,1)) -> 2 | P22: =IF(O22="","No data",INDEX(Config!$B$5:$B$9,O22)) -> Medium-Low | Q22: 0 | T22: =IF(O22="","",IF(AND(S22="Y",Q22<>0),MAX(1,MIN(5,O22+MAX(-Config!$C$27,MIN(Config!$C$27,Q22)))),O22)) -> 2 | U22: =IF(T22="","No data",INDEX(Config!$B$5:$B$9,T22)) -> Medium-Low | V22: =IF(Q22=0,"None",IF(S22="Y","Applied","Pending HO approval")) -> None | W22: =SUMPRODUCT((Indicators!$N$5:$N$35>0)*('Indicator Data'!$F$5:$F$35<>""))/SUMPRODUCT(--(Indicators!$N$5:$N$35>0)) -> 1
A23: =Entities!$A$7 -> JO-INV | B23: =INDEX(Entities!$B$5:$B$34,MATCH(A23,Entities!$A$5:$A$34,0)) -> Al-Arabi Investment Group (AB Invest) | C23: =INDEX(Entities!$D$5:$D$34,MATCH(A23,Entities!$A$5:$A$34,0)) -> Jordan (home) | D23: FC-05 | E23: =INDEX('Risk Taxonomy'!$B$5:$B$24,MATCH(D23,'Risk Taxonomy'!$A$5:$A$24,0)) -> Bribery and corruption | F23: =IFERROR(SUMPRODUCT((Indicators!$B$5:$B$35=F$4)*Indicators!$O$5:$O$35*'Indicator Scores'!$F$5:$F$35)/SUMPRODUCT((Indicators!$B$5:$B$35=F$4)*Indicators!$O$5:$O$35*('Indicator Scores'!$F$5:$F$35>0)),0) -> 2 | G23: =IFERROR(SUMPRODUCT((Indicators!$B$5:$B$35=G$4)*Indicators!$O$5:$O$35*'Indicator Scores'!$F$5:$F$35)/SUMPRODUCT((Indicators!$B$5:$B$35=G$4)*Indicators!$O$5:$O$35*('Indicator Scores'!$F$5:$F$35>0)),0) -> 2.6 | H23: =IFERROR(SUMPRODUCT((Indicators!$B$5:$B$35=H$4)*Indicators!$O$5:$O$35*'Indicator Scores'!$F$5:$F$35)/SUMPRODUCT((Indicators!$B$5:$B$35=H$4)*Indicators!$O$5:$O$35*('Indicator Scores'!$F$5:$F$35>0)),0) -> 1.5 | I23: =IFERROR(SUMPRODUCT((Indicators!$B$5:$B$35=I$4)*Indicators!$O$5:$O$35*'Indicator Scores'!$F$5:$F$35)/SUMPRODUCT((Indicators!$B$5:$B$35=I$4)*Indicators!$O$5:$O$35*('Indicator Scores'!$F$5:$F$35>0)),0) -> 3.2 | J23: =IFERROR(SUMPRODUCT((Indicators!$B$5:$B$35=J$4)*Indicators!$O$5:$O$35*'Indicator Scores'!$F$5:$F$35)/SUMPRODUCT((Indicators!$B$5:$B$35=J$4)*Indicators!$O$5:$O$35*('Indicator Scores'!$F$5:$F$35>0)),0) -> 3 | K23: =IFERROR(SUMPRODUCT(F23:J23,INDEX('Factor Weights'!$C$5:$G$11,MATCH(D23,'Factor Weights'!$A$5:$A$11,0),0))/SUMPRODUCT((F23:J23>0)*INDEX('Factor Weights'!$C$5:$G$11,MATCH(D23,'Factor Weights'!$A$5:$A$11,0),0)),0) -> 2.415 | L23: =MAX(F23:J23) -> 3.2 | M23: =IF(L23>=Config!$C$13,MAX(K23,Config!$C$14),K23) -> 2.415 | N23: =IF(Config!$C$12="Weighted average",K23,IF(Config!$C$12="Weighted with floor",M23,L23)) -> 2.415 | O23: =IF(N23<Config!$D$5,"",MATCH(N23,Config!$D$5:$D$9,1)) -> 2 | P23: =IF(O23="","No data",INDEX(Config!$B$5:$B$9,O23)) -> Medium-Low | Q23: 0 | T23: =IF(O23="","",IF(AND(S23="Y",Q23<>0),MAX(1,MIN(5,O23+MAX(-Config!$C$27,MIN(Config!$C$27,Q23)))),O23)) -> 2 | U23: =IF(T23="","No data",INDEX(Config!$B$5:$B$9,T23)) -> Medium-Low | V23: =IF(Q23=0,"None",IF(S23="Y","Applied","Pending HO approval")) -> None | W23: =SUMPRODUCT((Indicators!$O$5:$O$35>0)*('Indicator Data'!$F$5:$F$35<>""))/SUMPRODUCT(--(Indicators!$O$5:$O$35>0)) -> 1
A24: =Entities!$A$7 -> JO-INV | B24: =INDEX(Entities!$B$5:$B$34,MATCH(A24,Entities!$A$5:$A$34,0)) -> Al-Arabi Investment Group (AB Invest) | C24: =INDEX(Entities!$D$5:$D$34,MATCH(A24,Entities!$A$5:$A$34,0)) -> Jordan (home) | D24: FC-06 | E24: =INDEX('Risk Taxonomy'!$B$5:$B$24,MATCH(D24,'Risk Taxonomy'!$A$5:$A$24,0)) -> Fraud | F24: =IFERROR(SUMPRODUCT((Indicators!$B$5:$B$35=F$4)*Indicators!$P$5:$P$35*'Indicator Scores'!$F$5:$F$35)/SUMPRODUCT((Indicators!$B$5:$B$35=F$4)*Indicators!$P$5:$P$35*('Indicator Scores'!$F$5:$F$35>0)),0) -> 2 | G24: =IFERROR(SUMPRODUCT((Indicators!$B$5:$B$35=G$4)*Indicators!$P$5:$P$35*'Indicator Scores'!$F$5:$F$35)/SUMPRODUCT((Indicators!$B$5:$B$35=G$4)*Indicators!$P$5:$P$35*('Indicator Scores'!$F$5:$F$35>0)),0) -> 2.5 | H24: =IFERROR(SUMPRODUCT((Indicators!$B$5:$B$35=H$4)*Indicators!$P$5:$P$35*'Indicator Scores'!$F$5:$F$35)/SUMPRODUCT((Indicators!$B$5:$B$35=H$4)*Indicators!$P$5:$P$35*('Indicator Scores'!$F$5:$F$35>0)),0) -> 1.8 | I24: =IFERROR(SUMPRODUCT((Indicators!$B$5:$B$35=I$4)*Indicators!$P$5:$P$35*'Indicator Scores'!$F$5:$F$35)/SUMPRODUCT((Indicators!$B$5:$B$35=I$4)*Indicators!$P$5:$P$35*('Indicator Scores'!$F$5:$F$35>0)),0) -> 2.1111111 | J24: =IFERROR(SUMPRODUCT((Indicators!$B$5:$B$35=J$4)*Indicators!$P$5:$P$35*'Indicator Scores'!$F$5:$F$35)/SUMPRODUCT((Indicators!$B$5:$B$35=J$4)*Indicators!$P$5:$P$35*('Indicator Scores'!$F$5:$F$35>0)),0) -> 2 | K24: =IFERROR(SUMPRODUCT(F24:J24,INDEX('Factor Weights'!$C$5:$G$11,MATCH(D24,'Factor Weights'!$A$5:$A$11,0),0))/SUMPRODUCT((F24:J24>0)*INDEX('Factor Weights'!$C$5:$G$11,MATCH(D24,'Factor Weights'!$A$5:$A$11,0),0)),0) -> 2.0433333 | L24: =MAX(F24:J24) -> 2.5 | M24: =IF(L24>=Config!$C$13,MAX(K24,Config!$C$14),K24) -> 2.0433333 | N24: =IF(Config!$C$12="Weighted average",K24,IF(Config!$C$12="Weighted with floor",M24,L24)) -> 2.0433333 | O24: =IF(N24<Config!$D$5,"",MATCH(N24,Config!$D$5:$D$9,1)) -> 2 | P24: =IF(O24="","No data",INDEX(Config!$B$5:$B$9,O24)) -> Medium-Low | Q24: 0 | T24: =IF(O24="","",IF(AND(S24="Y",Q24<>0),MAX(1,MIN(5,O24+MAX(-Config!$C$27,MIN(Config!$C$27,Q24)))),O24)) -> 2 | U24: =IF(T24="","No data",INDEX(Config!$B$5:$B$9,T24)) -> Medium-Low | V24: =IF(Q24=0,"None",IF(S24="Y","Applied","Pending HO approval")) -> None | W24: =SUMPRODUCT((Indicators!$P$5:$P$35>0)*('Indicator Data'!$F$5:$F$35<>""))/SUMPRODUCT(--(Indicators!$P$5:$P$35>0)) -> 1
A25: =Entities!$A$7 -> JO-INV | B25: =INDEX(Entities!$B$5:$B$34,MATCH(A25,Entities!$A$5:$A$34,0)) -> Al-Arabi Investment Group (AB Invest) | C25: =INDEX(Entities!$D$5:$D$34,MATCH(A25,Entities!$A$5:$A$34,0)) -> Jordan (home) | D25: FC-07 | E25: =INDEX('Risk Taxonomy'!$B$5:$B$24,MATCH(D25,'Risk Taxonomy'!$A$5:$A$24,0)) -> Tax evasion and tax transparency | F25: =IFERROR(SUMPRODUCT((Indicators!$B$5:$B$35=F$4)*Indicators!$Q$5:$Q$35*'Indicator Scores'!$F$5:$F$35)/SUMPRODUCT((Indicators!$B$5:$B$35=F$4)*Indicators!$Q$5:$Q$35*('Indicator Scores'!$F$5:$F$35>0)),0) -> 2.8888889 | G25: =IFERROR(SUMPRODUCT((Indicators!$B$5:$B$35=G$4)*Indicators!$Q$5:$Q$35*'Indicator Scores'!$F$5:$F$35)/SUMPRODUCT((Indicators!$B$5:$B$35=G$4)*Indicators!$Q$5:$Q$35*('Indicator Scores'!$F$5:$F$35>0)),0) -> 3.1666667 | H25: =IFERROR(SUMPRODUCT((Indicators!$B$5:$B$35=H$4)*Indicators!$Q$5:$Q$35*'Indicator Scores'!$F$5:$F$35)/SUMPRODUCT((Indicators!$B$5:$B$35=H$4)*Indicators!$Q$5:$Q$35*('Indicator Scores'!$F$5:$F$35>0)),0) -> 2.1666667 | I25: =IFERROR(SUMPRODUCT((Indicators!$B$5:$B$35=I$4)*Indicators!$Q$5:$Q$35*'Indicator Scores'!$F$5:$F$35)/SUMPRODUCT((Indicators!$B$5:$B$35=I$4)*Indicators!$Q$5:$Q$35*('Indicator Scores'!$F$5:$F$35>0)),0) -> 3 | J25: =IFERROR(SUMPRODUCT((Indicators!$B$5:$B$35=J$4)*Indicators!$Q$5:$Q$35*'Indicator Scores'!$F$5:$F$35)/SUMPRODUCT((Indicators!$B$5:$B$35=J$4)*Indicators!$Q$5:$Q$35*('Indicator Scores'!$F$5:$F$35>0)),0) -> 2.6 | K25: =IFERROR(SUMPRODUCT(F25:J25,INDEX('Factor Weights'!$C$5:$G$11,MATCH(D25,'Factor Weights'!$A$5:$A$11,0),0))/SUMPRODUCT((F25:J25>0)*INDEX('Factor Weights'!$C$5:$G$11,MATCH(D25,'Factor Weights'!$A$5:$A$11,0),0)),0) -> 2.7961111 | L25: =MAX(F25:J25) -> 3.1666667 | M25: =IF(L25>=Config!$C$13,MAX(K25,Config!$C$14),K25) -> 2.7961111 | N25: =IF(Config!$C$12="Weighted average",K25,IF(Config!$C$12="Weighted with floor",M25,L25)) -> 2.7961111 | O25: =IF(N25<Config!$D$5,"",MATCH(N25,Config!$D$5:$D$9,1)) -> 3 | P25: =IF(O25="","No data",INDEX(Config!$B$5:$B$9,O25)) -> Medium | Q25: 0 | T25: =IF(O25="","",IF(AND(S25="Y",Q25<>0),MAX(1,MIN(5,O25+MAX(-Config!$C$27,MIN(Config!$C$27,Q25)))),O25)) -> 3 | U25: =IF(T25="","No data",INDEX(Config!$B$5:$B$9,T25)) -> Medium | V25: =IF(Q25=0,"None",IF(S25="Y","Applied","Pending HO approval")) -> None | W25: =SUMPRODUCT((Indicators!$Q$5:$Q$35>0)*('Indicator Data'!$F$5:$F$35<>""))/SUMPRODUCT(--(Indicators!$Q$5:$Q$35>0)) -> 1
A26: =Entities!$A$8 -> JO-INS | B26: =INDEX(Entities!$B$5:$B$34,MATCH(A26,Entities!$A$5:$A$34,0)) -> Insurance subsidiary – Jordan | C26: =INDEX(Entities!$D$5:$D$34,MATCH(A26,Entities!$A$5:$A$34,0)) -> Jordan (home) | D26: FC-01 | E26: =INDEX('Risk Taxonomy'!$B$5:$B$24,MATCH(D26,'Risk Taxonomy'!$A$5:$A$24,0)) -> Money laundering | F26: =IFERROR(SUMPRODUCT((Indicators!$B$5:$B$35=F$4)*Indicators!$K$5:$K$35*'Indicator Scores'!$G$5:$G$35)/SUMPRODUCT((Indicators!$B$5:$B$35=F$4)*Indicators!$K$5:$K$35*('Indicator Scores'!$G$5:$G$35>0)),0) -> 3.25 | G26: =IFERROR(SUMPRODUCT((Indicators!$B$5:$B$35=G$4)*Indicators!$K$5:$K$35*'Indicator Scores'!$G$5:$G$35)/SUMPRODUCT((Indicators!$B$5:$B$35=G$4)*Indicators!$K$5:$K$35*('Indicator Scores'!$G$5:$G$35>0)),0) -> 3.1111111 | H26: =IFERROR(SUMPRODUCT((Indicators!$B$5:$B$35=H$4)*Indicators!$K$5:$K$35*'Indicator Scores'!$G$5:$G$35)/SUMPRODUCT((Indicators!$B$5:$B$35=H$4)*Indicators!$K$5:$K$35*('Indicator Scores'!$G$5:$G$35>0)),0) -> 2 | I26: =IFERROR(SUMPRODUCT((Indicators!$B$5:$B$35=I$4)*Indicators!$K$5:$K$35*'Indicator Scores'!$G$5:$G$35)/SUMPRODUCT((Indicators!$B$5:$B$35=I$4)*Indicators!$K$5:$K$35*('Indicator Scores'!$G$5:$G$35>0)),0) -> 1.8571429 | J26: =IFERROR(SUMPRODUCT((Indicators!$B$5:$B$35=J$4)*Indicators!$K$5:$K$35*'Indicator Scores'!$G$5:$G$35)/SUMPRODUCT((Indicators!$B$5:$B$35=J$4)*Indicators!$K$5:$K$35*('Indicator Scores'!$G$5:$G$35>0)),0) -> 2.5 | K26: =IFERROR(SUMPRODUCT(F26:J26,INDEX('Factor Weights'!$C$5:$G$11,MATCH(D26,'Factor Weights'!$A$5:$A$11,0),0))/SUMPRODUCT((F26:J26>0)*INDEX('Factor Weights'!$C$5:$G$11,MATCH(D26,'Factor Weights'!$A$5:$A$11,0),0)),0) -> 2.6813492 | L26: =MAX(F26:J26) -> 3.25 | M26: =IF(L26>=Config!$C$13,MAX(K26,Config!$C$14),K26) -> 2.6813492 | N26: =IF(Config!$C$12="Weighted average",K26,IF(Config!$C$12="Weighted with floor",M26,L26)) -> 2.6813492 | O26: =IF(N26<Config!$D$5,"",MATCH(N26,Config!$D$5:$D$9,1)) -> 3 | P26: =IF(O26="","No data",INDEX(Config!$B$5:$B$9,O26)) -> Medium | Q26: 0 | T26: =IF(O26="","",IF(AND(S26="Y",Q26<>0),MAX(1,MIN(5,O26+MAX(-Config!$C$27,MIN(Config!$C$27,Q26)))),O26)) -> 3 | U26: =IF(T26="","No data",INDEX(Config!$B$5:$B$9,T26)) -> Medium | V26: =IF(Q26=0,"None",IF(S26="Y","Applied","Pending HO approval")) -> None | W26: =SUMPRODUCT((Indicators!$K$5:$K$35>0)*('Indicator Data'!$G$5:$G$35<>""))/SUMPRODUCT(--(Indicators!$K$5:$K$35>0)) -> 1
A27: =Entities!$A$8 -> JO-INS | B27: =INDEX(Entities!$B$5:$B$34,MATCH(A27,Entities!$A$5:$A$34,0)) -> Insurance subsidiary – Jordan | C27: =INDEX(Entities!$D$5:$D$34,MATCH(A27,Entities!$A$5:$A$34,0)) -> Jordan (home) | D27: FC-02 | E27: =INDEX('Risk Taxonomy'!$B$5:$B$24,MATCH(D27,'Risk Taxonomy'!$A$5:$A$24,0)) -> Terrorist financing | F27: =IFERROR(SUMPRODUCT((Indicators!$B$5:$B$35=F$4)*Indicators!$L$5:$L$35*'Indicator Scores'!$G$5:$G$35)/SUMPRODUCT((Indicators!$B$5:$B$35=F$4)*Indicators!$L$5:$L$35*('Indicator Scores'!$G$5:$G$35>0)),0) -> 2.7 | G27: =IFERROR(SUMPRODUCT((Indicators!$B$5:$B$35=G$4)*Indicators!$L$5:$L$35*'Indicator Scores'!$G$5:$G$35)/SUMPRODUCT((Indicators!$B$5:$B$35=G$4)*Indicators!$L$5:$L$35*('Indicator Scores'!$G$5:$G$35>0)),0) -> 3.2222222 | H27: =IFERROR(SUMPRODUCT((Indicators!$B$5:$B$35=H$4)*Indicators!$L$5:$L$35*'Indicator Scores'!$G$5:$G$35)/SUMPRODUCT((Indicators!$B$5:$B$35=H$4)*Indicators!$L$5:$L$35*('Indicator Scores'!$G$5:$G$35>0)),0) -> 1.3333333 | I27: =IFERROR(SUMPRODUCT((Indicators!$B$5:$B$35=I$4)*Indicators!$L$5:$L$35*'Indicator Scores'!$G$5:$G$35)/SUMPRODUCT((Indicators!$B$5:$B$35=I$4)*Indicators!$L$5:$L$35*('Indicator Scores'!$G$5:$G$35>0)),0) -> 2 | J27: =IFERROR(SUMPRODUCT((Indicators!$B$5:$B$35=J$4)*Indicators!$L$5:$L$35*'Indicator Scores'!$G$5:$G$35)/SUMPRODUCT((Indicators!$B$5:$B$35=J$4)*Indicators!$L$5:$L$35*('Indicator Scores'!$G$5:$G$35>0)),0) -> 2.1428571 | K27: =IFERROR(SUMPRODUCT(F27:J27,INDEX('Factor Weights'!$C$5:$G$11,MATCH(D27,'Factor Weights'!$A$5:$A$11,0),0))/SUMPRODUCT((F27:J27>0)*INDEX('Factor Weights'!$C$5:$G$11,MATCH(D27,'Factor Weights'!$A$5:$A$11,0),0)),0) -> 2.4702381 | L27: =MAX(F27:J27) -> 3.2222222 | M27: =IF(L27>=Config!$C$13,MAX(K27,Config!$C$14),K27) -> 2.4702381 | N27: =IF(Config!$C$12="Weighted average",K27,IF(Config!$C$12="Weighted with floor",M27,L27)) -> 2.4702381 | O27: =IF(N27<Config!$D$5,"",MATCH(N27,Config!$D$5:$D$9,1)) -> 2 | P27: =IF(O27="","No data",INDEX(Config!$B$5:$B$9,O27)) -> Medium-Low | Q27: 0 | T27: =IF(O27="","",IF(AND(S27="Y",Q27<>0),MAX(1,MIN(5,O27+MAX(-Config!$C$27,MIN(Config!$C$27,Q27)))),O27)) -> 2 | U27: =IF(T27="","No data",INDEX(Config!$B$5:$B$9,T27)) -> Medium-Low | V27: =IF(Q27=0,"None",IF(S27="Y","Applied","Pending HO approval")) -> None | W27: =SUMPRODUCT((Indicators!$L$5:$L$35>0)*('Indicator Data'!$G$5:$G$35<>""))/SUMPRODUCT(--(Indicators!$L$5:$L$35>0)) -> 1
A28: =Entities!$A$8 -> JO-INS | B28: =INDEX(Entities!$B$5:$B$34,MATCH(A28,Entities!$A$5:$A$34,0)) -> Insurance subsidiary – Jordan | C28: =INDEX(Entities!$D$5:$D$34,MATCH(A28,Entities!$A$5:$A$34,0)) -> Jordan (home) | D28: FC-03 | E28: =INDEX('Risk Taxonomy'!$B$5:$B$24,MATCH(D28,'Risk Taxonomy'!$A$5:$A$24,0)) -> Proliferation financing | F28: =IFERROR(SUMPRODUCT((Indicators!$B$5:$B$35=F$4)*Indicators!$M$5:$M$35*'Indicator Scores'!$G$5:$G$35)/SUMPRODUCT((Indicators!$B$5:$B$35=F$4)*Indicators!$M$5:$M$35*('Indicator Scores'!$G$5:$G$35>0)),0) -> 3.75 | G28: =IFERROR(SUMPRODUCT((Indicators!$B$5:$B$35=G$4)*Indicators!$M$5:$M$35*'Indicator Scores'!$G$5:$G$35)/SUMPRODUCT((Indicators!$B$5:$B$35=G$4)*Indicators!$M$5:$M$35*('Indicator Scores'!$G$5:$G$35>0)),0) -> 3.75 | H28: =IFERROR(SUMPRODUCT((Indicators!$B$5:$B$35=H$4)*Indicators!$M$5:$M$35*'Indicator Scores'!$G$5:$G$35)/SUMPRODUCT((Indicators!$B$5:$B$35=H$4)*Indicators!$M$5:$M$35*('Indicator Scores'!$G$5:$G$35>0)),0) -> 1.2222222 | I28: =IFERROR(SUMPRODUCT((Indicators!$B$5:$B$35=I$4)*Indicators!$M$5:$M$35*'Indicator Scores'!$G$5:$G$35)/SUMPRODUCT((Indicators!$B$5:$B$35=I$4)*Indicators!$M$5:$M$35*('Indicator Scores'!$G$5:$G$35>0)),0) -> 2.6666667 | J28: =IFERROR(SUMPRODUCT((Indicators!$B$5:$B$35=J$4)*Indicators!$M$5:$M$35*'Indicator Scores'!$G$5:$G$35)/SUMPRODUCT((Indicators!$B$5:$B$35=J$4)*Indicators!$M$5:$M$35*('Indicator Scores'!$G$5:$G$35>0)),0) -> 2.5 | K28: =IFERROR(SUMPRODUCT(F28:J28,INDEX('Factor Weights'!$C$5:$G$11,MATCH(D28,'Factor Weights'!$A$5:$A$11,0),0))/SUMPRODUCT((F28:J28>0)*INDEX('Factor Weights'!$C$5:$G$11,MATCH(D28,'Factor Weights'!$A$5:$A$11,0),0)),0) -> 2.6875 | L28: =MAX(F28:J28) -> 3.75 | M28: =IF(L28>=Config!$C$13,MAX(K28,Config!$C$14),K28) -> 2.6875 | N28: =IF(Config!$C$12="Weighted average",K28,IF(Config!$C$12="Weighted with floor",M28,L28)) -> 2.6875 | O28: =IF(N28<Config!$D$5,"",MATCH(N28,Config!$D$5:$D$9,1)) -> 3 | P28: =IF(O28="","No data",INDEX(Config!$B$5:$B$9,O28)) -> Medium | Q28: 0 | T28: =IF(O28="","",IF(AND(S28="Y",Q28<>0),MAX(1,MIN(5,O28+MAX(-Config!$C$27,MIN(Config!$C$27,Q28)))),O28)) -> 3 | U28: =IF(T28="","No data",INDEX(Config!$B$5:$B$9,T28)) -> Medium | V28: =IF(Q28=0,"None",IF(S28="Y","Applied","Pending HO approval")) -> None | W28: =SUMPRODUCT((Indicators!$M$5:$M$35>0)*('Indicator Data'!$G$5:$G$35<>""))/SUMPRODUCT(--(Indicators!$M$5:$M$35>0)) -> 1
A29: =Entities!$A$8 -> JO-INS | B29: =INDEX(Entities!$B$5:$B$34,MATCH(A29,Entities!$A$5:$A$34,0)) -> Insurance subsidiary – Jordan | C29: =INDEX(Entities!$D$5:$D$34,MATCH(A29,Entities!$A$5:$A$34,0)) -> Jordan (home) | D29: FC-04 | E29: =INDEX('Risk Taxonomy'!$B$5:$B$24,MATCH(D29,'Risk Taxonomy'!$A$5:$A$24,0)) -> Sanctions | F29: =IFERROR(SUMPRODUCT((Indicators!$B$5:$B$35=F$4)*Indicators!$N$5:$N$35*'Indicator Scores'!$G$5:$G$35)/SUMPRODUCT((Indicators!$B$5:$B$35=F$4)*Indicators!$N$5:$N$35*('Indicator Scores'!$G$5:$G$35>0)),0) -> 3.4285714 | G29: =IFERROR(SUMPRODUCT((Indicators!$B$5:$B$35=G$4)*Indicators!$N$5:$N$35*'Indicator Scores'!$G$5:$G$35)/SUMPRODUCT((Indicators!$B$5:$B$35=G$4)*Indicators!$N$5:$N$35*('Indicator Scores'!$G$5:$G$35>0)),0) -> 3.8571429 | H29: =IFERROR(SUMPRODUCT((Indicators!$B$5:$B$35=H$4)*Indicators!$N$5:$N$35*'Indicator Scores'!$G$5:$G$35)/SUMPRODUCT((Indicators!$B$5:$B$35=H$4)*Indicators!$N$5:$N$35*('Indicator Scores'!$G$5:$G$35>0)),0) -> 1.625 | I29: =IFERROR(SUMPRODUCT((Indicators!$B$5:$B$35=I$4)*Indicators!$N$5:$N$35*'Indicator Scores'!$G$5:$G$35)/SUMPRODUCT((Indicators!$B$5:$B$35=I$4)*Indicators!$N$5:$N$35*('Indicator Scores'!$G$5:$G$35>0)),0) -> 2.3333333 | J29: =IFERROR(SUMPRODUCT((Indicators!$B$5:$B$35=J$4)*Indicators!$N$5:$N$35*'Indicator Scores'!$G$5:$G$35)/SUMPRODUCT((Indicators!$B$5:$B$35=J$4)*Indicators!$N$5:$N$35*('Indicator Scores'!$G$5:$G$35>0)),0) -> 2.2 | K29: =IFERROR(SUMPRODUCT(F29:J29,INDEX('Factor Weights'!$C$5:$G$11,MATCH(D29,'Factor Weights'!$A$5:$A$11,0),0))/SUMPRODUCT((F29:J29>0)*INDEX('Factor Weights'!$C$5:$G$11,MATCH(D29,'Factor Weights'!$A$5:$A$11,0),0)),0) -> 2.9388095 | L29: =MAX(F29:J29) -> 3.8571429 | M29: =IF(L29>=Config!$C$13,MAX(K29,Config!$C$14),K29) -> 2.9388095 | N29: =IF(Config!$C$12="Weighted average",K29,IF(Config!$C$12="Weighted with floor",M29,L29)) -> 2.9388095 | O29: =IF(N29<Config!$D$5,"",MATCH(N29,Config!$D$5:$D$9,1)) -> 3 | P29: =IF(O29="","No data",INDEX(Config!$B$5:$B$9,O29)) -> Medium | Q29: 0 | T29: =IF(O29="","",IF(AND(S29="Y",Q29<>0),MAX(1,MIN(5,O29+MAX(-Config!$C$27,MIN(Config!$C$27,Q29)))),O29)) -> 3 | U29: =IF(T29="","No data",INDEX(Config!$B$5:$B$9,T29)) -> Medium | V29: =IF(Q29=0,"None",IF(S29="Y","Applied","Pending HO approval")) -> None | W29: =SUMPRODUCT((Indicators!$N$5:$N$35>0)*('Indicator Data'!$G$5:$G$35<>""))/SUMPRODUCT(--(Indicators!$N$5:$N$35>0)) -> 1
A30: =Entities!$A$8 -> JO-INS | B30: =INDEX(Entities!$B$5:$B$34,MATCH(A30,Entities!$A$5:$A$34,0)) -> Insurance subsidiary – Jordan | C30: =INDEX(Entities!$D$5:$D$34,MATCH(A30,Entities!$A$5:$A$34,0)) -> Jordan (home) | D30: FC-05 | E30: =INDEX('Risk Taxonomy'!$B$5:$B$24,MATCH(D30,'Risk Taxonomy'!$A$5:$A$24,0)) -> Bribery and corruption | F30: =IFERROR(SUMPRODUCT((Indicators!$B$5:$B$35=F$4)*Indicators!$O$5:$O$35*'Indicator Scores'!$G$5:$G$35)/SUMPRODUCT((Indicators!$B$5:$B$35=F$4)*Indicators!$O$5:$O$35*('Indicator Scores'!$G$5:$G$35>0)),0) -> 3 | G30: =IFERROR(SUMPRODUCT((Indicators!$B$5:$B$35=G$4)*Indicators!$O$5:$O$35*'Indicator Scores'!$G$5:$G$35)/SUMPRODUCT((Indicators!$B$5:$B$35=G$4)*Indicators!$O$5:$O$35*('Indicator Scores'!$G$5:$G$35>0)),0) -> 3 | H30: =IFERROR(SUMPRODUCT((Indicators!$B$5:$B$35=H$4)*Indicators!$O$5:$O$35*'Indicator Scores'!$G$5:$G$35)/SUMPRODUCT((Indicators!$B$5:$B$35=H$4)*Indicators!$O$5:$O$35*('Indicator Scores'!$G$5:$G$35>0)),0) -> 2.5 | I30: =IFERROR(SUMPRODUCT((Indicators!$B$5:$B$35=I$4)*Indicators!$O$5:$O$35*'Indicator Scores'!$G$5:$G$35)/SUMPRODUCT((Indicators!$B$5:$B$35=I$4)*Indicators!$O$5:$O$35*('Indicator Scores'!$G$5:$G$35>0)),0) -> 3 | J30: =IFERROR(SUMPRODUCT((Indicators!$B$5:$B$35=J$4)*Indicators!$O$5:$O$35*'Indicator Scores'!$G$5:$G$35)/SUMPRODUCT((Indicators!$B$5:$B$35=J$4)*Indicators!$O$5:$O$35*('Indicator Scores'!$G$5:$G$35>0)),0) -> 4 | K30: =IFERROR(SUMPRODUCT(F30:J30,INDEX('Factor Weights'!$C$5:$G$11,MATCH(D30,'Factor Weights'!$A$5:$A$11,0),0))/SUMPRODUCT((F30:J30>0)*INDEX('Factor Weights'!$C$5:$G$11,MATCH(D30,'Factor Weights'!$A$5:$A$11,0),0)),0) -> 3.025 | L30: =MAX(F30:J30) -> 4 | M30: =IF(L30>=Config!$C$13,MAX(K30,Config!$C$14),K30) -> 3.025 | N30: =IF(Config!$C$12="Weighted average",K30,IF(Config!$C$12="Weighted with floor",M30,L30)) -> 3.025 | O30: =IF(N30<Config!$D$5,"",MATCH(N30,Config!$D$5:$D$9,1)) -> 3 | P30: =IF(O30="","No data",INDEX(Config!$B$5:$B$9,O30)) -> Medium | Q30: 0 | T30: =IF(O30="","",IF(AND(S30="Y",Q30<>0),MAX(1,MIN(5,O30+MAX(-Config!$C$27,MIN(Config!$C$27,Q30)))),O30)) -> 3 | U30: =IF(T30="","No data",INDEX(Config!$B$5:$B$9,T30)) -> Medium | V30: =IF(Q30=0,"None",IF(S30="Y","Applied","Pending HO approval")) -> None | W30: =SUMPRODUCT((Indicators!$O$5:$O$35>0)*('Indicator Data'!$G$5:$G$35<>""))/SUMPRODUCT(--(Indicators!$O$5:$O$35>0)) -> 1
A31: =Entities!$A$8 -> JO-INS | B31: =INDEX(Entities!$B$5:$B$34,MATCH(A31,Entities!$A$5:$A$34,0)) -> Insurance subsidiary – Jordan | C31: =INDEX(Entities!$D$5:$D$34,MATCH(A31,Entities!$A$5:$A$34,0)) -> Jordan (home) | D31: FC-06 | E31: =INDEX('Risk Taxonomy'!$B$5:$B$24,MATCH(D31,'Risk Taxonomy'!$A$5:$A$24,0)) -> Fraud | F31: =IFERROR(SUMPRODUCT((Indicators!$B$5:$B$35=F$4)*Indicators!$P$5:$P$35*'Indicator Scores'!$G$5:$G$35)/SUMPRODUCT((Indicators!$B$5:$B$35=F$4)*Indicators!$P$5:$P$35*('Indicator Scores'!$G$5:$G$35>0)),0) -> 3 | G31: =IFERROR(SUMPRODUCT((Indicators!$B$5:$B$35=G$4)*Indicators!$P$5:$P$35*'Indicator Scores'!$G$5:$G$35)/SUMPRODUCT((Indicators!$B$5:$B$35=G$4)*Indicators!$P$5:$P$35*('Indicator Scores'!$G$5:$G$35>0)),0) -> 3 | H31: =IFERROR(SUMPRODUCT((Indicators!$B$5:$B$35=H$4)*Indicators!$P$5:$P$35*'Indicator Scores'!$G$5:$G$35)/SUMPRODUCT((Indicators!$B$5:$B$35=H$4)*Indicators!$P$5:$P$35*('Indicator Scores'!$G$5:$G$35>0)),0) -> 1.8 | I31: =IFERROR(SUMPRODUCT((Indicators!$B$5:$B$35=I$4)*Indicators!$P$5:$P$35*'Indicator Scores'!$G$5:$G$35)/SUMPRODUCT((Indicators!$B$5:$B$35=I$4)*Indicators!$P$5:$P$35*('Indicator Scores'!$G$5:$G$35>0)),0) -> 1.5555556 | J31: =IFERROR(SUMPRODUCT((Indicators!$B$5:$B$35=J$4)*Indicators!$P$5:$P$35*'Indicator Scores'!$G$5:$G$35)/SUMPRODUCT((Indicators!$B$5:$B$35=J$4)*Indicators!$P$5:$P$35*('Indicator Scores'!$G$5:$G$35>0)),0) -> 2 | K31: =IFERROR(SUMPRODUCT(F31:J31,INDEX('Factor Weights'!$C$5:$G$11,MATCH(D31,'Factor Weights'!$A$5:$A$11,0),0))/SUMPRODUCT((F31:J31>0)*INDEX('Factor Weights'!$C$5:$G$11,MATCH(D31,'Factor Weights'!$A$5:$A$11,0),0)),0) -> 2.1266667 | L31: =MAX(F31:J31) -> 3 | M31: =IF(L31>=Config!$C$13,MAX(K31,Config!$C$14),K31) -> 2.1266667 | N31: =IF(Config!$C$12="Weighted average",K31,IF(Config!$C$12="Weighted with floor",M31,L31)) -> 2.1266667 | O31: =IF(N31<Config!$D$5,"",MATCH(N31,Config!$D$5:$D$9,1)) -> 2 | P31: =IF(O31="","No data",INDEX(Config!$B$5:$B$9,O31)) -> Medium-Low | Q31: 0 | T31: =IF(O31="","",IF(AND(S31="Y",Q31<>0),MAX(1,MIN(5,O31+MAX(-Config!$C$27,MIN(Config!$C$27,Q31)))),O31)) -> 2 | U31: =IF(T31="","No data",INDEX(Config!$B$5:$B$9,T31)) -> Medium-Low | V31: =IF(Q31=0,"None",IF(S31="Y","Applied","Pending HO approval")) -> None | W31: =SUMPRODUCT((Indicators!$P$5:$P$35>0)*('Indicator Data'!$G$5:$G$35<>""))/SUMPRODUCT(--(Indicators!$P$5:$P$35>0)) -> 1
A32: =Entities!$A$8 -> JO-INS | B32: =INDEX(Entities!$B$5:$B$34,MATCH(A32,Entities!$A$5:$A$34,0)) -> Insurance subsidiary – Jordan | C32: =INDEX(Entities!$D$5:$D$34,MATCH(A32,Entities!$A$5:$A$34,0)) -> Jordan (home) | D32: FC-07 | E32: =INDEX('Risk Taxonomy'!$B$5:$B$24,MATCH(D32,'Risk Taxonomy'!$A$5:$A$24,0)) -> Tax evasion and tax transparency | F32: =IFERROR(SUMPRODUCT((Indicators!$B$5:$B$35=F$4)*Indicators!$Q$5:$Q$35*'Indicator Scores'!$G$5:$G$35)/SUMPRODUCT((Indicators!$B$5:$B$35=F$4)*Indicators!$Q$5:$Q$35*('Indicator Scores'!$G$5:$G$35>0)),0) -> 3.4444444 | G32: =IFERROR(SUMPRODUCT((Indicators!$B$5:$B$35=G$4)*Indicators!$Q$5:$Q$35*'Indicator Scores'!$G$5:$G$35)/SUMPRODUCT((Indicators!$B$5:$B$35=G$4)*Indicators!$Q$5:$Q$35*('Indicator Scores'!$G$5:$G$35>0)),0) -> 2.5 | H32: =IFERROR(SUMPRODUCT((Indicators!$B$5:$B$35=H$4)*Indicators!$Q$5:$Q$35*'Indicator Scores'!$G$5:$G$35)/SUMPRODUCT((Indicators!$B$5:$B$35=H$4)*Indicators!$Q$5:$Q$35*('Indicator Scores'!$G$5:$G$35>0)),0) -> 3.1666667 | I32: =IFERROR(SUMPRODUCT((Indicators!$B$5:$B$35=I$4)*Indicators!$Q$5:$Q$35*'Indicator Scores'!$G$5:$G$35)/SUMPRODUCT((Indicators!$B$5:$B$35=I$4)*Indicators!$Q$5:$Q$35*('Indicator Scores'!$G$5:$G$35>0)),0) -> 2 | J32: =IFERROR(SUMPRODUCT((Indicators!$B$5:$B$35=J$4)*Indicators!$Q$5:$Q$35*'Indicator Scores'!$G$5:$G$35)/SUMPRODUCT((Indicators!$B$5:$B$35=J$4)*Indicators!$Q$5:$Q$35*('Indicator Scores'!$G$5:$G$35>0)),0) -> 2.6 | K32: =IFERROR(SUMPRODUCT(F32:J32,INDEX('Factor Weights'!$C$5:$G$11,MATCH(D32,'Factor Weights'!$A$5:$A$11,0),0))/SUMPRODUCT((F32:J32>0)*INDEX('Factor Weights'!$C$5:$G$11,MATCH(D32,'Factor Weights'!$A$5:$A$11,0),0)),0) -> 2.9238889 | L32: =MAX(F32:J32) -> 3.4444444 | M32: =IF(L32>=Config!$C$13,MAX(K32,Config!$C$14),K32) -> 2.9238889 | N32: =IF(Config!$C$12="Weighted average",K32,IF(Config!$C$12="Weighted with floor",M32,L32)) -> 2.9238889 | O32: =IF(N32<Config!$D$5,"",MATCH(N32,Config!$D$5:$D$9,1)) -> 3 | P32: =IF(O32="","No data",INDEX(Config!$B$5:$B$9,O32)) -> Medium | Q32: 0 | T32: =IF(O32="","",IF(AND(S32="Y",Q32<>0),MAX(1,MIN(5,O32+MAX(-Config!$C$27,MIN(Config!$C$27,Q32)))),O32)) -> 3 | U32: =IF(T32="","No data",INDEX(Config!$B$5:$B$9,T32)) -> Medium | V32: =IF(Q32=0,"None",IF(S32="Y","Applied","Pending HO approval")) -> None | W32: =SUMPRODUCT((Indicators!$Q$5:$Q$35>0)*('Indicator Data'!$G$5:$G$35<>""))/SUMPRODUCT(--(Indicators!$Q$5:$Q$35>0)) -> 1
A33: =Entities!$A$9 -> JO-LSG | B33: =INDEX(Entities!$B$5:$B$34,MATCH(A33,Entities!$A$5:$A$34,0)) -> Leasing subsidiary – Jordan | C33: =INDEX(Entities!$D$5:$D$34,MATCH(A33,Entities!$A$5:$A$34,0)) -> Jordan (home) | D33: FC-01 | E33: =INDEX('Risk Taxonomy'!$B$5:$B$24,MATCH(D33,'Risk Taxonomy'!$A$5:$A$24,0)) -> Money laundering | F33: =IFERROR(SUMPRODUCT((Indicators!$B$5:$B$35=F$4)*Indicators!$K$5:$K$35*'Indicator Scores'!$H$5:$H$35)/SUMPRODUCT((Indicators!$B$5:$B$35=F$4)*Indicators!$K$5:$K$35*('Indicator Scores'!$H$5:$H$35>0)),0) -> 2.9166667 | G33: =IFERROR(SUMPRODUCT((Indicators!$B$5:$B$35=G$4)*Indicators!$K$5:$K$35*'Indicator Scores'!$H$5:$H$35)/SUMPRODUCT((Indicators!$B$5:$B$35=G$4)*Indicators!$K$5:$K$35*('Indicator Scores'!$H$5:$H$35>0)),0) -> 3.2222222 | H33: =IFERROR(SUMPRODUCT((Indicators!$B$5:$B$35=H$4)*Indicators!$K$5:$K$35*'Indicator Scores'!$H$5:$H$35)/SUMPRODUCT((Indicators!$B$5:$B$35=H$4)*Indicators!$K$5:$K$35*('Indicator Scores'!$H$5:$H$35>0)),0) -> 2 | I33: =IFERROR(SUMPRODUCT((Indicators!$B$5:$B$35=I$4)*Indicators!$K$5:$K$35*'Indicator Scores'!$H$5:$H$35)/SUMPRODUCT((Indicators!$B$5:$B$35=I$4)*Indicators!$K$5:$K$35*('Indicator Scores'!$H$5:$H$35>0)),0) -> 3.2857143 | J33: =IFERROR(SUMPRODUCT((Indicators!$B$5:$B$35=J$4)*Indicators!$K$5:$K$35*'Indicator Scores'!$H$5:$H$35)/SUMPRODUCT((Indicators!$B$5:$B$35=J$4)*Indicators!$K$5:$K$35*('Indicator Scores'!$H$5:$H$35>0)),0) -> 2.3 | K33: =IFERROR(SUMPRODUCT(F33:J33,INDEX('Factor Weights'!$C$5:$G$11,MATCH(D33,'Factor Weights'!$A$5:$A$11,0),0))/SUMPRODUCT((F33:J33>0)*INDEX('Factor Weights'!$C$5:$G$11,MATCH(D33,'Factor Weights'!$A$5:$A$11,0),0)),0) -> 2.8034127 | L33: =MAX(F33:J33) -> 3.2857143 | M33: =IF(L33>=Config!$C$13,MAX(K33,Config!$C$14),K33) -> 2.8034127 | N33: =IF(Config!$C$12="Weighted average",K33,IF(Config!$C$12="Weighted with floor",M33,L33)) -> 2.8034127 | O33: =IF(N33<Config!$D$5,"",MATCH(N33,Config!$D$5:$D$9,1)) -> 3 | P33: =IF(O33="","No data",INDEX(Config!$B$5:$B$9,O33)) -> Medium | Q33: 0 | T33: =IF(O33="","",IF(AND(S33="Y",Q33<>0),MAX(1,MIN(5,O33+MAX(-Config!$C$27,MIN(Config!$C$27,Q33)))),O33)) -> 3 | U33: =IF(T33="","No data",INDEX(Config!$B$5:$B$9,T33)) -> Medium | V33: =IF(Q33=0,"None",IF(S33="Y","Applied","Pending HO approval")) -> None | W33: =SUMPRODUCT((Indicators!$K$5:$K$35>0)*('Indicator Data'!$H$5:$H$35<>""))/SUMPRODUCT(--(Indicators!$K$5:$K$35>0)) -> 1
A34: =Entities!$A$9 -> JO-LSG | B34: =INDEX(Entities!$B$5:$B$34,MATCH(A34,Entities!$A$5:$A$34,0)) -> Leasing subsidiary – Jordan | C34: =INDEX(Entities!$D$5:$D$34,MATCH(A34,Entities!$A$5:$A$34,0)) -> Jordan (home) | D34: FC-02 | E34: =INDEX('Risk Taxonomy'!$B$5:$B$24,MATCH(D34,'Risk Taxonomy'!$A$5:$A$24,0)) -> Terrorist financing | F34: =IFERROR(SUMPRODUCT((Indicators!$B$5:$B$35=F$4)*Indicators!$L$5:$L$35*'Indicator Scores'!$H$5:$H$35)/SUMPRODUCT((Indicators!$B$5:$B$35=F$4)*Indicators!$L$5:$L$35*('Indicator Scores'!$H$5:$H$35>0)),0) -> 2.6 | G34: =IFERROR(SUMPRODUCT((Indicators!$B$5:$B$35=G$4)*Indicators!$L$5:$L$35*'Indicator Scores'!$H$5:$H$35)/SUMPRODUCT((Indicators!$B$5:$B$35=G$4)*Indicators!$L$5:$L$35*('Indicator Scores'!$H$5:$H$35>0)),0) -> 3 | H34: =IFERROR(SUMPRODUCT((Indicators!$B$5:$B$35=H$4)*Indicators!$L$5:$L$35*'Indicator Scores'!$H$5:$H$35)/SUMPRODUCT((Indicators!$B$5:$B$35=H$4)*Indicators!$L$5:$L$35*('Indicator Scores'!$H$5:$H$35>0)),0) -> 1.5 | I34: =IFERROR(SUMPRODUCT((Indicators!$B$5:$B$35=I$4)*Indicators!$L$5:$L$35*'Indicator Scores'!$H$5:$H$35)/SUMPRODUCT((Indicators!$B$5:$B$35=I$4)*Indicators!$L$5:$L$35*('Indicator Scores'!$H$5:$H$35>0)),0) -> 3.3333333 | J34: =IFERROR(SUMPRODUCT((Indicators!$B$5:$B$35=J$4)*Indicators!$L$5:$L$35*'Indicator Scores'!$H$5:$H$35)/SUMPRODUCT((Indicators!$B$5:$B$35=J$4)*Indicators!$L$5:$L$35*('Indicator Scores'!$H$5:$H$35>0)),0) -> 2.1428571 | K34: =IFERROR(SUMPRODUCT(F34:J34,INDEX('Factor Weights'!$C$5:$G$11,MATCH(D34,'Factor Weights'!$A$5:$A$11,0),0))/SUMPRODUCT((F34:J34>0)*INDEX('Factor Weights'!$C$5:$G$11,MATCH(D34,'Factor Weights'!$A$5:$A$11,0),0)),0) -> 2.5369048 | L34: =MAX(F34:J34) -> 3.3333333 | M34: =IF(L34>=Config!$C$13,MAX(K34,Config!$C$14),K34) -> 2.5369048 | N34: =IF(Config!$C$12="Weighted average",K34,IF(Config!$C$12="Weighted with floor",M34,L34)) -> 2.5369048 | O34: =IF(N34<Config!$D$5,"",MATCH(N34,Config!$D$5:$D$9,1)) -> 2 | P34: =IF(O34="","No data",INDEX(Config!$B$5:$B$9,O34)) -> Medium-Low | Q34: 0 | T34: =IF(O34="","",IF(AND(S34="Y",Q34<>0),MAX(1,MIN(5,O34+MAX(-Config!$C$27,MIN(Config!$C$27,Q34)))),O34)) -> 2 | U34: =IF(T34="","No data",INDEX(Config!$B$5:$B$9,T34)) -> Medium-Low | V34: =IF(Q34=0,"None",IF(S34="Y","Applied","Pending HO approval")) -> None | W34: =SUMPRODUCT((Indicators!$L$5:$L$35>0)*('Indicator Data'!$H$5:$H$35<>""))/SUMPRODUCT(--(Indicators!$L$5:$L$35>0)) -> 1
A35: =Entities!$A$9 -> JO-LSG | B35: =INDEX(Entities!$B$5:$B$34,MATCH(A35,Entities!$A$5:$A$34,0)) -> Leasing subsidiary – Jordan | C35: =INDEX(Entities!$D$5:$D$34,MATCH(A35,Entities!$A$5:$A$34,0)) -> Jordan (home) | D35: FC-03 | E35: =INDEX('Risk Taxonomy'!$B$5:$B$24,MATCH(D35,'Risk Taxonomy'!$A$5:$A$24,0)) -> Proliferation financing | F35: =IFERROR(SUMPRODUCT((Indicators!$B$5:$B$35=F$4)*Indicators!$M$5:$M$35*'Indicator Scores'!$H$5:$H$35)/SUMPRODUCT((Indicators!$B$5:$B$35=F$4)*Indicators!$M$5:$M$35*('Indicator Scores'!$H$5:$H$35>0)),0) -> 3 | G35: =IFERROR(SUMPRODUCT((Indicators!$B$5:$B$35=G$4)*Indicators!$M$5:$M$35*'Indicator Scores'!$H$5:$H$35)/SUMPRODUCT((Indicators!$B$5:$B$35=G$4)*Indicators!$M$5:$M$35*('Indicator Scores'!$H$5:$H$35>0)),0) -> 3.375 | H35: =IFERROR(SUMPRODUCT((Indicators!$B$5:$B$35=H$4)*Indicators!$M$5:$M$35*'Indicator Scores'!$H$5:$H$35)/SUMPRODUCT((Indicators!$B$5:$B$35=H$4)*Indicators!$M$5:$M$35*('Indicator Scores'!$H$5:$H$35>0)),0) -> 1.3333333 | I35: =IFERROR(SUMPRODUCT((Indicators!$B$5:$B$35=I$4)*Indicators!$M$5:$M$35*'Indicator Scores'!$H$5:$H$35)/SUMPRODUCT((Indicators!$B$5:$B$35=I$4)*Indicators!$M$5:$M$35*('Indicator Scores'!$H$5:$H$35>0)),0) -> 4.3333333 | J35: =IFERROR(SUMPRODUCT((Indicators!$B$5:$B$35=J$4)*Indicators!$M$5:$M$35*'Indicator Scores'!$H$5:$H$35)/SUMPRODUCT((Indicators!$B$5:$B$35=J$4)*Indicators!$M$5:$M$35*('Indicator Scores'!$H$5:$H$35>0)),0) -> 2 | K35: =IFERROR(SUMPRODUCT(F35:J35,INDEX('Factor Weights'!$C$5:$G$11,MATCH(D35,'Factor Weights'!$A$5:$A$11,0),0))/SUMPRODUCT((F35:J35>0)*INDEX('Factor Weights'!$C$5:$G$11,MATCH(D35,'Factor Weights'!$A$5:$A$11,0),0)),0) -> 2.4791667 | L35: =MAX(F35:J35) -> 4.3333333 | M35: =IF(L35>=Config!$C$13,MAX(K35,Config!$C$14),K35) -> 2.4791667 | N35: =IF(Config!$C$12="Weighted average",K35,IF(Config!$C$12="Weighted with floor",M35,L35)) -> 2.4791667 | O35: =IF(N35<Config!$D$5,"",MATCH(N35,Config!$D$5:$D$9,1)) -> 2 | P35: =IF(O35="","No data",INDEX(Config!$B$5:$B$9,O35)) -> Medium-Low | Q35: 0 | T35: =IF(O35="","",IF(AND(S35="Y",Q35<>0),MAX(1,MIN(5,O35+MAX(-Config!$C$27,MIN(Config!$C$27,Q35)))),O35)) -> 2 | U35: =IF(T35="","No data",INDEX(Config!$B$5:$B$9,T35)) -> Medium-Low | V35: =IF(Q35=0,"None",IF(S35="Y","Applied","Pending HO approval")) -> None | W35: =SUMPRODUCT((Indicators!$M$5:$M$35>0)*('Indicator Data'!$H$5:$H$35<>""))/SUMPRODUCT(--(Indicators!$M$5:$M$35>0)) -> 1
A36: =Entities!$A$9 -> JO-LSG | B36: =INDEX(Entities!$B$5:$B$34,MATCH(A36,Entities!$A$5:$A$34,0)) -> Leasing subsidiary – Jordan | C36: =INDEX(Entities!$D$5:$D$34,MATCH(A36,Entities!$A$5:$A$34,0)) -> Jordan (home) | D36: FC-04 | E36: =INDEX('Risk Taxonomy'!$B$5:$B$24,MATCH(D36,'Risk Taxonomy'!$A$5:$A$24,0)) -> Sanctions | F36: =IFERROR(SUMPRODUCT((Indicators!$B$5:$B$35=F$4)*Indicators!$N$5:$N$35*'Indicator Scores'!$H$5:$H$35)/SUMPRODUCT((Indicators!$B$5:$B$35=F$4)*Indicators!$N$5:$N$35*('Indicator Scores'!$H$5:$H$35>0)),0) -> 2.7142857 | G36: =IFERROR(SUMPRODUCT((Indicators!$B$5:$B$35=G$4)*Indicators!$N$5:$N$35*'Indicator Scores'!$H$5:$H$35)/SUMPRODUCT((Indicators!$B$5:$B$35=G$4)*Indicators!$N$5:$N$35*('Indicator Scores'!$H$5:$H$35>0)),0) -> 3.4285714 | H36: =IFERROR(SUMPRODUCT((Indicators!$B$5:$B$35=H$4)*Indicators!$N$5:$N$35*'Indicator Scores'!$H$5:$H$35)/SUMPRODUCT((Indicators!$B$5:$B$35=H$4)*Indicators!$N$5:$N$35*('Indicator Scores'!$H$5:$H$35>0)),0) -> 1.625 | I36: =IFERROR(SUMPRODUCT((Indicators!$B$5:$B$35=I$4)*Indicators!$N$5:$N$35*'Indicator Scores'!$H$5:$H$35)/SUMPRODUCT((Indicators!$B$5:$B$35=I$4)*Indicators!$N$5:$N$35*('Indicator Scores'!$H$5:$H$35>0)),0) -> 3.6666667 | J36: =IFERROR(SUMPRODUCT((Indicators!$B$5:$B$35=J$4)*Indicators!$N$5:$N$35*'Indicator Scores'!$H$5:$H$35)/SUMPRODUCT((Indicators!$B$5:$B$35=J$4)*Indicators!$N$5:$N$35*('Indicator Scores'!$H$5:$H$35>0)),0) -> 1.8 | K36: =IFERROR(SUMPRODUCT(F36:J36,INDEX('Factor Weights'!$C$5:$G$11,MATCH(D36,'Factor Weights'!$A$5:$A$11,0),0))/SUMPRODUCT((F36:J36>0)*INDEX('Factor Weights'!$C$5:$G$11,MATCH(D36,'Factor Weights'!$A$5:$A$11,0),0)),0) -> 2.6469048 | L36: =MAX(F36:J36) -> 3.6666667 | M36: =IF(L36>=Config!$C$13,MAX(K36,Config!$C$14),K36) -> 2.6469048 | N36: =IF(Config!$C$12="Weighted average",K36,IF(Config!$C$12="Weighted with floor",M36,L36)) -> 2.6469048 | O36: =IF(N36<Config!$D$5,"",MATCH(N36,Config!$D$5:$D$9,1)) -> 3 | P36: =IF(O36="","No data",INDEX(Config!$B$5:$B$9,O36)) -> Medium | Q36: 0 | T36: =IF(O36="","",IF(AND(S36="Y",Q36<>0),MAX(1,MIN(5,O36+MAX(-Config!$C$27,MIN(Config!$C$27,Q36)))),O36)) -> 3 | U36: =IF(T36="","No data",INDEX(Config!$B$5:$B$9,T36)) -> Medium | V36: =IF(Q36=0,"None",IF(S36="Y","Applied","Pending HO approval")) -> None | W36: =SUMPRODUCT((Indicators!$N$5:$N$35>0)*('Indicator Data'!$H$5:$H$35<>""))/SUMPRODUCT(--(Indicators!$N$5:$N$35>0)) -> 1
A37: =Entities!$A$9 -> JO-LSG | B37: =INDEX(Entities!$B$5:$B$34,MATCH(A37,Entities!$A$5:$A$34,0)) -> Leasing subsidiary – Jordan | C37: =INDEX(Entities!$D$5:$D$34,MATCH(A37,Entities!$A$5:$A$34,0)) -> Jordan (home) | D37: FC-05 | E37: =INDEX('Risk Taxonomy'!$B$5:$B$24,MATCH(D37,'Risk Taxonomy'!$A$5:$A$24,0)) -> Bribery and corruption | F37: =IFERROR(SUMPRODUCT((Indicators!$B$5:$B$35=F$4)*Indicators!$O$5:$O$35*'Indicator Scores'!$H$5:$H$35)/SUMPRODUCT((Indicators!$B$5:$B$35=F$4)*Indicators!$O$5:$O$35*('Indicator Scores'!$H$5:$H$35>0)),0) -> 1.7777778 | G37: =IFERROR(SUMPRODUCT((Indicators!$B$5:$B$35=G$4)*Indicators!$O$5:$O$35*'Indicator Scores'!$H$5:$H$35)/SUMPRODUCT((Indicators!$B$5:$B$35=G$4)*Indicators!$O$5:$O$35*('Indicator Scores'!$H$5:$H$35>0)),0) -> 3.8 | H37: =IFERROR(SUMPRODUCT((Indicators!$B$5:$B$35=H$4)*Indicators!$O$5:$O$35*'Indicator Scores'!$H$5:$H$35)/SUMPRODUCT((Indicators!$B$5:$B$35=H$4)*Indicators!$O$5:$O$35*('Indicator Scores'!$H$5:$H$35>0)),0) -> 2 | I37: =IFERROR(SUMPRODUCT((Indicators!$B$5:$B$35=I$4)*Indicators!$O$5:$O$35*'Indicator Scores'!$H$5:$H$35)/SUMPRODUCT((Indicators!$B$5:$B$35=I$4)*Indicators!$O$5:$O$35*('Indicator Scores'!$H$5:$H$35>0)),0) -> 2.6 | J37: =IFERROR(SUMPRODUCT((Indicators!$B$5:$B$35=J$4)*Indicators!$O$5:$O$35*'Indicator Scores'!$H$5:$H$35)/SUMPRODUCT((Indicators!$B$5:$B$35=J$4)*Indicators!$O$5:$O$35*('Indicator Scores'!$H$5:$H$35>0)),0) -> 3 | K37: =IFERROR(SUMPRODUCT(F37:J37,INDEX('Factor Weights'!$C$5:$G$11,MATCH(D37,'Factor Weights'!$A$5:$A$11,0),0))/SUMPRODUCT((F37:J37>0)*INDEX('Factor Weights'!$C$5:$G$11,MATCH(D37,'Factor Weights'!$A$5:$A$11,0),0)),0) -> 2.6033333 | L37: =MAX(F37:J37) -> 3.8 | M37: =IF(L37>=Config!$C$13,MAX(K37,Config!$C$14),K37) -> 2.6033333 | N37: =IF(Config!$C$12="Weighted average",K37,IF(Config!$C$12="Weighted with floor",M37,L37)) -> 2.6033333 | O37: =IF(N37<Config!$D$5,"",MATCH(N37,Config!$D$5:$D$9,1)) -> 2 | P37: =IF(O37="","No data",INDEX(Config!$B$5:$B$9,O37)) -> Medium-Low | Q37: 0 | T37: =IF(O37="","",IF(AND(S37="Y",Q37<>0),MAX(1,MIN(5,O37+MAX(-Config!$C$27,MIN(Config!$C$27,Q37)))),O37)) -> 2 | U37: =IF(T37="","No data",INDEX(Config!$B$5:$B$9,T37)) -> Medium-Low | V37: =IF(Q37=0,"None",IF(S37="Y","Applied","Pending HO approval")) -> None | W37: =SUMPRODUCT((Indicators!$O$5:$O$35>0)*('Indicator Data'!$H$5:$H$35<>""))/SUMPRODUCT(--(Indicators!$O$5:$O$35>0)) -> 1
A38: =Entities!$A$9 -> JO-LSG | B38: =INDEX(Entities!$B$5:$B$34,MATCH(A38,Entities!$A$5:$A$34,0)) -> Leasing subsidiary – Jordan | C38: =INDEX(Entities!$D$5:$D$34,MATCH(A38,Entities!$A$5:$A$34,0)) -> Jordan (home) | D38: FC-06 | E38: =INDEX('Risk Taxonomy'!$B$5:$B$24,MATCH(D38,'Risk Taxonomy'!$A$5:$A$24,0)) -> Fraud | F38: =IFERROR(SUMPRODUCT((Indicators!$B$5:$B$35=F$4)*Indicators!$P$5:$P$35*'Indicator Scores'!$H$5:$H$35)/SUMPRODUCT((Indicators!$B$5:$B$35=F$4)*Indicators!$P$5:$P$35*('Indicator Scores'!$H$5:$H$35>0)),0) -> 4 | G38: =IFERROR(SUMPRODUCT((Indicators!$B$5:$B$35=G$4)*Indicators!$P$5:$P$35*'Indicator Scores'!$H$5:$H$35)/SUMPRODUCT((Indicators!$B$5:$B$35=G$4)*Indicators!$P$5:$P$35*('Indicator Scores'!$H$5:$H$35>0)),0) -> 3.25 | H38: =IFERROR(SUMPRODUCT((Indicators!$B$5:$B$35=H$4)*Indicators!$P$5:$P$35*'Indicator Scores'!$H$5:$H$35)/SUMPRODUCT((Indicators!$B$5:$B$35=H$4)*Indicators!$P$5:$P$35*('Indicator Scores'!$H$5:$H$35>0)),0) -> 2.2 | I38: =IFERROR(SUMPRODUCT((Indicators!$B$5:$B$35=I$4)*Indicators!$P$5:$P$35*'Indicator Scores'!$H$5:$H$35)/SUMPRODUCT((Indicators!$B$5:$B$35=I$4)*Indicators!$P$5:$P$35*('Indicator Scores'!$H$5:$H$35>0)),0) -> 2.7777778 | J38: =IFERROR(SUMPRODUCT((Indicators!$B$5:$B$35=J$4)*Indicators!$P$5:$P$35*'Indicator Scores'!$H$5:$H$35)/SUMPRODUCT((Indicators!$B$5:$B$35=J$4)*Indicators!$P$5:$P$35*('Indicator Scores'!$H$5:$H$35>0)),0) -> 3 | K38: =IFERROR(SUMPRODUCT(F38:J38,INDEX('Factor Weights'!$C$5:$G$11,MATCH(D38,'Factor Weights'!$A$5:$A$11,0),0))/SUMPRODUCT((F38:J38>0)*INDEX('Factor Weights'!$C$5:$G$11,MATCH(D38,'Factor Weights'!$A$5:$A$11,0),0)),0) -> 2.9983333 | L38: =MAX(F38:J38) -> 4 | M38: =IF(L38>=Config!$C$13,MAX(K38,Config!$C$14),K38) -> 2.9983333 | N38: =IF(Config!$C$12="Weighted average",K38,IF(Config!$C$12="Weighted with floor",M38,L38)) -> 2.9983333 | O38: =IF(N38<Config!$D$5,"",MATCH(N38,Config!$D$5:$D$9,1)) -> 3 | P38: =IF(O38="","No data",INDEX(Config!$B$5:$B$9,O38)) -> Medium | Q38: 0 | T38: =IF(O38="","",IF(AND(S38="Y",Q38<>0),MAX(1,MIN(5,O38+MAX(-Config!$C$27,MIN(Config!$C$27,Q38)))),O38)) -> 3 | U38: =IF(T38="","No data",INDEX(Config!$B$5:$B$9,T38)) -> Medium | V38: =IF(Q38=0,"None",IF(S38="Y","Applied","Pending HO approval")) -> None | W38: =SUMPRODUCT((Indicators!$P$5:$P$35>0)*('Indicator Data'!$H$5:$H$35<>""))/SUMPRODUCT(--(Indicators!$P$5:$P$35>0)) -> 1
A39: =Entities!$A$9 -> JO-LSG | B39: =INDEX(Entities!$B$5:$B$34,MATCH(A39,Entities!$A$5:$A$34,0)) -> Leasing subsidiary – Jordan | C39: =INDEX(Entities!$D$5:$D$34,MATCH(A39,Entities!$A$5:$A$34,0)) -> Jordan (home) | D39: FC-07 | E39: =INDEX('Risk Taxonomy'!$B$5:$B$24,MATCH(D39,'Risk Taxonomy'!$A$5:$A$24,0)) -> Tax evasion and tax transparency | F39: =IFERROR(SUMPRODUCT((Indicators!$B$5:$B$35=F$4)*Indicators!$Q$5:$Q$35*'Indicator Scores'!$H$5:$H$35)/SUMPRODUCT((Indicators!$B$5:$B$35=F$4)*Indicators!$Q$5:$Q$35*('Indicator Scores'!$H$5:$H$35>0)),0) -> 3 | G39: =IFERROR(SUMPRODUCT((Indicators!$B$5:$B$35=G$4)*Indicators!$Q$5:$Q$35*'Indicator Scores'!$H$5:$H$35)/SUMPRODUCT((Indicators!$B$5:$B$35=G$4)*Indicators!$Q$5:$Q$35*('Indicator Scores'!$H$5:$H$35>0)),0) -> 2.8333333 | H39: =IFERROR(SUMPRODUCT((Indicators!$B$5:$B$35=H$4)*Indicators!$Q$5:$Q$35*'Indicator Scores'!$H$5:$H$35)/SUMPRODUCT((Indicators!$B$5:$B$35=H$4)*Indicators!$Q$5:$Q$35*('Indicator Scores'!$H$5:$H$35>0)),0) -> 3 | I39: =IFERROR(SUMPRODUCT((Indicators!$B$5:$B$35=I$4)*Indicators!$Q$5:$Q$35*'Indicator Scores'!$H$5:$H$35)/SUMPRODUCT((Indicators!$B$5:$B$35=I$4)*Indicators!$Q$5:$Q$35*('Indicator Scores'!$H$5:$H$35>0)),0) -> 4 | J39: =IFERROR(SUMPRODUCT((Indicators!$B$5:$B$35=J$4)*Indicators!$Q$5:$Q$35*'Indicator Scores'!$H$5:$H$35)/SUMPRODUCT((Indicators!$B$5:$B$35=J$4)*Indicators!$Q$5:$Q$35*('Indicator Scores'!$H$5:$H$35>0)),0) -> 1.8 | K39: =IFERROR(SUMPRODUCT(F39:J39,INDEX('Factor Weights'!$C$5:$G$11,MATCH(D39,'Factor Weights'!$A$5:$A$11,0),0))/SUMPRODUCT((F39:J39>0)*INDEX('Factor Weights'!$C$5:$G$11,MATCH(D39,'Factor Weights'!$A$5:$A$11,0),0)),0) -> 2.9383333 | L39: =MAX(F39:J39) -> 4 | M39: =IF(L39>=Config!$C$13,MAX(K39,Config!$C$14),K39) -> 2.9383333 | N39: =IF(Config!$C$12="Weighted average",K39,IF(Config!$C$12="Weighted with floor",M39,L39)) -> 2.9383333 | O39: =IF(N39<Config!$D$5,"",MATCH(N39,Config!$D$5:$D$9,1)) -> 3 | P39: =IF(O39="","No data",INDEX(Config!$B$5:$B$9,O39)) -> Medium | Q39: 0 | T39: =IF(O39="","",IF(AND(S39="Y",Q39<>0),MAX(1,MIN(5,O39+MAX(-Config!$C$27,MIN(Config!$C$27,Q39)))),O39)) -> 3 | U39: =IF(T39="","No data",INDEX(Config!$B$5:$B$9,T39)) -> Medium | V39: =IF(Q39=0,"None",IF(S39="Y","Applied","Pending HO approval")) -> None | W39: =SUMPRODUCT((Indicators!$Q$5:$Q$35>0)*('Indicator Data'!$H$5:$H$35<>""))/SUMPRODUCT(--(Indicators!$Q$5:$Q$35>0)) -> 1
A40: =Entities!$A$10 -> PS | B40: =INDEX(Entities!$B$5:$B$34,MATCH(A40,Entities!$A$5:$A$34,0)) -> Arab Bank – Palestine | C40: =INDEX(Entities!$D$5:$D$34,MATCH(A40,Entities!$A$5:$A$34,0)) -> Levant | D40: FC-01 | E40: =INDEX('Risk Taxonomy'!$B$5:$B$24,MATCH(D40,'Risk Taxonomy'!$A$5:$A$24,0)) -> Money laundering | F40: =IFERROR(SUMPRODUCT((Indicators!$B$5:$B$35=F$4)*Indicators!$K$5:$K$35*'Indicator Scores'!$I$5:$I$35)/SUMPRODUCT((Indicators!$B$5:$B$35=F$4)*Indicators!$K$5:$K$35*('Indicator Scores'!$I$5:$I$35>0)),0) -> 3.3333333 | G40: =IFERROR(SUMPRODUCT((Indicators!$B$5:$B$35=G$4)*Indicators!$K$5:$K$35*'Indicator Scores'!$I$5:$I$35)/SUMPRODUCT((Indicators!$B$5:$B$35=G$4)*Indicators!$K$5:$K$35*('Indicator Scores'!$I$5:$I$35>0)),0) -> 4.3333333 | H40: =IFERROR(SUMPRODUCT((Indicators!$B$5:$B$35=H$4)*Indicators!$K$5:$K$35*'Indicator Scores'!$I$5:$I$35)/SUMPRODUCT((Indicators!$B$5:$B$35=H$4)*Indicators!$K$5:$K$35*('Indicator Scores'!$I$5:$I$35>0)),0) -> 4.4 | I40: =IFERROR(SUMPRODUCT((Indicators!$B$5:$B$35=I$4)*Indicators!$K$5:$K$35*'Indicator Scores'!$I$5:$I$35)/SUMPRODUCT((Indicators!$B$5:$B$35=I$4)*Indicators!$K$5:$K$35*('Indicator Scores'!$I$5:$I$35>0)),0) -> 3.8571429 | J40: =IFERROR(SUMPRODUCT((Indicators!$B$5:$B$35=J$4)*Indicators!$K$5:$K$35*'Indicator Scores'!$I$5:$I$35)/SUMPRODUCT((Indicators!$B$5:$B$35=J$4)*Indicators!$K$5:$K$35*('Indicator Scores'!$I$5:$I$35>0)),0) -> 4.4 | K40: =IFERROR(SUMPRODUCT(F40:J40,INDEX('Factor Weights'!$C$5:$G$11,MATCH(D40,'Factor Weights'!$A$5:$A$11,0),0))/SUMPRODUCT((F40:J40>0)*INDEX('Factor Weights'!$C$5:$G$11,MATCH(D40,'Factor Weights'!$A$5:$A$11,0),0)),0) -> 3.9819048 | L40: =MAX(F40:J40) -> 4.4 | M40: =IF(L40>=Config!$C$13,MAX(K40,Config!$C$14),K40) -> 3.9819048 | N40: =IF(Config!$C$12="Weighted average",K40,IF(Config!$C$12="Weighted with floor",M40,L40)) -> 3.9819048 | O40: =IF(N40<Config!$D$5,"",MATCH(N40,Config!$D$5:$D$9,1)) -> 4 | P40: =IF(O40="","No data",INDEX(Config!$B$5:$B$9,O40)) -> Medium-High | Q40: 0 | T40: =IF(O40="","",IF(AND(S40="Y",Q40<>0),MAX(1,MIN(5,O40+MAX(-Config!$C$27,MIN(Config!$C$27,Q40)))),O40)) -> 4 | U40: =IF(T40="","No data",INDEX(Config!$B$5:$B$9,T40)) -> Medium-High | V40: =IF(Q40=0,"None",IF(S40="Y","Applied","Pending HO approval")) -> None | W40: =SUMPRODUCT((Indicators!$K$5:$K$35>0)*('Indicator Data'!$I$5:$I$35<>""))/SUMPRODUCT(--(Indicators!$K$5:$K$35>0)) -> 1
A41: =Entities!$A$10 -> PS | B41: =INDEX(Entities!$B$5:$B$34,MATCH(A41,Entities!$A$5:$A$34,0)) -> Arab Bank – Palestine | C41: =INDEX(Entities!$D$5:$D$34,MATCH(A41,Entities!$A$5:$A$34,0)) -> Levant | D41: FC-02 | E41: =INDEX('Risk Taxonomy'!$B$5:$B$24,MATCH(D41,'Risk Taxonomy'!$A$5:$A$24,0)) -> Terrorist financing | F41: =IFERROR(SUMPRODUCT((Indicators!$B$5:$B$35=F$4)*Indicators!$L$5:$L$35*'Indicator Scores'!$I$5:$I$35)/SUMPRODUCT((Indicators!$B$5:$B$35=F$4)*Indicators!$L$5:$L$35*('Indicator Scores'!$I$5:$I$35>0)),0) -> 3 | G41: =IFERROR(SUMPRODUCT((Indicators!$B$5:$B$35=G$4)*Indicators!$L$5:$L$35*'Indicator Scores'!$I$5:$I$35)/SUMPRODUCT((Indicators!$B$5:$B$35=G$4)*Indicators!$L$5:$L$35*('Indicator Scores'!$I$5:$I$35>0)),0) -> 3.7777778 | H41: =IFERROR(SUMPRODUCT((Indicators!$B$5:$B$35=H$4)*Indicators!$L$5:$L$35*'Indicator Scores'!$I$5:$I$35)/SUMPRODUCT((Indicators!$B$5:$B$35=H$4)*Indicators!$L$5:$L$35*('Indicator Scores'!$I$5:$I$35>0)),0) -> 4.5 | I41: =IFERROR(SUMPRODUCT((Indicators!$B$5:$B$35=I$4)*Indicators!$L$5:$L$35*'Indicator Scores'!$I$5:$I$35)/SUMPRODUCT((Indicators!$B$5:$B$35=I$4)*Indicators!$L$5:$L$35*('Indicator Scores'!$I$5:$I$35>0)),0) -> 3.8333333 | J41: =IFERROR(SUMPRODUCT((Indicators!$B$5:$B$35=J$4)*Indicators!$L$5:$L$35*'Indicator Scores'!$I$5:$I$35)/SUMPRODUCT((Indicators!$B$5:$B$35=J$4)*Indicators!$L$5:$L$35*('Indicator Scores'!$I$5:$I$35>0)),0) -> 4.4285714 | K41: =IFERROR(SUMPRODUCT(F41:J41,INDEX('Factor Weights'!$C$5:$G$11,MATCH(D41,'Factor Weights'!$A$5:$A$11,0),0))/SUMPRODUCT((F41:J41>0)*INDEX('Factor Weights'!$C$5:$G$11,MATCH(D41,'Factor Weights'!$A$5:$A$11,0),0)),0) -> 3.827381 | L41: =MAX(F41:J41) -> 4.5 | M41: =IF(L41>=Config!$C$13,MAX(K41,Config!$C$14),K41) -> 3.827381 | N41: =IF(Config!$C$12="Weighted average",K41,IF(Config!$C$12="Weighted with floor",M41,L41)) -> 3.827381 | O41: =IF(N41<Config!$D$5,"",MATCH(N41,Config!$D$5:$D$9,1)) -> 4 | P41: =IF(O41="","No data",INDEX(Config!$B$5:$B$9,O41)) -> Medium-High | Q41: 0 | T41: =IF(O41="","",IF(AND(S41="Y",Q41<>0),MAX(1,MIN(5,O41+MAX(-Config!$C$27,MIN(Config!$C$27,Q41)))),O41)) -> 4 | U41: =IF(T41="","No data",INDEX(Config!$B$5:$B$9,T41)) -> Medium-High | V41: =IF(Q41=0,"None",IF(S41="Y","Applied","Pending HO approval")) -> None | W41: =SUMPRODUCT((Indicators!$L$5:$L$35>0)*('Indicator Data'!$I$5:$I$35<>""))/SUMPRODUCT(--(Indicators!$L$5:$L$35>0)) -> 1
A42: =Entities!$A$10 -> PS | B42: =INDEX(Entities!$B$5:$B$34,MATCH(A42,Entities!$A$5:$A$34,0)) -> Arab Bank – Palestine | C42: =INDEX(Entities!$D$5:$D$34,MATCH(A42,Entities!$A$5:$A$34,0)) -> Levant | D42: FC-03 | E42: =INDEX('Risk Taxonomy'!$B$5:$B$24,MATCH(D42,'Risk Taxonomy'!$A$5:$A$24,0)) -> Proliferation financing | F42: =IFERROR(SUMPRODUCT((Indicators!$B$5:$B$35=F$4)*Indicators!$M$5:$M$35*'Indicator Scores'!$I$5:$I$35)/SUMPRODUCT((Indicators!$B$5:$B$35=F$4)*Indicators!$M$5:$M$35*('Indicator Scores'!$I$5:$I$35>0)),0) -> 3.25 | G42: =IFERROR(SUMPRODUCT((Indicators!$B$5:$B$35=G$4)*Indicators!$M$5:$M$35*'Indicator Scores'!$I$5:$I$35)/SUMPRODUCT((Indicators!$B$5:$B$35=G$4)*Indicators!$M$5:$M$35*('Indicator Scores'!$I$5:$I$35>0)),0) -> 4.5 | H42: =IFERROR(SUMPRODUCT((Indicators!$B$5:$B$35=H$4)*Indicators!$M$5:$M$35*'Indicator Scores'!$I$5:$I$35)/SUMPRODUCT((Indicators!$B$5:$B$35=H$4)*Indicators!$M$5:$M$35*('Indicator Scores'!$I$5:$I$35>0)),0) -> 4.3333333 | I42: =IFERROR(SUMPRODUCT((Indicators!$B$5:$B$35=I$4)*Indicators!$M$5:$M$35*'Indicator Scores'!$I$5:$I$35)/SUMPRODUCT((Indicators!$B$5:$B$35=I$4)*Indicators!$M$5:$M$35*('Indicator Scores'!$I$5:$I$35>0)),0) -> 3.3333333 | J42: =IFERROR(SUMPRODUCT((Indicators!$B$5:$B$35=J$4)*Indicators!$M$5:$M$35*'Indicator Scores'!$I$5:$I$35)/SUMPRODUCT((Indicators!$B$5:$B$35=J$4)*Indicators!$M$5:$M$35*('Indicator Scores'!$I$5:$I$35>0)),0) -> 4 | K42: =IFERROR(SUMPRODUCT(F42:J42,INDEX('Factor Weights'!$C$5:$G$11,MATCH(D42,'Factor Weights'!$A$5:$A$11,0),0))/SUMPRODUCT((F42:J42>0)*INDEX('Factor Weights'!$C$5:$G$11,MATCH(D42,'Factor Weights'!$A$5:$A$11,0),0)),0) -> 4.1041667 | L42: =MAX(F42:J42) -> 4.5 | M42: =IF(L42>=Config!$C$13,MAX(K42,Config!$C$14),K42) -> 4.1041667 | N42: =IF(Config!$C$12="Weighted average",K42,IF(Config!$C$12="Weighted with floor",M42,L42)) -> 4.1041667 | O42: =IF(N42<Config!$D$5,"",MATCH(N42,Config!$D$5:$D$9,1)) -> 4 | P42: =IF(O42="","No data",INDEX(Config!$B$5:$B$9,O42)) -> Medium-High | Q42: 0 | T42: =IF(O42="","",IF(AND(S42="Y",Q42<>0),MAX(1,MIN(5,O42+MAX(-Config!$C$27,MIN(Config!$C$27,Q42)))),O42)) -> 4 | U42: =IF(T42="","No data",INDEX(Config!$B$5:$B$9,T42)) -> Medium-High | V42: =IF(Q42=0,"None",IF(S42="Y","Applied","Pending HO approval")) -> None | W42: =SUMPRODUCT((Indicators!$M$5:$M$35>0)*('Indicator Data'!$I$5:$I$35<>""))/SUMPRODUCT(--(Indicators!$M$5:$M$35>0)) -> 1
A43: =Entities!$A$10 -> PS | B43: =INDEX(Entities!$B$5:$B$34,MATCH(A43,Entities!$A$5:$A$34,0)) -> Arab Bank – Palestine | C43: =INDEX(Entities!$D$5:$D$34,MATCH(A43,Entities!$A$5:$A$34,0)) -> Levant | D43: FC-04 | E43: =INDEX('Risk Taxonomy'!$B$5:$B$24,MATCH(D43,'Risk Taxonomy'!$A$5:$A$24,0)) -> Sanctions | F43: =IFERROR(SUMPRODUCT((Indicators!$B$5:$B$35=F$4)*Indicators!$N$5:$N$35*'Indicator Scores'!$I$5:$I$35)/SUMPRODUCT((Indicators!$B$5:$B$35=F$4)*Indicators!$N$5:$N$35*('Indicator Scores'!$I$5:$I$35>0)),0) -> 3.4285714 | G43: =IFERROR(SUMPRODUCT((Indicators!$B$5:$B$35=G$4)*Indicators!$N$5:$N$35*'Indicator Scores'!$I$5:$I$35)/SUMPRODUCT((Indicators!$B$5:$B$35=G$4)*Indicators!$N$5:$N$35*('Indicator Scores'!$I$5:$I$35>0)),0) -> 4.4285714 | H43: =IFERROR(SUMPRODUCT((Indicators!$B$5:$B$35=H$4)*Indicators!$N$5:$N$35*'Indicator Scores'!$I$5:$I$35)/SUMPRODUCT((Indicators!$B$5:$B$35=H$4)*Indicators!$N$5:$N$35*('Indicator Scores'!$I$5:$I$35>0)),0) -> 4.375 | I43: =IFERROR(SUMPRODUCT((Indicators!$B$5:$B$35=I$4)*Indicators!$N$5:$N$35*'Indicator Scores'!$I$5:$I$35)/SUMPRODUCT((Indicators!$B$5:$B$35=I$4)*Indicators!$N$5:$N$35*('Indicator Scores'!$I$5:$I$35>0)),0) -> 3.6666667 | J43: =IFERROR(SUMPRODUCT((Indicators!$B$5:$B$35=J$4)*Indicators!$N$5:$N$35*'Indicator Scores'!$I$5:$I$35)/SUMPRODUCT((Indicators!$B$5:$B$35=J$4)*Indicators!$N$5:$N$35*('Indicator Scores'!$I$5:$I$35>0)),0) -> 4 | K43: =IFERROR(SUMPRODUCT(F43:J43,INDEX('Factor Weights'!$C$5:$G$11,MATCH(D43,'Factor Weights'!$A$5:$A$11,0),0))/SUMPRODUCT((F43:J43>0)*INDEX('Factor Weights'!$C$5:$G$11,MATCH(D43,'Factor Weights'!$A$5:$A$11,0),0)),0) -> 4.1440476 | L43: =MAX(F43:J43) -> 4.4285714 | M43: =IF(L43>=Config!$C$13,MAX(K43,Config!$C$14),K43) -> 4.1440476 | N43: =IF(Config!$C$12="Weighted average",K43,IF(Config!$C$12="Weighted with floor",M43,L43)) -> 4.1440476 | O43: =IF(N43<Config!$D$5,"",MATCH(N43,Config!$D$5:$D$9,1)) -> 4 | P43: =IF(O43="","No data",INDEX(Config!$B$5:$B$9,O43)) -> Medium-High | Q43: 0 | T43: =IF(O43="","",IF(AND(S43="Y",Q43<>0),MAX(1,MIN(5,O43+MAX(-Config!$C$27,MIN(Config!$C$27,Q43)))),O43)) -> 4 | U43: =IF(T43="","No data",INDEX(Config!$B$5:$B$9,T43)) -> Medium-High | V43: =IF(Q43=0,"None",IF(S43="Y","Applied","Pending HO approval")) -> None | W43: =SUMPRODUCT((Indicators!$N$5:$N$35>0)*('Indicator Data'!$I$5:$I$35<>""))/SUMPRODUCT(--(Indicators!$N$5:$N$35>0)) -> 1
A44: =Entities!$A$10 -> PS | B44: =INDEX(Entities!$B$5:$B$34,MATCH(A44,Entities!$A$5:$A$34,0)) -> Arab Bank – Palestine | C44: =INDEX(Entities!$D$5:$D$34,MATCH(A44,Entities!$A$5:$A$34,0)) -> Levant | D44: FC-05 | E44: =INDEX('Risk Taxonomy'!$B$5:$B$24,MATCH(D44,'Risk Taxonomy'!$A$5:$A$24,0)) -> Bribery and corruption | F44: =IFERROR(SUMPRODUCT((Indicators!$B$5:$B$35=F$4)*Indicators!$O$5:$O$35*'Indicator Scores'!$I$5:$I$35)/SUMPRODUCT((Indicators!$B$5:$B$35=F$4)*Indicators!$O$5:$O$35*('Indicator Scores'!$I$5:$I$35>0)),0) -> 3.6666667 | G44: =IFERROR(SUMPRODUCT((Indicators!$B$5:$B$35=G$4)*Indicators!$O$5:$O$35*'Indicator Scores'!$I$5:$I$35)/SUMPRODUCT((Indicators!$B$5:$B$35=G$4)*Indicators!$O$5:$O$35*('Indicator Scores'!$I$5:$I$35>0)),0) -> 4.2 | H44: =IFERROR(SUMPRODUCT((Indicators!$B$5:$B$35=H$4)*Indicators!$O$5:$O$35*'Indicator Scores'!$I$5:$I$35)/SUMPRODUCT((Indicators!$B$5:$B$35=H$4)*Indicators!$O$5:$O$35*('Indicator Scores'!$I$5:$I$35>0)),0) -> 4 | I44: =IFERROR(SUMPRODUCT((Indicators!$B$5:$B$35=I$4)*Indicators!$O$5:$O$35*'Indicator Scores'!$I$5:$I$35)/SUMPRODUCT((Indicators!$B$5:$B$35=I$4)*Indicators!$O$5:$O$35*('Indicator Scores'!$I$5:$I$35>0)),0) -> 4.2 | J44: =IFERROR(SUMPRODUCT((Indicators!$B$5:$B$35=J$4)*Indicators!$O$5:$O$35*'Indicator Scores'!$I$5:$I$35)/SUMPRODUCT((Indicators!$B$5:$B$35=J$4)*Indicators!$O$5:$O$35*('Indicator Scores'!$I$5:$I$35>0)),0) -> 4 | K44: =IFERROR(SUMPRODUCT(F44:J44,INDEX('Factor Weights'!$C$5:$G$11,MATCH(D44,'Factor Weights'!$A$5:$A$11,0),0))/SUMPRODUCT((F44:J44>0)*INDEX('Factor Weights'!$C$5:$G$11,MATCH(D44,'Factor Weights'!$A$5:$A$11,0),0)),0) -> 3.99 | L44: =MAX(F44:J44) -> 4.2 | M44: =IF(L44>=Config!$C$13,MAX(K44,Config!$C$14),K44) -> 3.99 | N44: =IF(Config!$C$12="Weighted average",K44,IF(Config!$C$12="Weighted with floor",M44,L44)) -> 3.99 | O44: =IF(N44<Config!$D$5,"",MATCH(N44,Config!$D$5:$D$9,1)) -> 4 | P44: =IF(O44="","No data",INDEX(Config!$B$5:$B$9,O44)) -> Medium-High | Q44: 0 | T44: =IF(O44="","",IF(AND(S44="Y",Q44<>0),MAX(1,MIN(5,O44+MAX(-Config!$C$27,MIN(Config!$C$27,Q44)))),O44)) -> 4 | U44: =IF(T44="","No data",INDEX(Config!$B$5:$B$9,T44)) -> Medium-High | V44: =IF(Q44=0,"None",IF(S44="Y","Applied","Pending HO approval")) -> None | W44: =SUMPRODUCT((Indicators!$O$5:$O$35>0)*('Indicator Data'!$I$5:$I$35<>""))/SUMPRODUCT(--(Indicators!$O$5:$O$35>0)) -> 1
A45: =Entities!$A$10 -> PS | B45: =INDEX(Entities!$B$5:$B$34,MATCH(A45,Entities!$A$5:$A$34,0)) -> Arab Bank – Palestine | C45: =INDEX(Entities!$D$5:$D$34,MATCH(A45,Entities!$A$5:$A$34,0)) -> Levant | D45: FC-06 | E45: =INDEX('Risk Taxonomy'!$B$5:$B$24,MATCH(D45,'Risk Taxonomy'!$A$5:$A$24,0)) -> Fraud | F45: =IFERROR(SUMPRODUCT((Indicators!$B$5:$B$35=F$4)*Indicators!$P$5:$P$35*'Indicator Scores'!$I$5:$I$35)/SUMPRODUCT((Indicators!$B$5:$B$35=F$4)*Indicators!$P$5:$P$35*('Indicator Scores'!$I$5:$I$35>0)),0) -> 3.3333333 | G45: =IFERROR(SUMPRODUCT((Indicators!$B$5:$B$35=G$4)*Indicators!$P$5:$P$35*'Indicator Scores'!$I$5:$I$35)/SUMPRODUCT((Indicators!$B$5:$B$35=G$4)*Indicators!$P$5:$P$35*('Indicator Scores'!$I$5:$I$35>0)),0) -> 3.75 | H45: =IFERROR(SUMPRODUCT((Indicators!$B$5:$B$35=H$4)*Indicators!$P$5:$P$35*'Indicator Scores'!$I$5:$I$35)/SUMPRODUCT((Indicators!$B$5:$B$35=H$4)*Indicators!$P$5:$P$35*('Indicator Scores'!$I$5:$I$35>0)),0) -> 4.4 | I45: =IFERROR(SUMPRODUCT((Indicators!$B$5:$B$35=I$4)*Indicators!$P$5:$P$35*'Indicator Scores'!$I$5:$I$35)/SUMPRODUCT((Indicators!$B$5:$B$35=I$4)*Indicators!$P$5:$P$35*('Indicator Scores'!$I$5:$I$35>0)),0) -> 4.1111111 | J45: =IFERROR(SUMPRODUCT((Indicators!$B$5:$B$35=J$4)*Indicators!$P$5:$P$35*'Indicator Scores'!$I$5:$I$35)/SUMPRODUCT((Indicators!$B$5:$B$35=J$4)*Indicators!$P$5:$P$35*('Indicator Scores'!$I$5:$I$35>0)),0) -> 4.6 | K45: =IFERROR(SUMPRODUCT(F45:J45,INDEX('Factor Weights'!$C$5:$G$11,MATCH(D45,'Factor Weights'!$A$5:$A$11,0),0))/SUMPRODUCT((F45:J45>0)*INDEX('Factor Weights'!$C$5:$G$11,MATCH(D45,'Factor Weights'!$A$5:$A$11,0),0)),0) -> 4.075 | L45: =MAX(F45:J45) -> 4.6 | M45: =IF(L45>=Config!$C$13,MAX(K45,Config!$C$14),K45) -> 4.075 | N45: =IF(Config!$C$12="Weighted average",K45,IF(Config!$C$12="Weighted with floor",M45,L45)) -> 4.075 | O45: =IF(N45<Config!$D$5,"",MATCH(N45,Config!$D$5:$D$9,1)) -> 4 | P45: =IF(O45="","No data",INDEX(Config!$B$5:$B$9,O45)) -> Medium-High | Q45: 0 | T45: =IF(O45="","",IF(AND(S45="Y",Q45<>0),MAX(1,MIN(5,O45+MAX(-Config!$C$27,MIN(Config!$C$27,Q45)))),O45)) -> 4 | U45: =IF(T45="","No data",INDEX(Config!$B$5:$B$9,T45)) -> Medium-High | V45: =IF(Q45=0,"None",IF(S45="Y","Applied","Pending HO approval")) -> None | W45: =SUMPRODUCT((Indicators!$P$5:$P$35>0)*('Indicator Data'!$I$5:$I$35<>""))/SUMPRODUCT(--(Indicators!$P$5:$P$35>0)) -> 1
A46: =Entities!$A$10 -> PS | B46: =INDEX(Entities!$B$5:$B$34,MATCH(A46,Entities!$A$5:$A$34,0)) -> Arab Bank – Palestine | C46: =INDEX(Entities!$D$5:$D$34,MATCH(A46,Entities!$A$5:$A$34,0)) -> Levant | D46: FC-07 | E46: =INDEX('Risk Taxonomy'!$B$5:$B$24,MATCH(D46,'Risk Taxonomy'!$A$5:$A$24,0)) -> Tax evasion and tax transparency | F46: =IFERROR(SUMPRODUCT((Indicators!$B$5:$B$35=F$4)*Indicators!$Q$5:$Q$35*'Indicator Scores'!$I$5:$I$35)/SUMPRODUCT((Indicators!$B$5:$B$35=F$4)*Indicators!$Q$5:$Q$35*('Indicator Scores'!$I$5:$I$35>0)),0) -> 3.2222222 | G46: =IFERROR(SUMPRODUCT((Indicators!$B$5:$B$35=G$4)*Indicators!$Q$5:$Q$35*'Indicator Scores'!$I$5:$I$35)/SUMPRODUCT((Indicators!$B$5:$B$35=G$4)*Indicators!$Q$5:$Q$35*('Indicator Scores'!$I$5:$I$35>0)),0) -> 4.6666667 | H46: =IFERROR(SUMPRODUCT((Indicators!$B$5:$B$35=H$4)*Indicators!$Q$5:$Q$35*'Indicator Scores'!$I$5:$I$35)/SUMPRODUCT((Indicators!$B$5:$B$35=H$4)*Indicators!$Q$5:$Q$35*('Indicator Scores'!$I$5:$I$35>0)),0) -> 4.5 | I46: =IFERROR(SUMPRODUCT((Indicators!$B$5:$B$35=I$4)*Indicators!$Q$5:$Q$35*'Indicator Scores'!$I$5:$I$35)/SUMPRODUCT((Indicators!$B$5:$B$35=I$4)*Indicators!$Q$5:$Q$35*('Indicator Scores'!$I$5:$I$35>0)),0) -> 3.5 | J46: =IFERROR(SUMPRODUCT((Indicators!$B$5:$B$35=J$4)*Indicators!$Q$5:$Q$35*'Indicator Scores'!$I$5:$I$35)/SUMPRODUCT((Indicators!$B$5:$B$35=J$4)*Indicators!$Q$5:$Q$35*('Indicator Scores'!$I$5:$I$35>0)),0) -> 4 | K46: =IFERROR(SUMPRODUCT(F46:J46,INDEX('Factor Weights'!$C$5:$G$11,MATCH(D46,'Factor Weights'!$A$5:$A$11,0),0))/SUMPRODUCT((F46:J46>0)*INDEX('Factor Weights'!$C$5:$G$11,MATCH(D46,'Factor Weights'!$A$5:$A$11,0),0)),0) -> 3.9444444 | L46: =MAX(F46:J46) -> 4.6666667 | M46: =IF(L46>=Config!$C$13,MAX(K46,Config!$C$14),K46) -> 3.9444444 | N46: =IF(Config!$C$12="Weighted average",K46,IF(Config!$C$12="Weighted with floor",M46,L46)) -> 3.9444444 | O46: =IF(N46<Config!$D$5,"",MATCH(N46,Config!$D$5:$D$9,1)) -> 4 | P46: =IF(O46="","No data",INDEX(Config!$B$5:$B$9,O46)) -> Medium-High | Q46: 0 | T46: =IF(O46="","",IF(AND(S46="Y",Q46<>0),MAX(1,MIN(5,O46+MAX(-Config!$C$27,MIN(Config!$C$27,Q46)))),O46)) -> 4 | U46: =IF(T46="","No data",INDEX(Config!$B$5:$B$9,T46)) -> Medium-High | V46: =IF(Q46=0,"None",IF(S46="Y","Applied","Pending HO approval")) -> None | W46: =SUMPRODUCT((Indicators!$Q$5:$Q$35>0)*('Indicator Data'!$I$5:$I$35<>""))/SUMPRODUCT(--(Indicators!$Q$5:$Q$35>0)) -> 1
A47: =Entities!$A$11 -> PS-INV | B47: =INDEX(Entities!$B$5:$B$34,MATCH(A47,Entities!$A$5:$A$34,0)) -> Al-Arabi Investment Group – Palestine | C47: =INDEX(Entities!$D$5:$D$34,MATCH(A47,Entities!$A$5:$A$34,0)) -> Levant | D47: FC-01 | E47: =INDEX('Risk Taxonomy'!$B$5:$B$24,MATCH(D47,'Risk Taxonomy'!$A$5:$A$24,0)) -> Money laundering | F47: =IFERROR(SUMPRODUCT((Indicators!$B$5:$B$35=F$4)*Indicators!$K$5:$K$35*'Indicator Scores'!$J$5:$J$35)/SUMPRODUCT((Indicators!$B$5:$B$35=F$4)*Indicators!$K$5:$K$35*('Indicator Scores'!$J$5:$J$35>0)),0) -> 3.6666667 | G47: =IFERROR(SUMPRODUCT((Indicators!$B$5:$B$35=G$4)*Indicators!$K$5:$K$35*'Indicator Scores'!$J$5:$J$35)/SUMPRODUCT((Indicators!$B$5:$B$35=G$4)*Indicators!$K$5:$K$35*('Indicator Scores'!$J$5:$J$35>0)),0) -> 4.4444444 | H47: =IFERROR(SUMPRODUCT((Indicators!$B$5:$B$35=H$4)*Indicators!$K$5:$K$35*'Indicator Scores'!$J$5:$J$35)/SUMPRODUCT((Indicators!$B$5:$B$35=H$4)*Indicators!$K$5:$K$35*('Indicator Scores'!$J$5:$J$35>0)),0) -> 2.4 | I47: =IFERROR(SUMPRODUCT((Indicators!$B$5:$B$35=I$4)*Indicators!$K$5:$K$35*'Indicator Scores'!$J$5:$J$35)/SUMPRODUCT((Indicators!$B$5:$B$35=I$4)*Indicators!$K$5:$K$35*('Indicator Scores'!$J$5:$J$35>0)),0) -> 3 | J47: =IFERROR(SUMPRODUCT((Indicators!$B$5:$B$35=J$4)*Indicators!$K$5:$K$35*'Indicator Scores'!$J$5:$J$35)/SUMPRODUCT((Indicators!$B$5:$B$35=J$4)*Indicators!$K$5:$K$35*('Indicator Scores'!$J$5:$J$35>0)),0) -> 2.8 | K47: =IFERROR(SUMPRODUCT(F47:J47,INDEX('Factor Weights'!$C$5:$G$11,MATCH(D47,'Factor Weights'!$A$5:$A$11,0),0))/SUMPRODUCT((F47:J47>0)*INDEX('Factor Weights'!$C$5:$G$11,MATCH(D47,'Factor Weights'!$A$5:$A$11,0),0)),0) -> 3.4211111 | L47: =MAX(F47:J47) -> 4.4444444 | M47: =IF(L47>=Config!$C$13,MAX(K47,Config!$C$14),K47) -> 3.4211111 | N47: =IF(Config!$C$12="Weighted average",K47,IF(Config!$C$12="Weighted with floor",M47,L47)) -> 3.4211111 | O47: =IF(N47<Config!$D$5,"",MATCH(N47,Config!$D$5:$D$9,1)) -> 4 | P47: =IF(O47="","No data",INDEX(Config!$B$5:$B$9,O47)) -> Medium-High | Q47: 0 | T47: =IF(O47="","",IF(AND(S47="Y",Q47<>0),MAX(1,MIN(5,O47+MAX(-Config!$C$27,MIN(Config!$C$27,Q47)))),O47)) -> 4 | U47: =IF(T47="","No data",INDEX(Config!$B$5:$B$9,T47)) -> Medium-High | V47: =IF(Q47=0,"None",IF(S47="Y","Applied","Pending HO approval")) -> None | W47: =SUMPRODUCT((Indicators!$K$5:$K$35>0)*('Indicator Data'!$J$5:$J$35<>""))/SUMPRODUCT(--(Indicators!$K$5:$K$35>0)) -> 1
A48: =Entities!$A$11 -> PS-INV | B48: =INDEX(Entities!$B$5:$B$34,MATCH(A48,Entities!$A$5:$A$34,0)) -> Al-Arabi Investment Group – Palestine | C48: =INDEX(Entities!$D$5:$D$34,MATCH(A48,Entities!$A$5:$A$34,0)) -> Levant | D48: FC-02 | E48: =INDEX('Risk Taxonomy'!$B$5:$B$24,MATCH(D48,'Risk Taxonomy'!$A$5:$A$24,0)) -> Terrorist financing | F48: =IFERROR(SUMPRODUCT((Indicators!$B$5:$B$35=F$4)*Indicators!$L$5:$L$35*'Indicator Scores'!$J$5:$J$35)/SUMPRODUCT((Indicators!$B$5:$B$35=F$4)*Indicators!$L$5:$L$35*('Indicator Scores'!$J$5:$J$35>0)),0) -> 3 | G48: =IFERROR(SUMPRODUCT((Indicators!$B$5:$B$35=G$4)*Indicators!$L$5:$L$35*'Indicator Scores'!$J$5:$J$35)/SUMPRODUCT((Indicators!$B$5:$B$35=G$4)*Indicators!$L$5:$L$35*('Indicator Scores'!$J$5:$J$35>0)),0) -> 4.5555556 | H48: =IFERROR(SUMPRODUCT((Indicators!$B$5:$B$35=H$4)*Indicators!$L$5:$L$35*'Indicator Scores'!$J$5:$J$35)/SUMPRODUCT((Indicators!$B$5:$B$35=H$4)*Indicators!$L$5:$L$35*('Indicator Scores'!$J$5:$J$35>0)),0) -> 1.6666667 | I48: =IFERROR(SUMPRODUCT((Indicators!$B$5:$B$35=I$4)*Indicators!$L$5:$L$35*'Indicator Scores'!$J$5:$J$35)/SUMPRODUCT((Indicators!$B$5:$B$35=I$4)*Indicators!$L$5:$L$35*('Indicator Scores'!$J$5:$J$35>0)),0) -> 3 | J48: =IFERROR(SUMPRODUCT((Indicators!$B$5:$B$35=J$4)*Indicators!$L$5:$L$35*'Indicator Scores'!$J$5:$J$35)/SUMPRODUCT((Indicators!$B$5:$B$35=J$4)*Indicators!$L$5:$L$35*('Indicator Scores'!$J$5:$J$35>0)),0) -> 2.7142857 | K48: =IFERROR(SUMPRODUCT(F48:J48,INDEX('Factor Weights'!$C$5:$G$11,MATCH(D48,'Factor Weights'!$A$5:$A$11,0),0))/SUMPRODUCT((F48:J48>0)*INDEX('Factor Weights'!$C$5:$G$11,MATCH(D48,'Factor Weights'!$A$5:$A$11,0),0)),0) -> 3.2095238 | L48: =MAX(F48:J48) -> 4.5555556 | M48: =IF(L48>=Config!$C$13,MAX(K48,Config!$C$14),K48) -> 3.2095238 | N48: =IF(Config!$C$12="Weighted average",K48,IF(Config!$C$12="Weighted with floor",M48,L48)) -> 3.2095238 | O48: =IF(N48<Config!$D$5,"",MATCH(N48,Config!$D$5:$D$9,1)) -> 3 | P48: =IF(O48="","No data",INDEX(Config!$B$5:$B$9,O48)) -> Medium | Q48: 0 | T48: =IF(O48="","",IF(AND(S48="Y",Q48<>0),MAX(1,MIN(5,O48+MAX(-Config!$C$27,MIN(Config!$C$27,Q48)))),O48)) -> 3 | U48: =IF(T48="","No data",INDEX(Config!$B$5:$B$9,T48)) -> Medium | V48: =IF(Q48=0,"None",IF(S48="Y","Applied","Pending HO approval")) -> None | W48: =SUMPRODUCT((Indicators!$L$5:$L$35>0)*('Indicator Data'!$J$5:$J$35<>""))/SUMPRODUCT(--(Indicators!$L$5:$L$35>0)) -> 1
A49: =Entities!$A$11 -> PS-INV | B49: =INDEX(Entities!$B$5:$B$34,MATCH(A49,Entities!$A$5:$A$34,0)) -> Al-Arabi Investment Group – Palestine | C49: =INDEX(Entities!$D$5:$D$34,MATCH(A49,Entities!$A$5:$A$34,0)) -> Levant | D49: FC-03 | E49: =INDEX('Risk Taxonomy'!$B$5:$B$24,MATCH(D49,'Risk Taxonomy'!$A$5:$A$24,0)) -> Proliferation financing | F49: =IFERROR(SUMPRODUCT((Indicators!$B$5:$B$35=F$4)*Indicators!$M$5:$M$35*'Indicator Scores'!$J$5:$J$35)/SUMPRODUCT((Indicators!$B$5:$B$35=F$4)*Indicators!$M$5:$M$35*('Indicator Scores'!$J$5:$J$35>0)),0) -> 3.25 | G49: =IFERROR(SUMPRODUCT((Indicators!$B$5:$B$35=G$4)*Indicators!$M$5:$M$35*'Indicator Scores'!$J$5:$J$35)/SUMPRODUCT((Indicators!$B$5:$B$35=G$4)*Indicators!$M$5:$M$35*('Indicator Scores'!$J$5:$J$35>0)),0) -> 4.25 | H49: =IFERROR(SUMPRODUCT((Indicators!$B$5:$B$35=H$4)*Indicators!$M$5:$M$35*'Indicator Scores'!$J$5:$J$35)/SUMPRODUCT((Indicators!$B$5:$B$35=H$4)*Indicators!$M$5:$M$35*('Indicator Scores'!$J$5:$J$35>0)),0) -> 1.4444444 | I49: =IFERROR(SUMPRODUCT((Indicators!$B$5:$B$35=I$4)*Indicators!$M$5:$M$35*'Indicator Scores'!$J$5:$J$35)/SUMPRODUCT((Indicators!$B$5:$B$35=I$4)*Indicators!$M$5:$M$35*('Indicator Scores'!$J$5:$J$35>0)),0) -> 3 | J49: =IFERROR(SUMPRODUCT((Indicators!$B$5:$B$35=J$4)*Indicators!$M$5:$M$35*'Indicator Scores'!$J$5:$J$35)/SUMPRODUCT((Indicators!$B$5:$B$35=J$4)*Indicators!$M$5:$M$35*('Indicator Scores'!$J$5:$J$35>0)),0) -> 2 | K49: =IFERROR(SUMPRODUCT(F49:J49,INDEX('Factor Weights'!$C$5:$G$11,MATCH(D49,'Factor Weights'!$A$5:$A$11,0),0))/SUMPRODUCT((F49:J49>0)*INDEX('Factor Weights'!$C$5:$G$11,MATCH(D49,'Factor Weights'!$A$5:$A$11,0),0)),0) -> 2.7458333 | L49: =MAX(F49:J49) -> 4.25 | M49: =IF(L49>=Config!$C$13,MAX(K49,Config!$C$14),K49) -> 2.7458333 | N49: =IF(Config!$C$12="Weighted average",K49,IF(Config!$C$12="Weighted with floor",M49,L49)) -> 2.7458333 | O49: =IF(N49<Config!$D$5,"",MATCH(N49,Config!$D$5:$D$9,1)) -> 3 | P49: =IF(O49="","No data",INDEX(Config!$B$5:$B$9,O49)) -> Medium | Q49: 0 | T49: =IF(O49="","",IF(AND(S49="Y",Q49<>0),MAX(1,MIN(5,O49+MAX(-Config!$C$27,MIN(Config!$C$27,Q49)))),O49)) -> 3 | U49: =IF(T49="","No data",INDEX(Config!$B$5:$B$9,T49)) -> Medium | V49: =IF(Q49=0,"None",IF(S49="Y","Applied","Pending HO approval")) -> None | W49: =SUMPRODUCT((Indicators!$M$5:$M$35>0)*('Indicator Data'!$J$5:$J$35<>""))/SUMPRODUCT(--(Indicators!$M$5:$M$35>0)) -> 1
A50: =Entities!$A$11 -> PS-INV | B50: =INDEX(Entities!$B$5:$B$34,MATCH(A50,Entities!$A$5:$A$34,0)) -> Al-Arabi Investment Group – Palestine | C50: =INDEX(Entities!$D$5:$D$34,MATCH(A50,Entities!$A$5:$A$34,0)) -> Levant | D50: FC-04 | E50: =INDEX('Risk Taxonomy'!$B$5:$B$24,MATCH(D50,'Risk Taxonomy'!$A$5:$A$24,0)) -> Sanctions | F50: =IFERROR(SUMPRODUCT((Indicators!$B$5:$B$35=F$4)*Indicators!$N$5:$N$35*'Indicator Scores'!$J$5:$J$35)/SUMPRODUCT((Indicators!$B$5:$B$35=F$4)*Indicators!$N$5:$N$35*('Indicator Scores'!$J$5:$J$35>0)),0) -> 3.5714286 | G50: =IFERROR(SUMPRODUCT((Indicators!$B$5:$B$35=G$4)*Indicators!$N$5:$N$35*'Indicator Scores'!$J$5:$J$35)/SUMPRODUCT((Indicators!$B$5:$B$35=G$4)*Indicators!$N$5:$N$35*('Indicator Scores'!$J$5:$J$35>0)),0) -> 4.2857143 | H50: =IFERROR(SUMPRODUCT((Indicators!$B$5:$B$35=H$4)*Indicators!$N$5:$N$35*'Indicator Scores'!$J$5:$J$35)/SUMPRODUCT((Indicators!$B$5:$B$35=H$4)*Indicators!$N$5:$N$35*('Indicator Scores'!$J$5:$J$35>0)),0) -> 1.875 | I50: =IFERROR(SUMPRODUCT((Indicators!$B$5:$B$35=I$4)*Indicators!$N$5:$N$35*'Indicator Scores'!$J$5:$J$35)/SUMPRODUCT((Indicators!$B$5:$B$35=I$4)*Indicators!$N$5:$N$35*('Indicator Scores'!$J$5:$J$35>0)),0) -> 4 | J50: =IFERROR(SUMPRODUCT((Indicators!$B$5:$B$35=J$4)*Indicators!$N$5:$N$35*'Indicator Scores'!$J$5:$J$35)/SUMPRODUCT((Indicators!$B$5:$B$35=J$4)*Indicators!$N$5:$N$35*('Indicator Scores'!$J$5:$J$35>0)),0) -> 1.8 | K50: =IFERROR(SUMPRODUCT(F50:J50,INDEX('Factor Weights'!$C$5:$G$11,MATCH(D50,'Factor Weights'!$A$5:$A$11,0),0))/SUMPRODUCT((F50:J50>0)*INDEX('Factor Weights'!$C$5:$G$11,MATCH(D50,'Factor Weights'!$A$5:$A$11,0),0)),0) -> 3.185 | L50: =MAX(F50:J50) -> 4.2857143 | M50: =IF(L50>=Config!$C$13,MAX(K50,Config!$C$14),K50) -> 3.185 | N50: =IF(Config!$C$12="Weighted average",K50,IF(Config!$C$12="Weighted with floor",M50,L50)) -> 3.185 | O50: =IF(N50<Config!$D$5,"",MATCH(N50,Config!$D$5:$D$9,1)) -> 3 | P50: =IF(O50="","No data",INDEX(Config!$B$5:$B$9,O50)) -> Medium | Q50: 0 | T50: =IF(O50="","",IF(AND(S50="Y",Q50<>0),MAX(1,MIN(5,O50+MAX(-Config!$C$27,MIN(Config!$C$27,Q50)))),O50)) -> 3 | U50: =IF(T50="","No data",INDEX(Config!$B$5:$B$9,T50)) -> Medium | V50: =IF(Q50=0,"None",IF(S50="Y","Applied","Pending HO approval")) -> None | W50: =SUMPRODUCT((Indicators!$N$5:$N$35>0)*('Indicator Data'!$J$5:$J$35<>""))/SUMPRODUCT(--(Indicators!$N$5:$N$35>0)) -> 1
A51: =Entities!$A$11 -> PS-INV | B51: =INDEX(Entities!$B$5:$B$34,MATCH(A51,Entities!$A$5:$A$34,0)) -> Al-Arabi Investment Group – Palestine | C51: =INDEX(Entities!$D$5:$D$34,MATCH(A51,Entities!$A$5:$A$34,0)) -> Levant | D51: FC-05 | E51: =INDEX('Risk Taxonomy'!$B$5:$B$24,MATCH(D51,'Risk Taxonomy'!$A$5:$A$24,0)) -> Bribery and corruption | F51: =IFERROR(SUMPRODUCT((Indicators!$B$5:$B$35=F$4)*Indicators!$O$5:$O$35*'Indicator Scores'!$J$5:$J$35)/SUMPRODUCT((Indicators!$B$5:$B$35=F$4)*Indicators!$O$5:$O$35*('Indicator Scores'!$J$5:$J$35>0)),0) -> 3.4444444 | G51: =IFERROR(SUMPRODUCT((Indicators!$B$5:$B$35=G$4)*Indicators!$O$5:$O$35*'Indicator Scores'!$J$5:$J$35)/SUMPRODUCT((Indicators!$B$5:$B$35=G$4)*Indicators!$O$5:$O$35*('Indicator Scores'!$J$5:$J$35>0)),0) -> 4.2 | H51: =IFERROR(SUMPRODUCT((Indicators!$B$5:$B$35=H$4)*Indicators!$O$5:$O$35*'Indicator Scores'!$J$5:$J$35)/SUMPRODUCT((Indicators!$B$5:$B$35=H$4)*Indicators!$O$5:$O$35*('Indicator Scores'!$J$5:$J$35>0)),0) -> 2.5 | I51: =IFERROR(SUMPRODUCT((Indicators!$B$5:$B$35=I$4)*Indicators!$O$5:$O$35*'Indicator Scores'!$J$5:$J$35)/SUMPRODUCT((Indicators!$B$5:$B$35=I$4)*Indicators!$O$5:$O$35*('Indicator Scores'!$J$5:$J$35>0)),0) -> 3.8 | J51: =IFERROR(SUMPRODUCT((Indicators!$B$5:$B$35=J$4)*Indicators!$O$5:$O$35*'Indicator Scores'!$J$5:$J$35)/SUMPRODUCT((Indicators!$B$5:$B$35=J$4)*Indicators!$O$5:$O$35*('Indicator Scores'!$J$5:$J$35>0)),0) -> 3 | K51: =IFERROR(SUMPRODUCT(F51:J51,INDEX('Factor Weights'!$C$5:$G$11,MATCH(D51,'Factor Weights'!$A$5:$A$11,0),0))/SUMPRODUCT((F51:J51>0)*INDEX('Factor Weights'!$C$5:$G$11,MATCH(D51,'Factor Weights'!$A$5:$A$11,0),0)),0) -> 3.5183333 | L51: =MAX(F51:J51) -> 4.2 | M51: =IF(L51>=Config!$C$13,MAX(K51,Config!$C$14),K51) -> 3.5183333 | N51: =IF(Config!$C$12="Weighted average",K51,IF(Config!$C$12="Weighted with floor",M51,L51)) -> 3.5183333 | O51: =IF(N51<Config!$D$5,"",MATCH(N51,Config!$D$5:$D$9,1)) -> 4 | P51: =IF(O51="","No data",INDEX(Config!$B$5:$B$9,O51)) -> Medium-High | Q51: 0 | T51: =IF(O51="","",IF(AND(S51="Y",Q51<>0),MAX(1,MIN(5,O51+MAX(-Config!$C$27,MIN(Config!$C$27,Q51)))),O51)) -> 4 | U51: =IF(T51="","No data",INDEX(Config!$B$5:$B$9,T51)) -> Medium-High | V51: =IF(Q51=0,"None",IF(S51="Y","Applied","Pending HO approval")) -> None | W51: =SUMPRODUCT((Indicators!$O$5:$O$35>0)*('Indicator Data'!$J$5:$J$35<>""))/SUMPRODUCT(--(Indicators!$O$5:$O$35>0)) -> 1
A52: =Entities!$A$11 -> PS-INV | B52: =INDEX(Entities!$B$5:$B$34,MATCH(A52,Entities!$A$5:$A$34,0)) -> Al-Arabi Investment Group – Palestine | C52: =INDEX(Entities!$D$5:$D$34,MATCH(A52,Entities!$A$5:$A$34,0)) -> Levant | D52: FC-06 | E52: =INDEX('Risk Taxonomy'!$B$5:$B$24,MATCH(D52,'Risk Taxonomy'!$A$5:$A$24,0)) -> Fraud | F52: =IFERROR(SUMPRODUCT((Indicators!$B$5:$B$35=F$4)*Indicators!$P$5:$P$35*'Indicator Scores'!$J$5:$J$35)/SUMPRODUCT((Indicators!$B$5:$B$35=F$4)*Indicators!$P$5:$P$35*('Indicator Scores'!$J$5:$J$35>0)),0) -> 4 | G52: =IFERROR(SUMPRODUCT((Indicators!$B$5:$B$35=G$4)*Indicators!$P$5:$P$35*'Indicator Scores'!$J$5:$J$35)/SUMPRODUCT((Indicators!$B$5:$B$35=G$4)*Indicators!$P$5:$P$35*('Indicator Scores'!$J$5:$J$35>0)),0) -> 4.5 | H52: =IFERROR(SUMPRODUCT((Indicators!$B$5:$B$35=H$4)*Indicators!$P$5:$P$35*'Indicator Scores'!$J$5:$J$35)/SUMPRODUCT((Indicators!$B$5:$B$35=H$4)*Indicators!$P$5:$P$35*('Indicator Scores'!$J$5:$J$35>0)),0) -> 2.6 | I52: =IFERROR(SUMPRODUCT((Indicators!$B$5:$B$35=I$4)*Indicators!$P$5:$P$35*'Indicator Scores'!$J$5:$J$35)/SUMPRODUCT((Indicators!$B$5:$B$35=I$4)*Indicators!$P$5:$P$35*('Indicator Scores'!$J$5:$J$35>0)),0) -> 3.1111111 | J52: =IFERROR(SUMPRODUCT((Indicators!$B$5:$B$35=J$4)*Indicators!$P$5:$P$35*'Indicator Scores'!$J$5:$J$35)/SUMPRODUCT((Indicators!$B$5:$B$35=J$4)*Indicators!$P$5:$P$35*('Indicator Scores'!$J$5:$J$35>0)),0) -> 3.2 | K52: =IFERROR(SUMPRODUCT(F52:J52,INDEX('Factor Weights'!$C$5:$G$11,MATCH(D52,'Factor Weights'!$A$5:$A$11,0),0))/SUMPRODUCT((F52:J52>0)*INDEX('Factor Weights'!$C$5:$G$11,MATCH(D52,'Factor Weights'!$A$5:$A$11,0),0)),0) -> 3.3433333 | L52: =MAX(F52:J52) -> 4.5 | M52: =IF(L52>=Config!$C$13,MAX(K52,Config!$C$14),K52) -> 3.3433333 | N52: =IF(Config!$C$12="Weighted average",K52,IF(Config!$C$12="Weighted with floor",M52,L52)) -> 3.3433333 | O52: =IF(N52<Config!$D$5,"",MATCH(N52,Config!$D$5:$D$9,1)) -> 3 | P52: =IF(O52="","No data",INDEX(Config!$B$5:$B$9,O52)) -> Medium | Q52: 0 | T52: =IF(O52="","",IF(AND(S52="Y",Q52<>0),MAX(1,MIN(5,O52+MAX(-Config!$C$27,MIN(Config!$C$27,Q52)))),O52)) -> 3 | U52: =IF(T52="","No data",INDEX(Config!$B$5:$B$9,T52)) -> Medium | V52: =IF(Q52=0,"None",IF(S52="Y","Applied","Pending HO approval")) -> None | W52: =SUMPRODUCT((Indicators!$P$5:$P$35>0)*('Indicator Data'!$J$5:$J$35<>""))/SUMPRODUCT(--(Indicators!$P$5:$P$35>0)) -> 1
